Workbook

Sheet Summary
A1: Summary — all formulas
A3: Receipts
A4: Bank lines | B4: =COUNT(Receipts!$B$4:$B$600) -> 80
A5: Money in | B5: =SUMIF(Receipts!$B$4:$B$600,">0") -> 37328.24
A6: Money out (refunds / outflows) | B6: =SUMIF(Receipts!$B$4:$B$600,"<0") -> -409.5
A7: Money in — AUT-2025 | B7: =SUMIFS(Receipts!$B$4:$B$600,Receipts!$E$4:$E$600,"AUT-2025",Receipts!$B$4:$B$600,">0") -> 4125.25
A8: Money in — JAN-2026 | B8: =SUMIFS(Receipts!$B$4:$B$600,Receipts!$E$4:$E$600,"JAN-2026",Receipts!$B$4:$B$600,">0") -> 33202.99
A10: Allocation by tier (all terms)
A11: M — manual override [lines] | B11: =COUNTIF(Receipts!$I$4:$I$600,"M") -> 0
A12: M — manual override [£ in] | B12: =SUMIFS(Receipts!$B$4:$B$600,Receipts!$I$4:$I$600,"M",Receipts!$B$4:$B$600,">0") -> 0
A13: A — reference or verified payer alias [lines] | B13: =COUNTIF(Receipts!$I$4:$I$600,"A") -> 40
A14: A — reference or verified payer alias [£ in] | B14: =SUMIFS(Receipts!$B$4:$B$600,Receipts!$I$4:$I$600,"A",Receipts!$B$4:$B$600,">0") -> 19229.12
A15: B — unique surname in memo [lines] | B15: =COUNTIF(Receipts!$I$4:$I$600,"B") -> 29
A16: B — unique surname in memo [£ in] | B16: =SUMIFS(Receipts!$B$4:$B$600,Receipts!$I$4:$I$600,"B",Receipts!$B$4:$B$600,">0") -> 13453.87
A17: C — fuzzy / first name (review) [lines] | B17: =COUNTIF(Receipts!$I$4:$I$600,"C") -> 2
A18: C — fuzzy / first name (review) [£ in] | B18: =SUMIFS(Receipts!$B$4:$B$600,Receipts!$I$4:$I$600,"C",Receipts!$B$4:$B$600,">0") -> 694
A19: D — nothing usable or ambiguous (review) [lines] | B19: =COUNTIF(Receipts!$I$4:$I$600,"D") -> 6
A20: D — nothing usable or ambiguous (review) [£ in] | B20: =SUMIFS(Receipts!$B$4:$B$600,Receipts!$I$4:$I$600,"D",Receipts!$B$4:$B$600,">0") -> 2852.5
A21: X — reference contradicts memo (review) [lines] | B21: =COUNTIF(Receipts!$I$4:$I$600,"X") -> 3
A22: X — reference contradicts memo (review) [£ in] | B22: =SUMIFS(Receipts!$B$4:$B$600,Receipts!$I$4:$I$600,"X",Receipts!$B$4:$B$600,">0") -> 1098.75
A23: Lines allocated automatically | B23: =COUNTIF(Receipts!$H$4:$H$600,"yes") -> 69
A24: Share of lines allocated automatically | B24: =IF(COUNT(Receipts!$B$4:$B$600)=0,0,COUNTIF(Receipts!$H$4:$H$600,"yes")/COUNT(Receipts!$B$4:$B$600)) -> 0.8625
A25: JAN-2026 money in allocated | B25: =SUMIFS(Receipts!$B$4:$B$600,Receipts!$E$4:$E$600,"JAN-2026",Receipts!$H$4:$H$600,"yes",Receipts!$B$4:$B$600,">0") -> 29149.74
A26: JAN-2026 money in awaiting review | B26: =SUMIFS(Receipts!$B$4:$B$600,Receipts!$E$4:$E$600,"JAN-2026",Receipts!$H$4:$H$600,"",Receipts!$B$4:$B$600,">0") -> 4053.25
A27: Lines in Review queue | B27: =COUNTA(Review!$A$4:$A$600) -> 11
A29: Position — JAN-2026
A30: Expected income (rules) | B30: =SUM(Position!$E$5:$E$600) -> 36231.74
A31: Received (allocated) | B31: =SUM(Position!$F$5:$F$600) -> 29149.74
A32: Outstanding | B32: =SUMIF(Position!$G$5:$G$600,">0") -> 7491.5
A33: Families settled | B33: =COUNTIF(Position!$H$5:$H$600,"settled") -> 43
A34: Families part paid | B34: =COUNTIF(Position!$H$5:$H$600,"part paid") -> 5
A35: Families with nothing allocated | B35: =COUNTIF(Position!$H$5:$H$600,"unpaid") -> 11
A36: Families overpaid | B36: =COUNTIF(Position!$H$5:$H$600,"overpaid") -> 1
A37: Families flagged 'needs a look' | B37: =COUNTIF(Position!$M$5:$M$600,"?*") -> 19
A39: Rule check
A40: Children billed | B40: =COUNTIF(Children!$F$4:$F$500,"Enrolled") -> 93
A41: Invoices reproduced exactly by the fee rules | B41: =COUNTIFS(Children!$F$4:$F$500,"Enrolled",Children!$U$4:$U$500,"OK") -> 90
A43: Outstanding is overstated by whatever sits in Review and by any 2026 money tagged to AUT-2025. The AUT-2025 register is not loaded, so autumn has no position yet.

Sheet README
A1: Fee ledger — how it works
A2: Built from the pupil roster and the bank export. Health, guardian-contact and free-text pupil columns were deliberately not carried over.
A4: Where to look
A5: Position — the answer sheet. One row per family: what they owe, what came in, every receipt reference, whether it is settled. Colour-coded. Start here.
A6: Review — the only sheet that needs you. Receipts the engine would not allocate, with candidates and a reason. Decide, type the family ID into Receipts column F, re-run.
A7: Receipts — every bank line and what the engine did with it.
A8: Children / Families — the roster, and the fee each child should be charged. Difference and Check compare that with what the roster actually invoiced.
A9: Rates / Terms — the fee rules and the session counts. Change a number here and everything recalculates.
A10: Summary — headline figures.
A12: Colour key
A13: Blue text = typed in from a source file. Black = formula. Yellow fill = for you to fill in. Green = written by the engine.
A14: Green row / red row on Position = settled / owing. Amber = needs a look before you chase: a receipt sitting in Review, or money tagged to the wrong term.
... A32: Replace the bank export, run build_ledger.py then reconcile.py. Copy column F of Receipts and the alias column of Families first — manual decisions live in the workbook, not in the scripts.

Sheet Rates
A1: Fee rules — inputs (blue). Source: charity price list, January 2026 (photo supplied by user).
A3: Item | B3: Basis | C3: £ per session / per item | D3: Source / note
A4: Saturday school — 1 child | B4: per family per session | C4: 19.5 | D4: £195 per 10 sessions
A5: Saturday school — 2 siblings | B5: per family per session | C5: 34.5 | D5: £345 per 10 sessions
A6: Saturday school — 3 siblings | B6: per family per session | C6: 46 | D6: £460 per 10 sessions
A7: Saturday school — 4 siblings | B7: per family per session | C7: 57.1 | D7: £571 per 10 sessions
A9: Wednesday class — per child | B9: per child per session | C9: 16 | D9: £160 per 10 sessions; no sibling tier listed
A11: Registration fee | B11: per child, one-off at first registration | C11: 25 | D11: Price list says per family for Wednesday — treated per child here (one Wednesday child only)
A12: Supplies / annual membership | B12: per child per year | C12: 25 | D12: Price list
A14: Trial — Saturday, 1 child | B14: information only, not used in formulas | C14: 19.5 | D14: £34.50 / £46 / £57 for 2 / 3 / 4 siblings
A15: Trial — Wednesday | B15: information only, not used in formulas | C15: 16

Sheet Terms
A1: Invoicing terms — inputs (blue). Add a row per new term; the register for each term goes in Invoices.
A3: Term ID | B3: Description | C3: Saturday sessions | D3: Wednesday sessions | E3: Invoice series | F3: Register loaded? | G3: Receipts window from | H3: Receipts window to | I3: Note
A4: AUT-2025 | B4: Autumn 2025 (Sep–Dec) | C4: 11 | D4: 11 | E4: 2025-5xx / 2025-6xx | F4: No | G4: 45870 | H4: 46005 | I4: Sessions inferred from receipts (£214.50 = 11 × £19.50). Invoice register not supplied — add it to allocate autumn receipts.
A5: JAN-2026 | B5: Term starting January 2026 | C5: 21 | D5: 20 | E5: 2026-xxx | F5: Yes | G5: 46006 | H5: 46265 | I5: 21 = £409.50 ÷ £19.50. Wednesday 20 = £320 ÷ £16 (single club invoice). Confirm both with the office.

Sheet Families
A1: Families — stable key. One family can have several invoice numbers over time; the family ID never changes.
A3: Family ID | B3: Family surname(s) | C3: Children on roster | D3: Children billed (JAN-2026) | E3: Invoice no(s) JAN-2026 | F3: Bank payer alias (fill in; separate with ;) | G3: Payer names seen with a verified reference (engine) | H3: Note
A4: FAM-001 | B4: ABARCA | C4: =COUNTIF(Children!$B$4:$B$500,$A4) -> 1 | D4: =COUNTIFS(Children!$B$4:$B$500,$A4,Children!$F$4:$F$500,"Enrolled") -> 1 | E4: 2026-004 | G4: INGRID ABARCA
A5: FAM-002 | B5: ACHTERBERG | C5: =COUNTIF(Children!$B$4:$B$500,$A5) -> 1 | D5: =COUNTIFS(Children!$B$4:$B$500,$A5,Children!$F$4:$F$500,"Enrolled") -> 1 | E5: 2026-052
A6: FAM-003 | B6: ACHTERBERG-MARCHETTI | C6: =COUNTIF(Children!$B$4:$B$500,$A6) -> 1 | D6: =COUNTIFS(Children!$B$4:$B$500,$A6,Children!$F$4:$F$500,"Enrolled") -> 1 | E6: 2026-001 | G6: ADRIEN ACHTERBERG-MARCH
A7: FAM-004 | B7: ASHWORTH | C7: =COUNTIF(Children!$B$4:$B$500,$A7) -> 1 | D7: =COUNTIFS(Children!$B$4:$B$500,$A7,Children!$F$4:$F$500,"Enrolled") -> 1 | E7: 2026-005
A8: FAM-005 | B8: AUCLAIR | C8: =COUNTIF(Children!$B$4:$B$500,$A8) -> 2 | D8: =COUNTIFS(Children!$B$4:$B$500,$A8,Children!$F$4:$F$500,"Enrolled") -> 2 | E8: 2026-054 | G8: DERMOT AUCLAIR
A9: FAM-006 | B9: BAPTISTE | C9: =COUNTIF(Children!$B$4:$B$500,$A9) -> 2 | D9: =COUNTIFS(Children!$B$4:$B$500,$A9,Children!$F$4:$F$500,"Enrolled") -> 2 | E9: 2026-006 | G9: INGRID BAPTISTE
A10: FAM-007 | B10: BEAUCHAMP | C10: =COUNTIF(Children!$B$4:$B$500,$A10) -> 1 | D10: =COUNTIFS(Children!$B$4:$B$500,$A10,Children!$F$4:$F$500,"Enrolled") -> 1 | E10: 2026-007
A11: FAM-008 | B11: BELHADJ | C11: =COUNTIF(Children!$B$4:$B$500,$A11) -> 2 | D11: =COUNTIFS(Children!$B$4:$B$500,$A11,Children!$F$4:$F$500,"Enrolled") -> 2 | E11: 2026-008 | G11: GENEVIEVE BELHADJ | H11: invoice number shared with another family — 2026-008
A12: FAM-009 | B12: BELHADJ-TREVELYAN | C12: =COUNTIF(Children!$B$4:$B$500,$A12) -> 1 | D12: =COUNTIFS(Children!$B$4:$B$500,$A12,Children!$F$4:$F$500,"Enrolled") -> 1 | E12: 2026-002
A13: FAM-010 | B13: BERGQVIST | C13: =COUNTIF(Children!$B$4:$B$500,$A13) -> 2 | D13: =COUNTIFS(Children!$B$4:$B$500,$A13,Children!$F$4:$F$500,"Enrolled") -> 2 | E13: 2026-009 | G13: STEFAN BERGQVIST
A14: FAM-011 | B14: BLOMFIELD | C14: =COUNTIF(Children!$B$4:$B$500,$A14) -> 1 | D14: =COUNTIFS(Children!$B$4:$B$500,$A14,Children!$F$4:$F$500,"Enrolled") -> 1 | E14: 2026-010
A15: FAM-012 | B15: BOSANQUET | C15: =COUNTIF(Children!$B$4:$B$500,$A15) -> 2 | D15: =COUNTIFS(Children!$B$4:$B$500,$A15,Children!$F$4:$F$500,"Enrolled") -> 2 | E15: 2026-053 | G15: STEFAN BOSANQUET
A16: FAM-013 | B16: BRANNIGAN | C16: =COUNTIF(Children!$B$4:$B$500,$A16) -> 4 | D16: =COUNTIFS(Children!$B$4:$B$500,$A16,Children!$F$4:$F$500,"Enrolled") -> 4 | E16: 2026-055
A17: FAM-014 | B17: CARDOSO | C17: =COUNTIF(Children!$B$4:$B$500,$A17) -> 3 | D17: =COUNTIFS(Children!$B$4:$B$500,$A17,Children!$F$4:$F$500,"Enrolled") -> 3 | E17: 2026-011
A18: FAM-015 | B18: CASTELLANE | C18: =COUNTIF(Children!$B$4:$B$500,$A18) -> 2 | D18: =COUNTIFS(Children!$B$4:$B$500,$A18,Children!$F$4:$F$500,"Enrolled") -> 2 | E18: 2026-056 | G18: KATRIN CASTELLANE
A19: FAM-016 | B19: CHIDOZIE | C19: =COUNTIF(Children!$B$4:$B$500,$A19) -> 1 | D19: =COUNTIFS(Children!$B$4:$B$500,$A19,Children!$F$4:$F$500,"Enrolled") -> 0
A20: FAM-017 | B20: CHIDOZIE | C20: =COUNTIF(Children!$B$4:$B$500,$A20) -> 2 | D20: =COUNTIFS(Children!$B$4:$B$500,$A20,Children!$F$4:$F$500,"Enrolled") -> 2 | E20: 2026-012
A21: FAM-018 | B21: COMEAU | C21: =COUNTIF(Children!$B$4:$B$500,$A21) -> 1 | D21: =COUNTIFS(Children!$B$4:$B$500,$A21,Children!$F$4:$F$500,"Enrolled") -> 1 | E21: 2026-013 | G21: ZORA COMEAU
A22: FAM-019 | B22: DARRIEUSSECQ | C22: =COUNTIF(Children!$B$4:$B$500,$A22) -> 1 | D22: =COUNTIFS(Children!$B$4:$B$500,$A22,Children!$F$4:$F$500,"Enrolled") -> 1 | E22: 2026-014 | G22: FERGUS DARRIEUSSECQ
A23: FAM-020 | B23: DELACROIX | C23: =COUNTIF(Children!$B$4:$B$500,$A23) -> 3 | D23: =COUNTIFS(Children!$B$4:$B$500,$A23,Children!$F$4:$F$500,"Enrolled") -> 3 | E23: 2026-015 | G23: BETTINA DELACROIX
A24: FAM-021 | B24: DUPLANTIER | C24: =COUNTIF(Children!$B$4:$B$500,$A24) -> 1 | D24: =COUNTIFS(Children!$B$4:$B$500,$A24,Children!$F$4:$F$500,"Enrolled") -> 1 | E24: 2026-016
A25: FAM-022 | B25: DZIEDZIC | C25: =COUNTIF(Children!$B$4:$B$500,$A25) -> 1 | D25: =COUNTIFS(Children!$B$4:$B$500,$A25,Children!$F$4:$F$500,"Enrolled") -> 1 | E25: 2026-057 | G25: NILS DZIEDZIC
A26: FAM-023 | B26: ERIKSEN | C26: =COUNTIF(Children!$B$4:$B$500,$A26) -> 1 | D26: =COUNTIFS(Children!$B$4:$B$500,$A26,Children!$F$4:$F$500,"Enrolled") -> 1 | E26: 2026-017 | G26: INGRID ERIKSEN
A27: FAM-024 | B27: FALZON | C27: =COUNTIF(Children!$B$4:$B$500,$A27) -> 1 | D27: =COUNTIFS(Children!$B$4:$B$500,$A27,Children!$F$4:$F$500,"Enrolled") -> 1 | E27: 2026-018 | G27: VERA FALZON
A28: FAM-025 | B28: FERREIRO | C28: =COUNTIF(Children!$B$4:$B$500,$A28) -> 1 | D28: =COUNTIFS(Children!$B$4:$B$500,$A28,Children!$F$4:$F$500,"Enrolled") -> 1 | E28: 2026-058
A29: FAM-026 | B29: FITZHUGH | C29: =COUNTIF(Children!$B$4:$B$500,$A29) -> 1 | D29: =COUNTIFS(Children!$B$4:$B$500,$A29,Children!$F$4:$F$500,"Enrolled") -> 1 | E29: 2026-019 | G29: TOVE FITZHUGH
A30: FAM-027 | B30: GAILLARD | C30: =COUNTIF(Children!$B$4:$B$500,$A30) -> 1 | D30: =COUNTIFS(Children!$B$4:$B$500,$A30,Children!$F$4:$F$500,"Enrolled") -> 1 | E30: 2026-020
A31: FAM-028 | B31: GRIMALDSEN | C31: =COUNTIF(Children!$B$4:$B$500,$A31) -> 3 | D31: =COUNTIFS(Children!$B$4:$B$500,$A31,Children!$F$4:$F$500,"Enrolled") -> 3 | E31: 2026-059
A32: FAM-029 | B32: GRYNBERG | C32: =COUNTIF(Children!$B$4:$B$500,$A32) -> 1 | D32: =COUNTIFS(Children!$B$4:$B$500,$A32,Children!$F$4:$F$500,"Enrolled") -> 1 | E32: 2026-021
A33: FAM-030 | B33: HALVORSEN | C33: =COUNTIF(Children!$B$4:$B$500,$A33) -> 4 | D33: =COUNTIFS(Children!$B$4:$B$500,$A33,Children!$F$4:$F$500,"Enrolled") -> 4 | E33: 2026-022 | G33: PASCAL HALVORSEN
A34: FAM-031 | B34: HASANOVIC | C34: =COUNTIF(Children!$B$4:$B$500,$A34) -> 1 | D34: =COUNTIFS(Children!$B$4:$B$500,$A34,Children!$F$4:$F$500,"Enrolled") -> 1 | E34: 2026-060
A35: FAM-032 | B35: HOLLINGWORTH | C35: =COUNTIF(Children!$B$4:$B$500,$A35) -> 1 | D35: =COUNTIFS(Children!$B$4:$B$500,$A35,Children!$F$4:$F$500,"Enrolled") -> 1 | E35: 2026-023
A36: FAM-033 | B36: IBARRA | C36: =COUNTIF(Children!$B$4:$B$500,$A36) -> 1 | D36: =COUNTIFS(Children!$B$4:$B$500,$A36,Children!$F$4:$F$500,"Enrolled") -> 1 | E36: 2026-024 | G36: PASCAL IBARRA
A37: FAM-034 | B37: JANKOWSKI | C37: =COUNTIF(Children!$B$4:$B$500,$A37) -> 1 | D37: =COUNTIFS(Children!$B$4:$B$500,$A37,Children!$F$4:$F$500,"Enrolled") -> 1 | E37: 2026-025 | G37: JEROME JANKOWSKI
A38: FAM-035 | B38: KACZMAREK | C38: =COUNTIF(Children!$B$4:$B$500,$A38) -> 3 | D38: =COUNTIFS(Children!$B$4:$B$500,$A38,Children!$F$4:$F$500,"Enrolled") -> 3 | E38: 2026-026 | G38: ELODIE KACZMAREK
A39: FAM-036 | B39: KILBRIDE | C39: =COUNTIF(Children!$B$4:$B$500,$A39) -> 3 | D39: =COUNTIFS(Children!$B$4:$B$500,$A39,Children!$F$4:$F$500,"Enrolled") -> 3 | E39: 2026-027 | G39: GENEVIEVE KILBRIDE
A40: FAM-037 | B40: LACHAPELLE | C40: =COUNTIF(Children!$B$4:$B$500,$A40) -> 2 | D40: =COUNTIFS(Children!$B$4:$B$500,$A40,Children!$F$4:$F$500,"Enrolled") -> 2 | E40: 2026-028 | G40: CAMILLE LACHAPELLE
A41: FAM-038 | B41: LINDQVIST | C41: =COUNTIF(Children!$B$4:$B$500,$A41) -> 2 | D41: =COUNTIFS(Children!$B$4:$B$500,$A41,Children!$F$4:$F$500,"Enrolled") -> 2 | E41: 2026-029
A42: FAM-039 | B42: MAALOUF | C42: =COUNTIF(Children!$B$4:$B$500,$A42) -> 2 | D42: =COUNTIFS(Children!$B$4:$B$500,$A42,Children!$F$4:$F$500,"Enrolled") -> 2 | E42: 2026-030 | G42: GENEVIEVE MAALOUF
A43: FAM-040 | B43: MARCHETTI | C43: =COUNTIF(Children!$B$4:$B$500,$A43) -> 1 | D43: =COUNTIFS(Children!$B$4:$B$500,$A43,Children!$F$4:$F$500,"Enrolled") -> 1 | E43: 2026-031 | G43: ZORA MARCHETTI
A44: FAM-041 | B44: NAKASHIMA | C44: =COUNTIF(Children!$B$4:$B$500,$A44) -> 1 | D44: =COUNTIFS(Children!$B$4:$B$500,$A44,Children!$F$4:$F$500,"Enrolled") -> 1 | E44: 2026-032 | G44: KATRIN NAKASHIMA
A45: FAM-042 | B45: NAKASHIMA-PELLETIER | C45: =COUNTIF(Children!$B$4:$B$500,$A45) -> 2 | D45: =COUNTIFS(Children!$B$4:$B$500,$A45,Children!$F$4:$F$500,"Enrolled") -> 2 | E45: 2026-003
A46: FAM-043 | B46: NWACHUKWU | C46: =COUNTIF(Children!$B$4:$B$500,$A46) -> 1 | D46: =COUNTIFS(Children!$B$4:$B$500,$A46,Children!$F$4:$F$500,"Enrolled") -> 1 | E46: 2026-033
A47: FAM-044 | B47: OKONKWO | C47: =COUNTIF(Children!$B$4:$B$500,$A47) -> 1 | D47: =COUNTIFS(Children!$B$4:$B$500,$A47,Children!$F$4:$F$500,"Enrolled") -> 1 | E47: 2026-034
A48: FAM-045 | B48: PELLETIER | C48: =COUNTIF(Children!$B$4:$B$500,$A48) -> 1 | D48: =COUNTIFS(Children!$B$4:$B$500,$A48,Children!$F$4:$F$500,"Enrolled") -> 1 | E48: 2026-008 | H48: invoice number shared with another family — 2026-008
A49: FAM-046 | B49: PERREAULT | C49: =COUNTIF(Children!$B$4:$B$500,$A49) -> 2 | D49: =COUNTIFS(Children!$B$4:$B$500,$A49,Children!$F$4:$F$500,"Enrolled") -> 2 | E49: 2026-036
A50: FAM-047 | B50: QUILLIAM | C50: =COUNTIF(Children!$B$4:$B$500,$A50) -> 2 | D50: =COUNTIFS(Children!$B$4:$B$500,$A50,Children!$F$4:$F$500,"Enrolled") -> 2 | E50: 2026-037
A51: FAM-048 | B51: RASMUSSEN | C51: =COUNTIF(Children!$B$4:$B$500,$A51) -> 1 | D51: =COUNTIFS(Children!$B$4:$B$500,$A51,Children!$F$4:$F$500,"Enrolled") -> 1 | E51: 2026-038
A52: FAM-049 | B52: ROCHETEAU | C52: =COUNTIF(Children!$B$4:$B$500,$A52) -> 1 | D52: =COUNTIFS(Children!$B$4:$B$500,$A52,Children!$F$4:$F$500,"Enrolled") -> 1 | E52: 2026-039
A53: FAM-050 | B53: SANDOVAL | C53: =COUNTIF(Children!$B$4:$B$500,$A53) -> 2 | D53: =COUNTIFS(Children!$B$4:$B$500,$A53,Children!$F$4:$F$500,"Enrolled") -> 2 | E53: 2026-040 | G53: HUGO SANDOVAL
A54: FAM-051 | B54: SIGURDSSON | C54: =COUNTIF(Children!$B$4:$B$500,$A54) -> 2 | D54: =COUNTIFS(Children!$B$4:$B$500,$A54,Children!$F$4:$F$500,"Enrolled") -> 2 | E54: 2026-041 | G54: CAMILLE SIGURDSSON
A55: FAM-052 | B55: THIBODEAUX | C55: =COUNTIF(Children!$B$4:$B$500,$A55) -> 1 | D55: =COUNTIFS(Children!$B$4:$B$500,$A55,Children!$F$4:$F$500,"Enrolled") -> 1 | E55: 2026-042
A56: FAM-053 | B56: TREVELYAN | C56: =COUNTIF(Children!$B$4:$B$500,$A56) -> 2 | D56: =COUNTIFS(Children!$B$4:$B$500,$A56,Children!$F$4:$F$500,"Enrolled") -> 2 | E56: 2026-043
A57: FAM-054 | B57: UCHENDU | C57: =COUNTIF(Children!$B$4:$B$500,$A57) -> 1 | D57: =COUNTIFS(Children!$B$4:$B$500,$A57,Children!$F$4:$F$500,"Enrolled") -> 1 | E57: 2026-044 | G57: GENEVIEVE UCHENDU
A58: FAM-055 | B58: VANTERPOOL | C58: =COUNTIF(Children!$B$4:$B$500,$A58) -> 1 | D58: =COUNTIFS(Children!$B$4:$B$500,$A58,Children!$F$4:$F$500,"Enrolled") -> 1 | E58: 2026-045
A59: FAM-056 | B59: VILLALOBOS | C59: =COUNTIF(Children!$B$4:$B$500,$A59) -> 1 | D59: =COUNTIFS(Children!$B$4:$B$500,$A59,Children!$F$4:$F$500,"Enrolled") -> 1 | E59: 2026-046
A60: FAM-057 | B60: WENDELIN | C60: =COUNTIF(Children!$B$4:$B$500,$A60) -> 1 | D60: =COUNTIFS(Children!$B$4:$B$500,$A60,Children!$F$4:$F$500,"Enrolled") -> 1 | E60: 2026-047 | G60: MARGIT WENDELIN
A61: FAM-058 | B61: WOJCIECHOWSKI | C61: =COUNTIF(Children!$B$4:$B$500,$A61) -> 1 | D61: =COUNTIFS(Children!$B$4:$B$500,$A61,Children!$F$4:$F$500,"Enrolled") -> 1 | E61: 2026-048
A62: FAM-059 | B62: YANKOVIC | C62: =COUNTIF(Children!$B$4:$B$500,$A62) -> 1 | D62: =COUNTIFS(Children!$B$4:$B$500,$A62,Children!$F$4:$F$500,"Enrolled") -> 1 | E62: 2026-049
A63: FAM-060 | B63: ZABALA | C63: =COUNTIF(Children!$B$4:$B$500,$A63) -> 2 | D63: =COUNTIFS(Children!$B$4:$B$500,$A63,Children!$F$4:$F$500,"Enrolled") -> 2 | E63: 2026-050 | G63: NILS ZABALA
A64: FAM-061 | B64: ZIMMERLI | C64: =COUNTIF(Children!$B$4:$B$500,$A64) -> 1 | D64: =COUNTIFS(Children!$B$4:$B$500,$A64,Children!$F$4:$F$500,"Enrolled") -> 1 | E64: 2026-051

Sheet Children
A1: Children — facts per child (blue) drive the expected fee (black). 'Check' must be OK; anything else is an invoice that does not follow the rules.
A3: Child ID | B3: Family ID | C3: Surname | D3: First name | E3: Class | F3: Status | G3: Term | H3: Invoice no (roster) | I3: Sessions | J3: Sessions override | K3: Siblings billed | L3: Rate per session | M3: Tuition | N3: Discount | O3: Add-ons charged | P3: Reg fee | Q3: Supplies | R3: Expected total | S3: Invoiced on roster | T3: Difference | U3: Check | V3: Note
A4: CH-001 | B4: FAM-001 | C4: ABARCA | D4: Lorcan | E4: Saturday | F4: Enrolled | G4: JAN-2026 | H4: 2026-004 | I4: =IF($J4<>"",$J4,IF($E4="Wednesday",INDEX(Terms!$D$4:$D$5,MATCH($G4,Terms!$A$4:$A$5,0)),INDEX(Terms!$C$4:$C$5,MATCH($G4,Terms!$A$4:$A$5,0)))) -> 21 | K4: =COUNTIFS($B$4:$B$500,$B4,$F$4:$F$500,"Enrolled") -> 1 | L4: =IF($F4<>"Enrolled",0,IF($K4=0,0,IF($E4="Wednesday",Rates!$C$9,INDEX(Rates!$C$4:$C$7,MIN($K4,4))/$K4))) -> 19.5 | M4: =ROUND($L4*$I4,2) -> 409.5 | N4: 0 | P4: =IF(ISNUMBER(SEARCH("reg",$O4)),Rates!$C$11,0) -> 0 | Q4: =IF(ISNUMBER(SEARCH("supplies",$O4)),Rates!$C$12,0) -> 0 | R4: =$M4-$N4+$P4+$Q4 -> 409.5 | S4: 409.5 | T4: =ROUND($R4-$S4,2) -> 0 | U4: =IF(ABS($T4)<0.02,"OK","CHECK") -> OK | V4: roster PAID: paid
A5: CH-002 | B5: FAM-002 | C5: ACHTERBERG | D5: Eleni | E5: Saturday | F5: Enrolled | G5: JAN-2026 | H5: 2026-052 | I5: =IF($J5<>"",$J5,IF($E5="Wednesday",INDEX(Terms!$D$4:$D$5,MATCH($G5,Terms!$A$4:$A$5,0)),INDEX(Terms!$C$4:$C$5,MATCH($G5,Terms!$A$4:$A$5,0)))) -> 21 | K5: =COUNTIFS($B$4:$B$500,$B5,$F$4:$F$500,"Enrolled") -> 1 | L5: =IF($F5<>"Enrolled",0,IF($K5=0,0,IF($E5="Wednesday",Rates!$C$9,INDEX(Rates!$C$4:$C$7,MIN($K5,4))/$K5))) -> 19.5 | M5: =ROUND($L5*$I5,2) -> 409.5 | N5: 0 | O5: supplies | P5: =IF(ISNUMBER(SEARCH("reg",$O5)),Rates!$C$11,0) -> 0 | Q5: =IF(ISNUMBER(SEARCH("supplies",$O5)),Rates!$C$12,0) -> 25 | R5: =$M5-$N5+$P5+$Q5 -> 434.5 | S5: 434.5 | T5: =ROUND($R5-$S5,2) -> 0 | U5: =IF(ABS($T5)<0.02,"OK","CHECK") -> OK | V5: roster PAID: paid
A6: CH-003 | B6: FAM-003 | C6: ACHTERBERG-MARCHETTI | D6: Leocadie | E6: Saturday | F6: Enrolled | G6: JAN-2026 | H6: 2026-001 | I6: =IF($J6<>"",$J6,IF($E6="Wednesday",INDEX(Terms!$D$4:$D$5,MATCH($G6,Terms!$A$4:$A$5,0)),INDEX(Terms!$C$4:$C$5,MATCH($G6,Terms!$A$4:$A$5,0)))) -> 21 | K6: =COUNTIFS($B$4:$B$500,$B6,$F$4:$F$500,"Enrolled") -> 1 | L6: =IF($F6<>"Enrolled",0,IF($K6=0,0,IF($E6="Wednesday",Rates!$C$9,INDEX(Rates!$C$4:$C$7,MIN($K6,4))/$K6))) -> 19.5 | M6: =ROUND($L6*$I6,2) -> 409.5 | N6: 0 | O6: supplies | P6: =IF(ISNUMBER(SEARCH("reg",$O6)),Rates!$C$11,0) -> 0 | Q6: =IF(ISNUMBER(SEARCH("supplies",$O6)),Rates!$C$12,0) -> 25 | R6: =$M6-$N6+$P6+$Q6 -> 434.5 | S6: 434.5 | T6: =ROUND($R6-$S6,2) -> 0 | U6: =IF(ABS($T6)<0.02,"OK","CHECK") -> OK | V6: roster PAID: paid
A7: CH-004 | B7: FAM-004 | C7: ASHWORTH | D7: Maelys | E7: Saturday | F7: Enrolled | G7: JAN-2026 | H7: 2026-005 | I7: =IF($J7<>"",$J7,IF($E7="Wednesday",INDEX(Terms!$D$4:$D$5,MATCH($G7,Terms!$A$4:$A$5,0)),INDEX(Terms!$C$4:$C$5,MATCH($G7,Terms!$A$4:$A$5,0)))) -> 21 | K7: =COUNTIFS($B$4:$B$500,$B7,$F$4:$F$500,"Enrolled") -> 1 | L7: =IF($F7<>"Enrolled",0,IF($K7=0,0,IF($E7="Wednesday",Rates!$C$9,INDEX(Rates!$C$4:$C$7,MIN($K7,4))/$K7))) -> 19.5 | M7: =ROUND($L7*$I7,2) -> 409.5 | N7: 0 | O7: supplies | P7: =IF(ISNUMBER(SEARCH("reg",$O7)),Rates!$C$11,0) -> 0 | Q7: =IF(ISNUMBER(SEARCH("supplies",$O7)),Rates!$C$12,0) -> 25 | R7: =$M7-$N7+$P7+$Q7 -> 434.5 | S7: 434.5 | T7: =ROUND($R7-$S7,2) -> 0 | U7: =IF(ABS($T7)<0.02,"OK","CHECK") -> OK | V7: roster PAID: paid
A8: CH-005 | B8: FAM-005 | C8: AUCLAIR | D8: Halima | E8: Saturday | F8: Enrolled | G8: JAN-2026 | H8: 2026-054 | I8: =IF($J8<>"",$J8,IF($E8="Wednesday",INDEX(Terms!$D$4:$D$5,MATCH($G8,Terms!$A$4:$A$5,0)),INDEX(Terms!$C$4:$C$5,MATCH($G8,Terms!$A$4:$A$5,0)))) -> 21 | K8: =COUNTIFS($B$4:$B$500,$B8,$F$4:$F$500,"Enrolled") -> 2 | L8: =IF($F8<>"Enrolled",0,IF($K8=0,0,IF($E8="Wednesday",Rates!$C$9,INDEX(Rates!$C$4:$C$7,MIN($K8,4))/$K8))) -> 17.25 | M8: =ROUND($L8*$I8,2) -> 362.25 | N8: 0 | O8: supplies | P8: =IF(ISNUMBER(SEARCH("reg",$O8)),Rates!$C$11,0) -> 0 | Q8: =IF(ISNUMBER(SEARCH("supplies",$O8)),Rates!$C$12,0) -> 25 | R8: =$M8-$N8+$P8+$Q8 -> 387.25 | S8: 387.25 | T8: =ROUND($R8-$S8,2) -> 0 | U8: =IF(ABS($T8)<0.02,"OK","CHECK") -> OK
A9: CH-006 | B9: FAM-005 | C9: AUCLAIR | D9: Xanthe | E9: Saturday | F9: Enrolled | G9: JAN-2026 | H9: 2026-054a | I9: =IF($J9<>"",$J9,IF($E9="Wednesday",INDEX(Terms!$D$4:$D$5,MATCH($G9,Terms!$A$4:$A$5,0)),INDEX(Terms!$C$4:$C$5,MATCH($G9,Terms!$A$4:$A$5,0)))) -> 21 | K9: =COUNTIFS($B$4:$B$500,$B9,$F$4:$F$500,"Enrolled") -> 2 | L9: =IF($F9<>"Enrolled",0,IF($K9=0,0,IF($E9="Wednesday",Rates!$C$9,INDEX(Rates!$C$4:$C$7,MIN($K9,4))/$K9))) -> 17.25 | M9: =ROUND($L9*$I9,2) -> 362.25 | N9: 0 | P9: =IF(ISNUMBER(SEARCH("reg",$O9)),Rates!$C$11,0) -> 0 | Q9: =IF(ISNUMBER(SEARCH("supplies",$O9)),Rates!$C$12,0) -> 0 | R9: =$M9-$N9+$P9+$Q9 -> 362.25 | S9: 362.25 | T9: =ROUND($R9-$S9,2) -> 0 | U9: =IF(ABS($T9)<0.02,"OK","CHECK") -> OK
A10: CH-007 | B10: FAM-006 | C10: BAPTISTE | D10: Kaia | E10: Saturday | F10: Enrolled | G10: JAN-2026 | H10: 2026-006 | I10: =IF($J10<>"",$J10,IF($E10="Wednesday",INDEX(Terms!$D$4:$D$5,MATCH($G10,Terms!$A$4:$A$5,0)),INDEX(Terms!$C$4:$C$5,MATCH($G10,Terms!$A$4:$A$5,0)))) -> 21 | K10: =COUNTIFS($B$4:$B$500,$B10,$F$4:$F$500,"Enrolled") -> 2 | L10: =IF($F10<>"Enrolled",0,IF($K10=0,0,IF($E10="Wednesday",Rates!$C$9,INDEX(Rates!$C$4:$C$7,MIN($K10,4))/$K10))) -> 17.25 | M10: =ROUND($L10*$I10,2) -> 362.25 | N10: 0 | O10: supplies | P10: =IF(ISNUMBER(SEARCH("reg",$O10)),Rates!$C$11,0) -> 0 | Q10: =IF(ISNUMBER(SEARCH("supplies",$O10)),Rates!$C$12,0) -> 25 | R10: =$M10-$N10+$P10+$Q10 -> 387.25 | S10: 387.25 | T10: =ROUND($R10-$S10,2) -> 0 | U10: =IF(ABS($T10)<0.02,"OK","CHECK") -> OK
A11: CH-008 | B11: FAM-006 | C11: BAPTISTE | D11: Piero | E11: Saturday | F11: Enrolled | G11: JAN-2026 | H11: 2026-006a | I11: =IF($J11<>"",$J11,IF($E11="Wednesday",INDEX(Terms!$D$4:$D$5,MATCH($G11,Terms!$A$4:$A$5,0)),INDEX(Terms!$C$4:$C$5,MATCH($G11,Terms!$A$4:$A$5,0)))) -> 21 | K11: =COUNTIFS($B$4:$B$500,$B11,$F$4:$F$500,"Enrolled") -> 2 | L11: =IF($F11<>"Enrolled",0,IF($K11=0,0,IF($E11="Wednesday",Rates!$C$9,INDEX(Rates!$C$4:$C$7,MIN($K11,4))/$K11))) -> 17.25 | M11: =ROUND($L11*$I11,2) -> 362.25 | N11: 0 | O11: supplies | P11: =IF(ISNUMBER(SEARCH("reg",$O11)),Rates!$C$11,0) -> 0 | Q11: =IF(ISNUMBER(SEARCH("supplies",$O11)),Rates!$C$12,0) -> 25 | R11: =$M11-$N11+$P11+$Q11 -> 387.25 | S11: 387.25 | T11: =ROUND($R11-$S11,2) -> 0 | U11: =IF(ABS($T11)<0.02,"OK","CHECK") -> OK | V11: roster PAID: paid
A12: CH-009 | B12: FAM-007 | C12: BEAUCHAMP | D12: Anselm | E12: Saturday | F12: Enrolled | G12: JAN-2026 | H12: 2026-007 | I12: =IF($J12<>"",$J12,IF($E12="Wednesday",INDEX(Terms!$D$4:$D$5,MATCH($G12,Terms!$A$4:$A$5,0)),INDEX(Terms!$C$4:$C$5,MATCH($G12,Terms!$A$4:$A$5,0)))) -> 21 | K12: =COUNTIFS($B$4:$B$500,$B12,$F$4:$F$500,"Enrolled") -> 1 | L12: =IF($F12<>"Enrolled",0,IF($K12=0,0,IF($E12="Wednesday",Rates!$C$9,INDEX(Rates!$C$4:$C$7,MIN($K12,4))/$K12))) -> 19.5 | M12: =ROUND($L12*$I12,2) -> 409.5 | N12: 0 | O12: supplies | P12: =IF(ISNUMBER(SEARCH("reg",$O12)),Rates!$C$11,0) -> 0 | Q12: =IF(ISNUMBER(SEARCH("supplies",$O12)),Rates!$C$12,0) -> 25 | R12: =$M12-$N12+$P12+$Q12 -> 434.5 | S12: 434.5 | T12: =ROUND($R12-$S12,2) -> 0 | U12: =IF(ABS($T12)<0.02,"OK","CHECK") -> OK | V12: roster PAID: part paid
A13: CH-010 | B13: FAM-008 | C13: BELHADJ | D13: Celestine | E13: Saturday | F13: Enrolled | G13: JAN-2026 | H13: 2026-008 | I13: =IF($J13<>"",$J13,IF($E13="Wednesday",INDEX(Terms!$D$4:$D$5,MATCH($G13,Terms!$A$4:$A$5,0)),INDEX(Terms!$C$4:$C$5,MATCH($G13,Terms!$A$4:$A$5,0)))) -> 21 | K13: =COUNTIFS($B$4:$B$500,$B13,$F$4:$F$500,"Enrolled") -> 2 | L13: =IF($F13<>"Enrolled",0,IF($K13=0,0,IF($E13="Wednesday",Rates!$C$9,INDEX(Rates!$C$4:$C$7,MIN($K13,4))/$K13))) -> 17.25 | M13: =ROUND($L13*$I13,2) -> 362.25 | N13: 0 | O13: supplies | P13: =IF(ISNUMBER(SEARCH("reg",$O13)),Rates!$C$11,0) -> 0 | Q13: =IF(ISNUMBER(SEARCH("supplies",$O13)),Rates!$C$12,0) -> 25 | R13: =$M13-$N13+$P13+$Q13 -> 387.25 | S13: 387.25 | T13: =ROUND($R13-$S13,2) -> 0 | U13: =IF(ABS($T13)<0.02,"OK","CHECK") -> OK
A14: CH-011 | B14: FAM-008 | C14: BELHADJ | D14: Gaspard | E14: Saturday | F14: Enrolled | G14: JAN-2026 | H14: 2026-008a | I14: =IF($J14<>"",$J14,IF($E14="Wednesday",INDEX(Terms!$D$4:$D$5,MATCH($G14,Terms!$A$4:$A$5,0)),INDEX(Terms!$C$4:$C$5,MATCH($G14,Terms!$A$4:$A$5,0)))) -> 21 | K14: =COUNTIFS($B$4:$B$500,$B14,$F$4:$F$500,"Enrolled") -> 2 | L14: =IF($F14<>"Enrolled",0,IF($K14=0,0,IF($E14="Wednesday",Rates!$C$9,INDEX(Rates!$C$4:$C$7,MIN($K14,4))/$K14))) -> 17.25 | M14: =ROUND($L14*$I14,2) -> 362.25 | N14: 0 | O14: supplies | P14: =IF(ISNUMBER(SEARCH("reg",$O14)),Rates!$C$11,0) -> 0 | Q14: =IF(ISNUMBER(SEARCH("supplies",$O14)),Rates!$C$12,0) -> 25 | R14: =$M14-$N14+$P14+$Q14 -> 387.25 | S14: 387.25 | T14: =ROUND($R14-$S14,2) -> 0 | U14: =IF(ABS($T14)<0.02,"OK","CHECK") -> OK | V14: roster PAID: paid
A15: CH-012 | B15: FAM-009 | C15: BELHADJ-TREVELYAN | D15: Beatriz | E15: Saturday | F15: Enrolled | G15: JAN-2026 | H15: 2026-002 | I15: =IF($J15<>"",$J15,IF($E15="Wednesday",INDEX(Terms!$D$4:$D$5,MATCH($G15,Terms!$A$4:$A$5,0)),INDEX(Terms!$C$4:$C$5,MATCH($G15,Terms!$A$4:$A$5,0)))) -> 21 | K15: =COUNTIFS($B$4:$B$500,$B15,$F$4:$F$500,"Enrolled") -> 1 | L15: =IF($F15<>"Enrolled",0,IF($K15=0,0,IF($E15="Wednesday",Rates!$C$9,INDEX(Rates!$C$4:$C$7,MIN($K15,4))/$K15))) -> 19.5 | M15: =ROUND($L15*$I15,2) -> 409.5 | N15: 0 | O15: supplies | P15: =IF(ISNUMBER(SEARCH("reg",$O15)),Rates!$C$11,0) -> 0 | Q15: =IF(ISNUMBER(SEARCH("supplies",$O15)),Rates!$C$12,0) -> 25 | R15: =$M15-$N15+$P15+$Q15 -> 434.5 | S15: 434.5 | T15: =ROUND($R15-$S15,2) -> 0 | U15: =IF(ABS($T15)<0.02,"OK","CHECK") -> OK | V15: roster PAID: part paid
A16: CH-013 | B16: FAM-010 | C16: BERGQVIST | D16: Rune | E16: Saturday | F16: Enrolled | G16: JAN-2026 | H16: 2026-009 | I16: =IF($J16<>"",$J16,IF($E16="Wednesday",INDEX(Terms!$D$4:$D$5,MATCH($G16,Terms!$A$4:$A$5,0)),INDEX(Terms!$C$4:$C$5,MATCH($G16,Terms!$A$4:$A$5,0)))) -> 21 | K16: =COUNTIFS($B$4:$B$500,$B16,$F$4:$F$500,"Enrolled") -> 2 | L16: =IF($F16<>"Enrolled",0,IF($K16=0,0,IF($E16="Wednesday",Rates!$C$9,INDEX(Rates!$C$4:$C$7,MIN($K16,4))/$K16))) -> 17.25 | M16: =ROUND($L16*$I16,2) -> 362.25 | N16: 0 | O16: supplies | P16: =IF(ISNUMBER(SEARCH("reg",$O16)),Rates!$C$11,0) -> 0 | Q16: =IF(ISNUMBER(SEARCH("supplies",$O16)),Rates!$C$12,0) -> 25 | R16: =$M16-$N16+$P16+$Q16 -> 387.25 | S16: 387.25 | T16: =ROUND($R16-$S16,2) -> 0 | U16: =IF(ABS($T16)<0.02,"OK","CHECK") -> OK | V16: roster PAID: paid
A17: CH-014 | B17: FAM-010 | C17: BERGQVIST | D17: Tamsin | E17: Saturday | F17: Enrolled | G17: JAN-2026 | H17: 2026-009a | I17: =IF($J17<>"",$J17,IF($E17="Wednesday",INDEX(Terms!$D$4:$D$5,MATCH($G17,Terms!$A$4:$A$5,0)),INDEX(Terms!$C$4:$C$5,MATCH($G17,Terms!$A$4:$A$5,0)))) -> 21 | K17: =COUNTIFS($B$4:$B$500,$B17,$F$4:$F$500,"Enrolled") -> 2 | L17: =IF($F17<>"Enrolled",0,IF($K17=0,0,IF($E17="Wednesday",Rates!$C$9,INDEX(Rates!$C$4:$C$7,MIN($K17,4))/$K17))) -> 17.25 | M17: =ROUND($L17*$I17,2) -> 362.25 | N17: 30 | P17: =IF(ISNUMBER(SEARCH("reg",$O17)),Rates!$C$11,0) -> 0 | Q17: =IF(ISNUMBER(SEARCH("supplies",$O17)),Rates!$C$12,0) -> 0 | R17: =$M17-$N17+$P17+$Q17 -> 332.25 | S17: 332.25 | T17: =ROUND($R17-$S17,2) -> 0 | U17: =IF(ABS($T17)<0.02,"OK","CHECK") -> OK | V17: roster PAID: paid
A18: CH-015 | B18: FAM-011 | C18: BLOMFIELD | D18: Solveig | E18: Saturday | F18: Enrolled | G18: JAN-2026 | H18: 2026-010 | I18: =IF($J18<>"",$J18,IF($E18="Wednesday",INDEX(Terms!$D$4:$D$5,MATCH($G18,Terms!$A$4:$A$5,0)),INDEX(Terms!$C$4:$C$5,MATCH($G18,Terms!$A$4:$A$5,0)))) -> 21 | K18: =COUNTIFS($B$4:$B$500,$B18,$F$4:$F$500,"Enrolled") -> 1 | L18: =IF($F18<>"Enrolled",0,IF($K18=0,0,IF($E18="Wednesday",Rates!$C$9,INDEX(Rates!$C$4:$C$7,MIN($K18,4))/$K18))) -> 19.5 | M18: =ROUND($L18*$I18,2) -> 409.5 | N18: 0 | O18: supplies | P18: =IF(ISNUMBER(SEARCH("reg",$O18)),Rates!$C$11,0) -> 0 | Q18: =IF(ISNUMBER(SEARCH("supplies",$O18)),Rates!$C$12,0) -> 25 | R18: =$M18-$N18+$P18+$Q18 -> 434.5 | S18: 434.5 | T18: =ROUND($R18-$S18,2) -> 0 | U18: =IF(ABS($T18)<0.02,"OK","CHECK") -> OK
A19: CH-016 | B19: FAM-012 | C19: BOSANQUET | D19: Hektor | E19: Saturday | F19: Enrolled | G19: JAN-2026 | H19: 2026-053a | I19: =IF($J19<>"",$J19,IF($E19="Wednesday",INDEX(Terms!$D$4:$D$5,MATCH($G19,Terms!$A$4:$A$5,0)),INDEX(Terms!$C$4:$C$5,MATCH($G19,Terms!$A$4:$A$5,0)))) -> 21 | K19: =COUNTIFS($B$4:$B$500,$B19,$F$4:$F$500,"Enrolled") -> 2 | L19: =IF($F19<>"Enrolled",0,IF($K19=0,0,IF($E19="Wednesday",Rates!$C$9,INDEX(Rates!$C$4:$C$7,MIN($K19,4))/$K19))) -> 17.25 | M19: =ROUND($L19*$I19,2) -> 362.25 | N19: 0 | O19: supplies | P19: =IF(ISNUMBER(SEARCH("reg",$O19)),Rates!$C$11,0) -> 0 | Q19: =IF(ISNUMBER(SEARCH("supplies",$O19)),Rates!$C$12,0) -> 25 | R19: =$M19-$N19+$P19+$Q19 -> 387.25 | S19: 387.25 | T19: =ROUND($R19-$S19,2) -> 0 | U19: =IF(ABS($T19)<0.02,"OK","CHECK") -> OK
A20: CH-017 | B20: FAM-012 | C20: BOSANQUET | D20: Rune | E20: Saturday | F20: Enrolled | G20: JAN-2026 | H20: 2026-053 | I20: =IF($J20<>"",$J20,IF($E20="Wednesday",INDEX(Terms!$D$4:$D$5,MATCH($G20,Terms!$A$4:$A$5,0)),INDEX(Terms!$C$4:$C$5,MATCH($G20,Terms!$A$4:$A$5,0)))) -> 21 | K20: =COUNTIFS($B$4:$B$500,$B20,$F$4:$F$500,"Enrolled") -> 2 | L20: =IF($F20<>"Enrolled",0,IF($K20=0,0,IF($E20="Wednesday",Rates!$C$9,INDEX(Rates!$C$4:$C$7,MIN($K20,4))/$K20))) -> 17.25 | M20: =ROUND($L20*$I20,2) -> 362.25 | N20: 0 | P20: =IF(ISNUMBER(SEARCH("reg",$O20)),Rates!$C$11,0) -> 0 | Q20: =IF(ISNUMBER(SEARCH("supplies",$O20)),Rates!$C$12,0) -> 0 | R20: =$M20-$N20+$P20+$Q20 -> 362.25 | S20: 362.25 | T20: =ROUND($R20-$S20,2) -> 0 | U20: =IF(ABS($T20)<0.02,"OK","CHECK") -> OK | V20: roster PAID: part paid
A21: CH-018 | B21: FAM-013 | C21: BRANNIGAN | D21: Dario | E21: Saturday | F21: Enrolled | G21: JAN-2026 | H21: 2026-055 | I21: =IF($J21<>"",$J21,IF($E21="Wednesday",INDEX(Terms!$D$4:$D$5,MATCH($G21,Terms!$A$4:$A$5,0)),INDEX(Terms!$C$4:$C$5,MATCH($G21,Terms!$A$4:$A$5,0)))) -> 21 | K21: =COUNTIFS($B$4:$B$500,$B21,$F$4:$F$500,"Enrolled") -> 4 | L21: =IF($F21<>"Enrolled",0,IF($K21=0,0,IF($E21="Wednesday",Rates!$C$9,INDEX(Rates!$C$4:$C$7,MIN($K21,4))/$K21))) -> 14.275 | M21: =ROUND($L21*$I21,2) -> 299.78 | N21: 0 | P21: =IF(ISNUMBER(SEARCH("reg",$O21)),Rates!$C$11,0) -> 0 | Q21: =IF(ISNUMBER(SEARCH("supplies",$O21)),Rates!$C$12,0) -> 0 | R21: =$M21-$N21+$P21+$Q21 -> 299.78 | S21: 299.78 | T21: =ROUND($R21-$S21,2) -> 0 | U21: =IF(ABS($T21)<0.02,"OK","CHECK") -> OK | V21: roster PAID: paid
A22: CH-019 | B22: FAM-013 | C22: BRANNIGAN | D22: Giulia | E22: Saturday | F22: Enrolled | G22: JAN-2026 | H22: 2026-055 | I22: =IF($J22<>"",$J22,IF($E22="Wednesday",INDEX(Terms!$D$4:$D$5,MATCH($G22,Terms!$A$4:$A$5,0)),INDEX(Terms!$C$4:$C$5,MATCH($G22,Terms!$A$4:$A$5,0)))) -> 21 | K22: =COUNTIFS($B$4:$B$500,$B22,$F$4:$F$500,"Enrolled") -> 4 | L22: =IF($F22<>"Enrolled",0,IF($K22=0,0,IF($E22="Wednesday",Rates!$C$9,INDEX(Rates!$C$4:$C$7,MIN($K22,4))/$K22))) -> 14.275 | M22: =ROUND($L22*$I22,2) -> 299.78 | N22: 0 | P22: =IF(ISNUMBER(SEARCH("reg",$O22)),Rates!$C$11,0) -> 0 | Q22: =IF(ISNUMBER(SEARCH("supplies",$O22)),Rates!$C$12,0) -> 0 | R22: =$M22-$N22+$P22+$Q22 -> 299.78 | S22: 299.78 | T22: =ROUND($R22-$S22,2) -> 0 | U22: =IF(ABS($T22)<0.02,"OK","CHECK") -> OK | V22: roster PAID: paid
A23: CH-020 | B23: FAM-013 | C23: BRANNIGAN | D23: Juniper | E23: Saturday | F23: Enrolled | G23: JAN-2026 | H23: 2026-055a | I23: =IF($J23<>"",$J23,IF($E23="Wednesday",INDEX(Terms!$D$4:$D$5,MATCH($G23,Terms!$A$4:$A$5,0)),INDEX(Terms!$C$4:$C$5,MATCH($G23,Terms!$A$4:$A$5,0)))) -> 21 | K23: =COUNTIFS($B$4:$B$500,$B23,$F$4:$F$500,"Enrolled") -> 4 | L23: =IF($F23<>"Enrolled",0,IF($K23=0,0,IF($E23="Wednesday",Rates!$C$9,INDEX(Rates!$C$4:$C$7,MIN($K23,4))/$K23))) -> 14.275 | M23: =ROUND($L23*$I23,2) -> 299.78 | N23: 0 | O23: reg, supplies | P23: =IF(ISNUMBER(SEARCH("reg",$O23)),Rates!$C$11,0) -> 25 | Q23: =IF(ISNUMBER(SEARCH("supplies",$O23)),Rates!$C$12,0) -> 25 | R23: =$M23-$N23+$P23+$Q23 -> 349.78 | S23: 349.78 | T23: =ROUND($R23-$S23,2) -> 0 | U23: =IF(ABS($T23)<0.02,"OK","CHECK") -> OK
A24: CH-021 | B24: FAM-013 | C24: BRANNIGAN | D24: Ndidi | E24: Saturday | F24: Enrolled | G24: JAN-2026 | H24: 2026-055 | I24: =IF($J24<>"",$J24,IF($E24="Wednesday",INDEX(Terms!$D$4:$D$5,MATCH($G24,Terms!$A$4:$A$5,0)),INDEX(Terms!$C$4:$C$5,MATCH($G24,Terms!$A$4:$A$5,0)))) -> 21 | K24: =COUNTIFS($B$4:$B$500,$B24,$F$4:$F$500,"Enrolled") -> 4 | L24: =IF($F24<>"Enrolled",0,IF($K24=0,0,IF($E24="Wednesday",Rates!$C$9,INDEX(Rates!$C$4:$C$7,MIN($K24,4))/$K24))) -> 14.275 | M24: =ROUND($L24*$I24,2) -> 299.78 | N24: 0 | P24: =IF(ISNUMBER(SEARCH("reg",$O24)),Rates!$C$11,0) -> 0 | Q24: =IF(ISNUMBER(SEARCH("supplies",$O24)),Rates!$C$12,0) -> 0 | R24: =$M24-$N24+$P24+$Q24 -> 299.78 | S24: 299.78 | T24: =ROUND($R24-$S24,2) -> 0 | U24: =IF(ABS($T24)<0.02,"OK","CHECK") -> OK | V24: roster PAID: paid
A25: CH-022 | B25: FAM-014 | C25: CARDOSO | D25: Caspian | E25: Saturday | F25: Enrolled | G25: JAN-2026 | H25: 2026-011 | I25: =IF($J25<>"",$J25,IF($E25="Wednesday",INDEX(Terms!$D$4:$D$5,MATCH($G25,Terms!$A$4:$A$5,0)),INDEX(Terms!$C$4:$C$5,MATCH($G25,Terms!$A$4:$A$5,0)))) -> 21 | K25: =COUNTIFS($B$4:$B$500,$B25,$F$4:$F$500,"Enrolled") -> 3 | L25: =IF($F25<>"Enrolled",0,IF($K25=0,0,IF($E25="Wednesday",Rates!$C$9,INDEX(Rates!$C$4:$C$7,MIN($K25,4))/$K25))) -> 15.333333 | M25: =ROUND($L25*$I25,2) -> 322 | N25: 0 | O25: supplies | P25: =IF(ISNUMBER(SEARCH("reg",$O25)),Rates!$C$11,0) -> 0 | Q25: =IF(ISNUMBER(SEARCH("supplies",$O25)),Rates!$C$12,0) -> 25 | R25: =$M25-$N25+$P25+$Q25 -> 347 | S25: 347 | T25: =ROUND($R25-$S25,2) -> 0 | U25: =IF(ABS($T25)<0.02,"OK","CHECK") -> OK | V25: roster PAID: paid
A26: CH-023 | B26: FAM-014 | C26: CARDOSO | D26: Dario | E26: Saturday | F26: Enrolled | G26: JAN-2026 | H26: 2026-011a | I26: =IF($J26<>"",$J26,IF($E26="Wednesday",INDEX(Terms!$D$4:$D$5,MATCH($G26,Terms!$A$4:$A$5,0)),INDEX(Terms!$C$4:$C$5,MATCH($G26,Terms!$A$4:$A$5,0)))) -> 21 | K26: =COUNTIFS($B$4:$B$500,$B26,$F$4:$F$500,"Enrolled") -> 3 | L26: =IF($F26<>"Enrolled",0,IF($K26=0,0,IF($E26="Wednesday",Rates!$C$9,INDEX(Rates!$C$4:$C$7,MIN($K26,4))/$K26))) -> 15.333333 | M26: =ROUND($L26*$I26,2) -> 322 | N26: 0 | O26: supplies | P26: =IF(ISNUMBER(SEARCH("reg",$O26)),Rates!$C$11,0) -> 0 | Q26: =IF(ISNUMBER(SEARCH("supplies",$O26)),Rates!$C$12,0) -> 25 | R26: =$M26-$N26+$P26+$Q26 -> 347 | S26: 347 | T26: =ROUND($R26-$S26,2) -> 0 | U26: =IF(ABS($T26)<0.02,"OK","CHECK") -> OK | V26: roster PAID: paid
A27: CH-024 | B27: FAM-014 | C27: CARDOSO | D27: Eleni | E27: Saturday | F27: Enrolled | G27: JAN-2026 | H27: 2026-011 | I27: =IF($J27<>"",$J27,IF($E27="Wednesday",INDEX(Terms!$D$4:$D$5,MATCH($G27,Terms!$A$4:$A$5,0)),INDEX(Terms!$C$4:$C$5,MATCH($G27,Terms!$A$4:$A$5,0)))) -> 21 | K27: =COUNTIFS($B$4:$B$500,$B27,$F$4:$F$500,"Enrolled") -> 3 | L27: =IF($F27<>"Enrolled",0,IF($K27=0,0,IF($E27="Wednesday",Rates!$C$9,INDEX(Rates!$C$4:$C$7,MIN($K27,4))/$K27))) -> 15.333333 | M27: =ROUND($L27*$I27,2) -> 322 | N27: 0 | O27: supplies | P27: =IF(ISNUMBER(SEARCH("reg",$O27)),Rates!$C$11,0) -> 0 | Q27: =IF(ISNUMBER(SEARCH("supplies",$O27)),Rates!$C$12,0) -> 25 | R27: =$M27-$N27+$P27+$Q27 -> 347 | S27: 347 | T27: =ROUND($R27-$S27,2) -> 0 | U27: =IF(ABS($T27)<0.02,"OK","CHECK") -> OK
A28: CH-025 | B28: FAM-015 | C28: CASTELLANE | D28: Quentin | E28: Saturday | F28: Enrolled | G28: JAN-2026 | H28: 2026-056a | I28: =IF($J28<>"",$J28,IF($E28="Wednesday",INDEX(Terms!$D$4:$D$5,MATCH($G28,Terms!$A$4:$A$5,0)),INDEX(Terms!$C$4:$C$5,MATCH($G28,Terms!$A$4:$A$5,0)))) -> 21 | K28: =COUNTIFS($B$4:$B$500,$B28,$F$4:$F$500,"Enrolled") -> 2 | L28: =IF($F28<>"Enrolled",0,IF($K28=0,0,IF($E28="Wednesday",Rates!$C$9,INDEX(Rates!$C$4:$C$7,MIN($K28,4))/$K28))) -> 17.25 | M28: =ROUND($L28*$I28,2) -> 362.25 | N28: 0 | O28: supplies | P28: =IF(ISNUMBER(SEARCH("reg",$O28)),Rates!$C$11,0) -> 0 | Q28: =IF(ISNUMBER(SEARCH("supplies",$O28)),Rates!$C$12,0) -> 25 | R28: =$M28-$N28+$P28+$Q28 -> 387.25 | S28: 387.25 | T28: =ROUND($R28-$S28,2) -> 0 | U28: =IF(ABS($T28)<0.02,"OK","CHECK") -> OK | V28: roster PAID: paid
A29: CH-026 | B29: FAM-015 | C29: CASTELLANE | D29: Zephyr | E29: Saturday | F29: Enrolled | G29: JAN-2026 | H29: 2026-056 | I29: =IF($J29<>"",$J29,IF($E29="Wednesday",INDEX(Terms!$D$4:$D$5,MATCH($G29,Terms!$A$4:$A$5,0)),INDEX(Terms!$C$4:$C$5,MATCH($G29,Terms!$A$4:$A$5,0)))) -> 21 | K29: =COUNTIFS($B$4:$B$500,$B29,$F$4:$F$500,"Enrolled") -> 2 | L29: =IF($F29<>"Enrolled",0,IF($K29=0,0,IF($E29="Wednesday",Rates!$C$9,INDEX(Rates!$C$4:$C$7,MIN($K29,4))/$K29))) -> 17.25 | M29: =ROUND($L29*$I29,2) -> 362.25 | N29: 0 | O29: supplies | P29: =IF(ISNUMBER(SEARCH("reg",$O29)),Rates!$C$11,0) -> 0 | Q29: =IF(ISNUMBER(SEARCH("supplies",$O29)),Rates!$C$12,0) -> 25 | R29: =$M29-$N29+$P29+$Q29 -> 387.25 | S29: 387.25 | T29: =ROUND($R29-$S29,2) -> 0 | U29: =IF(ABS($T29)<0.02,"OK","CHECK") -> OK | V29: roster PAID: part paid
A30: CH-027 | B30: FAM-016 | C30: CHIDOZIE | D30: Amara | E30: Saturday | F30: Not invoiced | G30: JAN-2026 | I30: =IF($J30<>"",$J30,IF($E30="Wednesday",INDEX(Terms!$D$4:$D$5,MATCH($G30,Terms!$A$4:$A$5,0)),INDEX(Terms!$C$4:$C$5,MATCH($G30,Terms!$A$4:$A$5,0)))) -> 21 | K30: =COUNTIFS($B$4:$B$500,$B30,$F$4:$F$500,"Enrolled") -> 0 | L30: =IF($F30<>"Enrolled",0,IF($K30=0,0,IF($E30="Wednesday",Rates!$C$9,INDEX(Rates!$C$4:$C$7,MIN($K30,4))/$K30))) -> 0 | M30: =ROUND($L30*$I30,2) -> 0 | N30: 0 | O30: supplies | P30: =IF(ISNUMBER(SEARCH("reg",$O30)),Rates!$C$11,0) -> 0 | Q30: =IF(ISNUMBER(SEARCH("supplies",$O30)),Rates!$C$12,0) -> 25 | R30: =$M30-$N30+$P30+$Q30 -> 25 | S30: 25 | T30: =ROUND($R30-$S30,2) -> 0 | U30: =IF(ABS($T30)<0.02,"OK","CHECK") -> OK | V30: roster PAID: part paid
A31: CH-028 | B31: FAM-017 | C31: CHIDOZIE | D31: Delphine | E31: Saturday | F31: Enrolled | G31: JAN-2026 | H31: 2026-012 | I31: =IF($J31<>"",$J31,IF($E31="Wednesday",INDEX(Terms!$D$4:$D$5,MATCH($G31,Terms!$A$4:$A$5,0)),INDEX(Terms!$C$4:$C$5,MATCH($G31,Terms!$A$4:$A$5,0)))) -> 21 | K31: =COUNTIFS($B$4:$B$500,$B31,$F$4:$F$500,"Enrolled") -> 2 | L31: =IF($F31<>"Enrolled",0,IF($K31=0,0,IF($E31="Wednesday",Rates!$C$9,INDEX(Rates!$C$4:$C$7,MIN($K31,4))/$K31))) -> 17.25 | M31: =ROUND($L31*$I31,2) -> 362.25 | N31: 0 | O31: supplies | P31: =IF(ISNUMBER(SEARCH("reg",$O31)),Rates!$C$11,0) -> 0 | Q31: =IF(ISNUMBER(SEARCH("supplies",$O31)),Rates!$C$12,0) -> 25 | R31: =$M31-$N31+$P31+$Q31 -> 387.25 | S31: 347 | T31: =ROUND($R31-$S31,2) -> 40.25 | U31: =IF(ABS($T31)<0.02,"OK","CHECK") -> CHECK | V31: roster PAID: part paid
A32: CH-029 | B32: FAM-017 | C32: CHIDOZIE | D32: Zephyr | E32: Saturday | F32: Enrolled | G32: JAN-2026 | H32: 2026-012a | I32: =IF($J32<>"",$J32,IF($E32="Wednesday",INDEX(Terms!$D$4:$D$5,MATCH($G32,Terms!$A$4:$A$5,0)),INDEX(Terms!$C$4:$C$5,MATCH($G32,Terms!$A$4:$A$5,0)))) -> 21 | K32: =COUNTIFS($B$4:$B$500,$B32,$F$4:$F$500,"Enrolled") -> 2 | L32: =IF($F32<>"Enrolled",0,IF($K32=0,0,IF($E32="Wednesday",Rates!$C$9,INDEX(Rates!$C$4:$C$7,MIN($K32,4))/$K32))) -> 17.25 | M32: =ROUND($L32*$I32,2) -> 362.25 | N32: 0 | O32: supplies | P32: =IF(ISNUMBER(SEARCH("reg",$O32)),Rates!$C$11,0) -> 0 | Q32: =IF(ISNUMBER(SEARCH("supplies",$O32)),Rates!$C$12,0) -> 25 | R32: =$M32-$N32+$P32+$Q32 -> 387.25 | S32: 347 | T32: =ROUND($R32-$S32,2) -> 40.25 | U32: =IF(ABS($T32)<0.02,"OK","CHECK") -> CHECK | V32: roster PAID: paid
A33: CH-030 | B33: FAM-018 | C33: COMEAU | D33: Olamide | E33: Saturday | F33: Enrolled | G33: JAN-2026 | H33: 2026-013 | I33: =IF($J33<>"",$J33,IF($E33="Wednesday",INDEX(Terms!$D$4:$D$5,MATCH($G33,Terms!$A$4:$A$5,0)),INDEX(Terms!$C$4:$C$5,MATCH($G33,Terms!$A$4:$A$5,0)))) -> 21 | K33: =COUNTIFS($B$4:$B$500,$B33,$F$4:$F$500,"Enrolled") -> 1 | L33: =IF($F33<>"Enrolled",0,IF($K33=0,0,IF($E33="Wednesday",Rates!$C$9,INDEX(Rates!$C$4:$C$7,MIN($K33,4))/$K33))) -> 19.5 | M33: =ROUND($L33*$I33,2) -> 409.5 | N33: 0 | P33: =IF(ISNUMBER(SEARCH("reg",$O33)),Rates!$C$11,0) -> 0 | Q33: =IF(ISNUMBER(SEARCH("supplies",$O33)),Rates!$C$12,0) -> 0 | R33: =$M33-$N33+$P33+$Q33 -> 409.5 | S33: 409.5 | T33: =ROUND($R33-$S33,2) -> 0 | U33: =IF(ABS($T33)<0.02,"OK","CHECK") -> OK | V33: roster PAID: paid
A34: CH-031 | B34: FAM-019 | C34: DARRIEUSSECQ | D34: Valentin | E34: Saturday | F34: Enrolled | G34: JAN-2026 | H34: 2026-014 | I34: =IF($J34<>"",$J34,IF($E34="Wednesday",INDEX(Terms!$D$4:$D$5,MATCH($G34,Terms!$A$4:$A$5,0)),INDEX(Terms!$C$4:$C$5,MATCH($G34,Terms!$A$4:$A$5,0)))) -> 21 | K34: =COUNTIFS($B$4:$B$500,$B34,$F$4:$F$500,"Enrolled") -> 1 | L34: =IF($F34<>"Enrolled",0,IF($K34=0,0,IF($E34="Wednesday",Rates!$C$9,INDEX(Rates!$C$4:$C$7,MIN($K34,4))/$K34))) -> 19.5 | M34: =ROUND($L34*$I34,2) -> 409.5 | N34: 0 | O34: supplies | P34: =IF(ISNUMBER(SEARCH("reg",$O34)),Rates!$C$11,0) -> 0 | Q34: =IF(ISNUMBER(SEARCH("supplies",$O34)),Rates!$C$12,0) -> 25 | R34: =$M34-$N34+$P34+$Q34 -> 434.5 | S34: 434.5 | T34: =ROUND($R34-$S34,2) -> 0 | U34: =IF(ABS($T34)<0.02,"OK","CHECK") -> OK
A35: CH-032 | B35: FAM-020 | C35: DELACROIX | D35: Fabienne | E35: Saturday | F35: Enrolled | G35: JAN-2026 | H35: 2026-015 | I35: =IF($J35<>"",$J35,IF($E35="Wednesday",INDEX(Terms!$D$4:$D$5,MATCH($G35,Terms!$A$4:$A$5,0)),INDEX(Terms!$C$4:$C$5,MATCH($G35,Terms!$A$4:$A$5,0)))) -> 21 | K35: =COUNTIFS($B$4:$B$500,$B35,$F$4:$F$500,"Enrolled") -> 3 | L35: =IF($F35<>"Enrolled",0,IF($K35=0,0,IF($E35="Wednesday",Rates!$C$9,INDEX(Rates!$C$4:$C$7,MIN($K35,4))/$K35))) -> 15.333333 | M35: =ROUND($L35*$I35,2) -> 322 | N35: 0 | O35: supplies | P35: =IF(ISNUMBER(SEARCH("reg",$O35)),Rates!$C$11,0) -> 0 | Q35: =IF(ISNUMBER(SEARCH("supplies",$O35)),Rates!$C$12,0) -> 25 | R35: =$M35-$N35+$P35+$Q35 -> 347 | S35: 347 | T35: =ROUND($R35-$S35,2) -> 0 | U35: =IF(ABS($T35)<0.02,"OK","CHECK") -> OK | V35: roster PAID: part paid
A36: CH-033 | B36: FAM-020 | C36: DELACROIX | D36: Matteo | E36: Saturday | F36: Enrolled | G36: JAN-2026 | H36: 2026-015 | I36: =IF($J36<>"",$J36,IF($E36="Wednesday",INDEX(Terms!$D$4:$D$5,MATCH($G36,Terms!$A$4:$A$5,0)),INDEX(Terms!$C$4:$C$5,MATCH($G36,Terms!$A$4:$A$5,0)))) -> 21 | K36: =COUNTIFS($B$4:$B$500,$B36,$F$4:$F$500,"Enrolled") -> 3 | L36: =IF($F36<>"Enrolled",0,IF($K36=0,0,IF($E36="Wednesday",Rates!$C$9,INDEX(Rates!$C$4:$C$7,MIN($K36,4))/$K36))) -> 15.333333 | M36: =ROUND($L36*$I36,2) -> 322 | N36: 0 | O36: supplies | P36: =IF(ISNUMBER(SEARCH("reg",$O36)),Rates!$C$11,0) -> 0 | Q36: =IF(ISNUMBER(SEARCH("supplies",$O36)),Rates!$C$12,0) -> 25 | R36: =$M36-$N36+$P36+$Q36 -> 347 | S36: 347 | T36: =ROUND($R36-$S36,2) -> 0 | U36: =IF(ABS($T36)<0.02,"OK","CHECK") -> OK
A37: CH-034 | B37: FAM-020 | C37: DELACROIX | D37: Yusuf | E37: Saturday | F37: Enrolled | G37: JAN-2026 | H37: 2026-015a | I37: =IF($J37<>"",$J37,IF($E37="Wednesday",INDEX(Terms!$D$4:$D$5,MATCH($G37,Terms!$A$4:$A$5,0)),INDEX(Terms!$C$4:$C$5,MATCH($G37,Terms!$A$4:$A$5,0)))) -> 21 | K37: =COUNTIFS($B$4:$B$500,$B37,$F$4:$F$500,"Enrolled") -> 3 | L37: =IF($F37<>"Enrolled",0,IF($K37=0,0,IF($E37="Wednesday",Rates!$C$9,INDEX(Rates!$C$4:$C$7,MIN($K37,4))/$K37))) -> 15.333333 | M37: =ROUND($L37*$I37,2) -> 322 | N37: 0 | O37: supplies | P37: =IF(ISNUMBER(SEARCH("reg",$O37)),Rates!$C$11,0) -> 0 | Q37: =IF(ISNUMBER(SEARCH("supplies",$O37)),Rates!$C$12,0) -> 25 | R37: =$M37-$N37+$P37+$Q37 -> 347 | S37: 347 | T37: =ROUND($R37-$S37,2) -> 0 | U37: =IF(ABS($T37)<0.02,"OK","CHECK") -> OK | V37: roster PAID: paid
A38: CH-035 | B38: FAM-021 | C38: DUPLANTIER | D38: Halima | E38: Saturday | F38: Enrolled | G38: JAN-2026 | H38: 2026-016 | I38: =IF($J38<>"",$J38,IF($E38="Wednesday",INDEX(Terms!$D$4:$D$5,MATCH($G38,Terms!$A$4:$A$5,0)),INDEX(Terms!$C$4:$C$5,MATCH($G38,Terms!$A$4:$A$5,0)))) -> 21 | K38: =COUNTIFS($B$4:$B$500,$B38,$F$4:$F$500,"Enrolled") -> 1 | L38: =IF($F38<>"Enrolled",0,IF($K38=0,0,IF($E38="Wednesday",Rates!$C$9,INDEX(Rates!$C$4:$C$7,MIN($K38,4))/$K38))) -> 19.5 | M38: =ROUND($L38*$I38,2) -> 409.5 | N38: 0 | P38: =IF(ISNUMBER(SEARCH("reg",$O38)),Rates!$C$11,0) -> 0 | Q38: =IF(ISNUMBER(SEARCH("supplies",$O38)),Rates!$C$12,0) -> 0 | R38: =$M38-$N38+$P38+$Q38 -> 409.5 | S38: 409.5 | T38: =ROUND($R38-$S38,2) -> 0 | U38: =IF(ABS($T38)<0.02,"OK","CHECK") -> OK
A39: CH-036 | B39: FAM-022 | C39: DZIEDZIC | D39: Solveig | E39: Saturday | F39: Enrolled | G39: JAN-2026 | H39: 2026-057 | I39: =IF($J39<>"",$J39,IF($E39="Wednesday",INDEX(Terms!$D$4:$D$5,MATCH($G39,Terms!$A$4:$A$5,0)),INDEX(Terms!$C$4:$C$5,MATCH($G39,Terms!$A$4:$A$5,0)))) -> 21 | K39: =COUNTIFS($B$4:$B$500,$B39,$F$4:$F$500,"Enrolled") -> 1 | L39: =IF($F39<>"Enrolled",0,IF($K39=0,0,IF($E39="Wednesday",Rates!$C$9,INDEX(Rates!$C$4:$C$7,MIN($K39,4))/$K39))) -> 19.5 | M39: =ROUND($L39*$I39,2) -> 409.5 | N39: 0 | O39: supplies | P39: =IF(ISNUMBER(SEARCH("reg",$O39)),Rates!$C$11,0) -> 0 | Q39: =IF(ISNUMBER(SEARCH("supplies",$O39)),Rates!$C$12,0) -> 25 | R39: =$M39-$N39+$P39+$Q39 -> 434.5 | S39: 434.5 | T39: =ROUND($R39-$S39,2) -> 0 | U39: =IF(ABS($T39)<0.02,"OK","CHECK") -> OK | V39: roster PAID: paid
A40: CH-037 | B40: FAM-023 | C40: ERIKSEN | D40: Giulia | E40: Saturday | F40: Enrolled | G40: JAN-2026 | H40: 2026-017 | I40: =IF($J40<>"",$J40,IF($E40="Wednesday",INDEX(Terms!$D$4:$D$5,MATCH($G40,Terms!$A$4:$A$5,0)),INDEX(Terms!$C$4:$C$5,MATCH($G40,Terms!$A$4:$A$5,0)))) -> 21 | K40: =COUNTIFS($B$4:$B$500,$B40,$F$4:$F$500,"Enrolled") -> 1 | L40: =IF($F40<>"Enrolled",0,IF($K40=0,0,IF($E40="Wednesday",Rates!$C$9,INDEX(Rates!$C$4:$C$7,MIN($K40,4))/$K40))) -> 19.5 | M40: =ROUND($L40*$I40,2) -> 409.5 | N40: 0 | O40: supplies | P40: =IF(ISNUMBER(SEARCH("reg",$O40)),Rates!$C$11,0) -> 0 | Q40: =IF(ISNUMBER(SEARCH("supplies",$O40)),Rates!$C$12,0) -> 25 | R40: =$M40-$N40+$P40+$Q40 -> 434.5 | S40: 434.5 | T40: =ROUND($R40-$S40,2) -> 0 | U40: =IF(ABS($T40)<0.02,"OK","CHECK") -> OK | V40: roster PAID: paid
A41: CH-038 | B41: FAM-024 | C41: FALZON | D41: Jomo | E41: Saturday | F41: Enrolled | G41: JAN-2026 | H41: 2026-018 | I41: =IF($J41<>"",$J41,IF($E41="Wednesday",INDEX(Terms!$D$4:$D$5,MATCH($G41,Terms!$A$4:$A$5,0)),INDEX(Terms!$C$4:$C$5,MATCH($G41,Terms!$A$4:$A$5,0)))) -> 21 | K41: =COUNTIFS($B$4:$B$500,$B41,$F$4:$F$500,"Enrolled") -> 1 | L41: =IF($F41<>"Enrolled",0,IF($K41=0,0,IF($E41="Wednesday",Rates!$C$9,INDEX(Rates!$C$4:$C$7,MIN($K41,4))/$K41))) -> 19.5 | M41: =ROUND($L41*$I41,2) -> 409.5 | N41: 0 | O41: reg | P41: =IF(ISNUMBER(SEARCH("reg",$O41)),Rates!$C$11,0) -> 25 | Q41: =IF(ISNUMBER(SEARCH("supplies",$O41)),Rates!$C$12,0) -> 0 | R41: =$M41-$N41+$P41+$Q41 -> 434.5 | S41: 434.5 | T41: =ROUND($R41-$S41,2) -> 0 | U41: =IF(ABS($T41)<0.02,"OK","CHECK") -> OK | V41: roster PAID: paid
A42: CH-039 | B42: FAM-025 | C42: FERREIRO | D42: Giulia | E42: Saturday | F42: Enrolled | G42: JAN-2026 | H42: 2026-058 | I42: =IF($J42<>"",$J42,IF($E42="Wednesday",INDEX(Terms!$D$4:$D$5,MATCH($G42,Terms!$A$4:$A$5,0)),INDEX(Terms!$C$4:$C$5,MATCH($G42,Terms!$A$4:$A$5,0)))) -> 21 | K42: =COUNTIFS($B$4:$B$500,$B42,$F$4:$F$500,"Enrolled") -> 1 | L42: =IF($F42<>"Enrolled",0,IF($K42=0,0,IF($E42="Wednesday",Rates!$C$9,INDEX(Rates!$C$4:$C$7,MIN($K42,4))/$K42))) -> 19.5 | M42: =ROUND($L42*$I42,2) -> 409.5 | N42: 0 | O42: supplies | P42: =IF(ISNUMBER(SEARCH("reg",$O42)),Rates!$C$11,0) -> 0 | Q42: =IF(ISNUMBER(SEARCH("supplies",$O42)),Rates!$C$12,0) -> 25 | R42: =$M42-$N42+$P42+$Q42 -> 434.5 | S42: 434.5 | T42: =ROUND($R42-$S42,2) -> 0 | U42: =IF(ABS($T42)<0.02,"OK","CHECK") -> OK | V42: roster PAID: paid
A43: CH-040 | B43: FAM-026 | C43: FITZHUGH | D43: Emeka | E43: Saturday | F43: Enrolled | G43: JAN-2026 | H43: 2026-019 | I43: =IF($J43<>"",$J43,IF($E43="Wednesday",INDEX(Terms!$D$4:$D$5,MATCH($G43,Terms!$A$4:$A$5,0)),INDEX(Terms!$C$4:$C$5,MATCH($G43,Terms!$A$4:$A$5,0)))) -> 21 | K43: =COUNTIFS($B$4:$B$500,$B43,$F$4:$F$500,"Enrolled") -> 1 | L43: =IF($F43<>"Enrolled",0,IF($K43=0,0,IF($E43="Wednesday",Rates!$C$9,INDEX(Rates!$C$4:$C$7,MIN($K43,4))/$K43))) -> 19.5 | M43: =ROUND($L43*$I43,2) -> 409.5 | N43: 0 | O43: supplies | P43: =IF(ISNUMBER(SEARCH("reg",$O43)),Rates!$C$11,0) -> 0 | Q43: =IF(ISNUMBER(SEARCH("supplies",$O43)),Rates!$C$12,0) -> 25 | R43: =$M43-$N43+$P43+$Q43 -> 434.5 | S43: 434.5 | T43: =ROUND($R43-$S43,2) -> 0 | U43: =IF(ABS($T43)<0.02,"OK","CHECK") -> OK | V43: roster PAID: part paid
A44: CH-041 | B44: FAM-027 | C44: GAILLARD | D44: Esben | E44: Saturday | F44: Enrolled | G44: JAN-2026 | H44: 2026-020 | I44: =IF($J44<>"",$J44,IF($E44="Wednesday",INDEX(Terms!$D$4:$D$5,MATCH($G44,Terms!$A$4:$A$5,0)),INDEX(Terms!$C$4:$C$5,MATCH($G44,Terms!$A$4:$A$5,0)))) -> 21 | K44: =COUNTIFS($B$4:$B$500,$B44,$F$4:$F$500,"Enrolled") -> 1 | L44: =IF($F44<>"Enrolled",0,IF($K44=0,0,IF($E44="Wednesday",Rates!$C$9,INDEX(Rates!$C$4:$C$7,MIN($K44,4))/$K44))) -> 19.5 | M44: =ROUND($L44*$I44,2) -> 409.5 | N44: 0 | O44: supplies | P44: =IF(ISNUMBER(SEARCH("reg",$O44)),Rates!$C$11,0) -> 0 | Q44: =IF(ISNUMBER(SEARCH("supplies",$O44)),Rates!$C$12,0) -> 25 | R44: =$M44-$N44+$P44+$Q44 -> 434.5 | S44: 434.5 | T44: =ROUND($R44-$S44,2) -> 0 | U44: =IF(ABS($T44)<0.02,"OK","CHECK") -> OK | V44: roster PAID: paid
A45: CH-042 | B45: FAM-028 | C45: GRIMALDSEN | D45: Celestine | E45: Saturday | F45: Enrolled | G45: JAN-2026 | H45: 2026-059a | I45: =IF($J45<>"",$J45,IF($E45="Wednesday",INDEX(Terms!$D$4:$D$5,MATCH($G45,Terms!$A$4:$A$5,0)),INDEX(Terms!$C$4:$C$5,MATCH($G45,Terms!$A$4:$A$5,0)))) -> 21 | K45: =COUNTIFS($B$4:$B$500,$B45,$F$4:$F$500,"Enrolled") -> 3 | L45: =IF($F45<>"Enrolled",0,IF($K45=0,0,IF($E45="Wednesday",Rates!$C$9,INDEX(Rates!$C$4:$C$7,MIN($K45,4))/$K45))) -> 15.333333 | M45: =ROUND($L45*$I45,2) -> 322 | N45: 0 | O45: supplies | P45: =IF(ISNUMBER(SEARCH("reg",$O45)),Rates!$C$11,0) -> 0 | Q45: =IF(ISNUMBER(SEARCH("supplies",$O45)),Rates!$C$12,0) -> 25 | R45: =$M45-$N45+$P45+$Q45 -> 347 | S45: 347 | T45: =ROUND($R45-$S45,2) -> 0 | U45: =IF(ABS($T45)<0.02,"OK","CHECK") -> OK
A46: CH-043 | B46: FAM-028 | C46: GRIMALDSEN | D46: Delphine | E46: Saturday | F46: Enrolled | G46: JAN-2026 | H46: 2026-059 | I46: =IF($J46<>"",$J46,IF($E46="Wednesday",INDEX(Terms!$D$4:$D$5,MATCH($G46,Terms!$A$4:$A$5,0)),INDEX(Terms!$C$4:$C$5,MATCH($G46,Terms!$A$4:$A$5,0)))) -> 21 | K46: =COUNTIFS($B$4:$B$500,$B46,$F$4:$F$500,"Enrolled") -> 3 | L46: =IF($F46<>"Enrolled",0,IF($K46=0,0,IF($E46="Wednesday",Rates!$C$9,INDEX(Rates!$C$4:$C$7,MIN($K46,4))/$K46))) -> 15.333333 | M46: =ROUND($L46*$I46,2) -> 322 | N46: 0 | P46: =IF(ISNUMBER(SEARCH("reg",$O46)),Rates!$C$11,0) -> 0 | Q46: =IF(ISNUMBER(SEARCH("supplies",$O46)),Rates!$C$12,0) -> 0 | R46: =$M46-$N46+$P46+$Q46 -> 322 | S46: 322 | T46: =ROUND($R46-$S46,2) -> 0 | U46: =IF(ABS($T46)<0.02,"OK","CHECK") -> OK | V46: roster PAID: paid
A47: CH-044 | B47: FAM-028 | C47: GRIMALDSEN | D47: Matteo | E47: Saturday | F47: Enrolled | G47: JAN-2026 | H47: 2026-059 | I47: =IF($J47<>"",$J47,IF($E47="Wednesday",INDEX(Terms!$D$4:$D$5,MATCH($G47,Terms!$A$4:$A$5,0)),INDEX(Terms!$C$4:$C$5,MATCH($G47,Terms!$A$4:$A$5,0)))) -> 21 | K47: =COUNTIFS($B$4:$B$500,$B47,$F$4:$F$500,"Enrolled") -> 3 | L47: =IF($F47<>"Enrolled",0,IF($K47=0,0,IF($E47="Wednesday",Rates!$C$9,INDEX(Rates!$C$4:$C$7,MIN($K47,4))/$K47))) -> 15.333333 | M47: =ROUND($L47*$I47,2) -> 322 | N47: 0 | O47: reg, supplies | P47: =IF(ISNUMBER(SEARCH("reg",$O47)),Rates!$C$11,0) -> 25 | Q47: =IF(ISNUMBER(SEARCH("supplies",$O47)),Rates!$C$12,0) -> 25 | R47: =$M47-$N47+$P47+$Q47 -> 372 | S47: 372 | T47: =ROUND($R47-$S47,2) -> 0 | U47: =IF(ABS($T47)<0.02,"OK","CHECK") -> OK
A48: CH-045 | B48: FAM-029 | C48: GRYNBERG | D48: Rafaela | E48: Saturday | F48: Enrolled | G48: JAN-2026 | H48: 2026-021 | I48: =IF($J48<>"",$J48,IF($E48="Wednesday",INDEX(Terms!$D$4:$D$5,MATCH($G48,Terms!$A$4:$A$5,0)),INDEX(Terms!$C$4:$C$5,MATCH($G48,Terms!$A$4:$A$5,0)))) -> 21 | K48: =COUNTIFS($B$4:$B$500,$B48,$F$4:$F$500,"Enrolled") -> 1 | L48: =IF($F48<>"Enrolled",0,IF($K48=0,0,IF($E48="Wednesday",Rates!$C$9,INDEX(Rates!$C$4:$C$7,MIN($K48,4))/$K48))) -> 19.5 | M48: =ROUND($L48*$I48,2) -> 409.5 | N48: 0 | P48: =IF(ISNUMBER(SEARCH("reg",$O48)),Rates!$C$11,0) -> 0 | Q48: =IF(ISNUMBER(SEARCH("supplies",$O48)),Rates!$C$12,0) -> 0 | R48: =$M48-$N48+$P48+$Q48 -> 409.5 | S48: 409.5 | T48: =ROUND($R48-$S48,2) -> 0 | U48: =IF(ABS($T48)<0.02,"OK","CHECK") -> OK
A49: CH-046 | B49: FAM-030 | C49: HALVORSEN | D49: Bijou | E49: Saturday | F49: Enrolled | G49: JAN-2026 | H49: 2026-022a | I49: =IF($J49<>"",$J49,IF($E49="Wednesday",INDEX(Terms!$D$4:$D$5,MATCH($G49,Terms!$A$4:$A$5,0)),INDEX(Terms!$C$4:$C$5,MATCH($G49,Terms!$A$4:$A$5,0)))) -> 21 | K49: =COUNTIFS($B$4:$B$500,$B49,$F$4:$F$500,"Enrolled") -> 4 | L49: =IF($F49<>"Enrolled",0,IF($K49=0,0,IF($E49="Wednesday",Rates!$C$9,INDEX(Rates!$C$4:$C$7,MIN($K49,4))/$K49))) -> 14.275 | M49: =ROUND($L49*$I49,2) -> 299.78 | N49: 0 | O49: supplies | P49: =IF(ISNUMBER(SEARCH("reg",$O49)),Rates!$C$11,0) -> 0 | Q49: =IF(ISNUMBER(SEARCH("supplies",$O49)),Rates!$C$12,0) -> 25 | R49: =$M49-$N49+$P49+$Q49 -> 324.78 | S49: 324.78 | T49: =ROUND($R49-$S49,2) -> 0 | U49: =IF(ABS($T49)<0.02,"OK","CHECK") -> OK | V49: roster PAID: paid
A50: CH-047 | B50: FAM-030 | C50: HALVORSEN | D50: Cato | E50: Saturday | F50: Enrolled | G50: JAN-2026 | H50: 2026-022 | I50: =IF($J50<>"",$J50,IF($E50="Wednesday",INDEX(Terms!$D$4:$D$5,MATCH($G50,Terms!$A$4:$A$5,0)),INDEX(Terms!$C$4:$C$5,MATCH($G50,Terms!$A$4:$A$5,0)))) -> 21 | K50: =COUNTIFS($B$4:$B$500,$B50,$F$4:$F$500,"Enrolled") -> 4 | L50: =IF($F50<>"Enrolled",0,IF($K50=0,0,IF($E50="Wednesday",Rates!$C$9,INDEX(Rates!$C$4:$C$7,MIN($K50,4))/$K50))) -> 14.275 | M50: =ROUND($L50*$I50,2) -> 299.78 | N50: 0 | O50: supplies | P50: =IF(ISNUMBER(SEARCH("reg",$O50)),Rates!$C$11,0) -> 0 | Q50: =IF(ISNUMBER(SEARCH("supplies",$O50)),Rates!$C$12,0) -> 25 | R50: =$M50-$N50+$P50+$Q50 -> 324.78 | S50: 324.78 | T50: =ROUND($R50-$S50,2) -> 0 | U50: =IF(ABS($T50)<0.02,"OK","CHECK") -> OK | V50: roster PAID: part paid
A51: CH-048 | B51: FAM-030 | C51: HALVORSEN | D51: Ezra | E51: Saturday | F51: Enrolled | G51: JAN-2026 | H51: 2026-022 | I51: =IF($J51<>"",$J51,IF($E51="Wednesday",INDEX(Terms!$D$4:$D$5,MATCH($G51,Terms!$A$4:$A$5,0)),INDEX(Terms!$C$4:$C$5,MATCH($G51,Terms!$A$4:$A$5,0)))) -> 21 | K51: =COUNTIFS($B$4:$B$500,$B51,$F$4:$F$500,"Enrolled") -> 4 | L51: =IF($F51<>"Enrolled",0,IF($K51=0,0,IF($E51="Wednesday",Rates!$C$9,INDEX(Rates!$C$4:$C$7,MIN($K51,4))/$K51))) -> 14.275 | M51: =ROUND($L51*$I51,2) -> 299.78 | N51: 0 | O51: supplies | P51: =IF(ISNUMBER(SEARCH("reg",$O51)),Rates!$C$11,0) -> 0 | Q51: =IF(ISNUMBER(SEARCH("supplies",$O51)),Rates!$C$12,0) -> 25 | R51: =$M51-$N51+$P51+$Q51 -> 324.78 | S51: 324.78 | T51: =ROUND($R51-$S51,2) -> 0 | U51: =IF(ABS($T51)<0.02,"OK","CHECK") -> OK | V51: roster PAID: paid
A52: CH-049 | B52: FAM-030 | C52: HALVORSEN | D52: Ndidi | E52: Saturday | F52: Enrolled | G52: JAN-2026 | H52: 2026-022 | I52: =IF($J52<>"",$J52,IF($E52="Wednesday",INDEX(Terms!$D$4:$D$5,MATCH($G52,Terms!$A$4:$A$5,0)),INDEX(Terms!$C$4:$C$5,MATCH($G52,Terms!$A$4:$A$5,0)))) -> 21 | K52: =COUNTIFS($B$4:$B$500,$B52,$F$4:$F$500,"Enrolled") -> 4 | L52: =IF($F52<>"Enrolled",0,IF($K52=0,0,IF($E52="Wednesday",Rates!$C$9,INDEX(Rates!$C$4:$C$7,MIN($K52,4))/$K52))) -> 14.275 | M52: =ROUND($L52*$I52,2) -> 299.78 | N52: 0 | O52: supplies | P52: =IF(ISNUMBER(SEARCH("reg",$O52)),Rates!$C$11,0) -> 0 | Q52: =IF(ISNUMBER(SEARCH("supplies",$O52)),Rates!$C$12,0) -> 25 | R52: =$M52-$N52+$P52+$Q52 -> 324.78 | S52: 324.78 | T52: =ROUND($R52-$S52,2) -> 0 | U52: =IF(ABS($T52)<0.02,"OK","CHECK") -> OK | V52: roster PAID: paid
A53: CH-050 | B53: FAM-031 | C53: HASANOVIC | D53: Rune | E53: Saturday | F53: Enrolled | G53: JAN-2026 | H53: 2026-060 | I53: =IF($J53<>"",$J53,IF($E53="Wednesday",INDEX(Terms!$D$4:$D$5,MATCH($G53,Terms!$A$4:$A$5,0)),INDEX(Terms!$C$4:$C$5,MATCH($G53,Terms!$A$4:$A$5,0)))) -> 21 | K53: =COUNTIFS($B$4:$B$500,$B53,$F$4:$F$500,"Enrolled") -> 1 | L53: =IF($F53<>"Enrolled",0,IF($K53=0,0,IF($E53="Wednesday",Rates!$C$9,INDEX(Rates!$C$4:$C$7,MIN($K53,4))/$K53))) -> 19.5 | M53: =ROUND($L53*$I53,2) -> 409.5 | N53: 0 | O53: supplies | P53: =IF(ISNUMBER(SEARCH("reg",$O53)),Rates!$C$11,0) -> 0 | Q53: =IF(ISNUMBER(SEARCH("supplies",$O53)),Rates!$C$12,0) -> 25 | R53: =$M53-$N53+$P53+$Q53 -> 434.5 | S53: 434.5 | T53: =ROUND($R53-$S53,2) -> 0 | U53: =IF(ABS($T53)<0.02,"OK","CHECK") -> OK | V53: roster PAID: paid
A54: CH-051 | B54: FAM-032 | C54: HOLLINGWORTH | D54: Otto | E54: Saturday | F54: Enrolled | G54: JAN-2026 | H54: 2026-023 | I54: =IF($J54<>"",$J54,IF($E54="Wednesday",INDEX(Terms!$D$4:$D$5,MATCH($G54,Terms!$A$4:$A$5,0)),INDEX(Terms!$C$4:$C$5,MATCH($G54,Terms!$A$4:$A$5,0)))) -> 21 | K54: =COUNTIFS($B$4:$B$500,$B54,$F$4:$F$500,"Enrolled") -> 1 | L54: =IF($F54<>"Enrolled",0,IF($K54=0,0,IF($E54="Wednesday",Rates!$C$9,INDEX(Rates!$C$4:$C$7,MIN($K54,4))/$K54))) -> 19.5 | M54: =ROUND($L54*$I54,2) -> 409.5 | N54: 0 | O54: supplies | P54: =IF(ISNUMBER(SEARCH("reg",$O54)),Rates!$C$11,0) -> 0 | Q54: =IF(ISNUMBER(SEARCH("supplies",$O54)),Rates!$C$12,0) -> 25 | R54: =$M54-$N54+$P54+$Q54 -> 434.5 | S54: 434.5 | T54: =ROUND($R54-$S54,2) -> 0 | U54: =IF(ABS($T54)<0.02,"OK","CHECK") -> OK
A55: CH-052 | B55: FAM-033 | C55: IBARRA | D55: Wren | E55: Saturday | F55: Enrolled | G55: JAN-2026 | H55: 2026-024 | I55: =IF($J55<>"",$J55,IF($E55="Wednesday",INDEX(Terms!$D$4:$D$5,MATCH($G55,Terms!$A$4:$A$5,0)),INDEX(Terms!$C$4:$C$5,MATCH($G55,Terms!$A$4:$A$5,0)))) -> 21 | K55: =COUNTIFS($B$4:$B$500,$B55,$F$4:$F$500,"Enrolled") -> 1 | L55: =IF($F55<>"Enrolled",0,IF($K55=0,0,IF($E55="Wednesday",Rates!$C$9,INDEX(Rates!$C$4:$C$7,MIN($K55,4))/$K55))) -> 19.5 | M55: =ROUND($L55*$I55,2) -> 409.5 | N55: 0 | O55: reg | P55: =IF(ISNUMBER(SEARCH("reg",$O55)),Rates!$C$11,0) -> 25 | Q55: =IF(ISNUMBER(SEARCH("supplies",$O55)),Rates!$C$12,0) -> 0 | R55: =$M55-$N55+$P55+$Q55 -> 434.5 | S55: 434.5 | T55: =ROUND($R55-$S55,2) -> 0 | U55: =IF(ABS($T55)<0.02,"OK","CHECK") -> OK
A56: CH-053 | B56: FAM-034 | C56: JANKOWSKI | D56: Ingvar | E56: Saturday | F56: Enrolled | G56: JAN-2026 | H56: 2026-025 | I56: =IF($J56<>"",$J56,IF($E56="Wednesday",INDEX(Terms!$D$4:$D$5,MATCH($G56,Terms!$A$4:$A$5,0)),INDEX(Terms!$C$4:$C$5,MATCH($G56,Terms!$A$4:$A$5,0)))) -> 21 | K56: =COUNTIFS($B$4:$B$500,$B56,$F$4:$F$500,"Enrolled") -> 1 | L56: =IF($F56<>"Enrolled",0,IF($K56=0,0,IF($E56="Wednesday",Rates!$C$9,INDEX(Rates!$C$4:$C$7,MIN($K56,4))/$K56))) -> 19.5 | M56: =ROUND($L56*$I56,2) -> 409.5 | N56: 0 | O56: supplies | P56: =IF(ISNUMBER(SEARCH("reg",$O56)),Rates!$C$11,0) -> 0 | Q56: =IF(ISNUMBER(SEARCH("supplies",$O56)),Rates!$C$12,0) -> 25 | R56: =$M56-$N56+$P56+$Q56 -> 434.5 | S56: 434.5 | T56: =ROUND($R56-$S56,2) -> 0 | U56: =IF(ABS($T56)<0.02,"OK","CHECK") -> OK | V56: roster PAID: part paid
A57: CH-054 | B57: FAM-035 | C57: KACZMAREK | D57: Hektor | E57: Saturday | F57: Enrolled | G57: JAN-2026 | H57: 2026-026 | I57: =IF($J57<>"",$J57,IF($E57="Wednesday",INDEX(Terms!$D$4:$D$5,MATCH($G57,Terms!$A$4:$A$5,0)),INDEX(Terms!$C$4:$C$5,MATCH($G57,Terms!$A$4:$A$5,0)))) -> 21 | K57: =COUNTIFS($B$4:$B$500,$B57,$F$4:$F$500,"Enrolled") -> 3 | L57: =IF($F57<>"Enrolled",0,IF($K57=0,0,IF($E57="Wednesday",Rates!$C$9,INDEX(Rates!$C$4:$C$7,MIN($K57,4))/$K57))) -> 15.333333 | M57: =ROUND($L57*$I57,2) -> 322 | N57: 0 | O57: supplies | P57: =IF(ISNUMBER(SEARCH("reg",$O57)),Rates!$C$11,0) -> 0 | Q57: =IF(ISNUMBER(SEARCH("supplies",$O57)),Rates!$C$12,0) -> 25 | R57: =$M57-$N57+$P57+$Q57 -> 347 | S57: 347 | T57: =ROUND($R57-$S57,2) -> 0 | U57: =IF(ABS($T57)<0.02,"OK","CHECK") -> OK | V57: roster PAID: paid
A58: CH-055 | B58: FAM-035 | C58: KACZMAREK | D58: Nadia | E58: Saturday | F58: Enrolled | G58: JAN-2026 | H58: 2026-026a | I58: =IF($J58<>"",$J58,IF($E58="Wednesday",INDEX(Terms!$D$4:$D$5,MATCH($G58,Terms!$A$4:$A$5,0)),INDEX(Terms!$C$4:$C$5,MATCH($G58,Terms!$A$4:$A$5,0)))) -> 21 | K58: =COUNTIFS($B$4:$B$500,$B58,$F$4:$F$500,"Enrolled") -> 3 | L58: =IF($F58<>"Enrolled",0,IF($K58=0,0,IF($E58="Wednesday",Rates!$C$9,INDEX(Rates!$C$4:$C$7,MIN($K58,4))/$K58))) -> 15.333333 | M58: =ROUND($L58*$I58,2) -> 322 | N58: 0 | O58: supplies | P58: =IF(ISNUMBER(SEARCH("reg",$O58)),Rates!$C$11,0) -> 0 | Q58: =IF(ISNUMBER(SEARCH("supplies",$O58)),Rates!$C$12,0) -> 25 | R58: =$M58-$N58+$P58+$Q58 -> 347 | S58: 347 | T58: =ROUND($R58-$S58,2) -> 0 | U58: =IF(ABS($T58)<0.02,"OK","CHECK") -> OK | V58: roster PAID: paid
A59: CH-056 | B59: FAM-035 | C59: KACZMAREK | D59: Thibault | E59: Saturday | F59: Enrolled | G59: JAN-2026 | H59: 2026-026 | I59: =IF($J59<>"",$J59,IF($E59="Wednesday",INDEX(Terms!$D$4:$D$5,MATCH($G59,Terms!$A$4:$A$5,0)),INDEX(Terms!$C$4:$C$5,MATCH($G59,Terms!$A$4:$A$5,0)))) -> 21 | K59: =COUNTIFS($B$4:$B$500,$B59,$F$4:$F$500,"Enrolled") -> 3 | L59: =IF($F59<>"Enrolled",0,IF($K59=0,0,IF($E59="Wednesday",Rates!$C$9,INDEX(Rates!$C$4:$C$7,MIN($K59,4))/$K59))) -> 15.333333 | M59: =ROUND($L59*$I59,2) -> 322 | N59: 0 | O59: supplies | P59: =IF(ISNUMBER(SEARCH("reg",$O59)),Rates!$C$11,0) -> 0 | Q59: =IF(ISNUMBER(SEARCH("supplies",$O59)),Rates!$C$12,0) -> 25 | R59: =$M59-$N59+$P59+$Q59 -> 347 | S59: 347 | T59: =ROUND($R59-$S59,2) -> 0 | U59: =IF(ABS($T59)<0.02,"OK","CHECK") -> OK
A60: CH-057 | B60: FAM-036 | C60: KILBRIDE | D60: Juniper | E60: Saturday | F60: Enrolled | G60: JAN-2026 | H60: 2026-027 | I60: =IF($J60<>"",$J60,IF($E60="Wednesday",INDEX(Terms!$D$4:$D$5,MATCH($G60,Terms!$A$4:$A$5,0)),INDEX(Terms!$C$4:$C$5,MATCH($G60,Terms!$A$4:$A$5,0)))) -> 21 | K60: =COUNTIFS($B$4:$B$500,$B60,$F$4:$F$500,"Enrolled") -> 3 | L60: =IF($F60<>"Enrolled",0,IF($K60=0,0,IF($E60="Wednesday",Rates!$C$9,INDEX(Rates!$C$4:$C$7,MIN($K60,4))/$K60))) -> 15.333333 | M60: =ROUND($L60*$I60,2) -> 322 | N60: 0 | O60: supplies | P60: =IF(ISNUMBER(SEARCH("reg",$O60)),Rates!$C$11,0) -> 0 | Q60: =IF(ISNUMBER(SEARCH("supplies",$O60)),Rates!$C$12,0) -> 25 | R60: =$M60-$N60+$P60+$Q60 -> 347 | S60: 347 | T60: =ROUND($R60-$S60,2) -> 0 | U60: =IF(ABS($T60)<0.02,"OK","CHECK") -> OK | V60: roster PAID: paid
A61: CH-058 | B61: FAM-036 | C61: KILBRIDE | D61: Xanthe | E61: Saturday | F61: Enrolled | G61: JAN-2026 | H61: 2026-027a | I61: =IF($J61<>"",$J61,IF($E61="Wednesday",INDEX(Terms!$D$4:$D$5,MATCH($G61,Terms!$A$4:$A$5,0)),INDEX(Terms!$C$4:$C$5,MATCH($G61,Terms!$A$4:$A$5,0)))) -> 21 | K61: =COUNTIFS($B$4:$B$500,$B61,$F$4:$F$500,"Enrolled") -> 3 | L61: =IF($F61<>"Enrolled",0,IF($K61=0,0,IF($E61="Wednesday",Rates!$C$9,INDEX(Rates!$C$4:$C$7,MIN($K61,4))/$K61))) -> 15.333333 | M61: =ROUND($L61*$I61,2) -> 322 | N61: 0 | O61: supplies | P61: =IF(ISNUMBER(SEARCH("reg",$O61)),Rates!$C$11,0) -> 0 | Q61: =IF(ISNUMBER(SEARCH("supplies",$O61)),Rates!$C$12,0) -> 25 | R61: =$M61-$N61+$P61+$Q61 -> 347 | S61: 347 | T61: =ROUND($R61-$S61,2) -> 0 | U61: =IF(ABS($T61)<0.02,"OK","CHECK") -> OK
A62: CH-059 | B62: FAM-036 | C62: KILBRIDE | D62: Zosia | E62: Saturday | F62: Enrolled | G62: JAN-2026 | H62: 2026-027 | I62: =IF($J62<>"",$J62,IF($E62="Wednesday",INDEX(Terms!$D$4:$D$5,MATCH($G62,Terms!$A$4:$A$5,0)),INDEX(Terms!$C$4:$C$5,MATCH($G62,Terms!$A$4:$A$5,0)))) -> 21 | K62: =COUNTIFS($B$4:$B$500,$B62,$F$4:$F$500,"Enrolled") -> 3 | L62: =IF($F62<>"Enrolled",0,IF($K62=0,0,IF($E62="Wednesday",Rates!$C$9,INDEX(Rates!$C$4:$C$7,MIN($K62,4))/$K62))) -> 15.333333 | M62: =ROUND($L62*$I62,2) -> 322 | N62: 0 | O62: supplies | P62: =IF(ISNUMBER(SEARCH("reg",$O62)),Rates!$C$11,0) -> 0 | Q62: =IF(ISNUMBER(SEARCH("supplies",$O62)),Rates!$C$12,0) -> 25 | R62: =$M62-$N62+$P62+$Q62 -> 347 | S62: 347 | T62: =ROUND($R62-$S62,2) -> 0 | U62: =IF(ABS($T62)<0.02,"OK","CHECK") -> OK
A63: CH-060 | B63: FAM-037 | C63: LACHAPELLE | D63: Fionn | E63: Saturday | F63: Enrolled | G63: JAN-2026 | H63: 2026-028 | I63: =IF($J63<>"",$J63,IF($E63="Wednesday",INDEX(Terms!$D$4:$D$5,MATCH($G63,Terms!$A$4:$A$5,0)),INDEX(Terms!$C$4:$C$5,MATCH($G63,Terms!$A$4:$A$5,0)))) -> 21 | K63: =COUNTIFS($B$4:$B$500,$B63,$F$4:$F$500,"Enrolled") -> 2 | L63: =IF($F63<>"Enrolled",0,IF($K63=0,0,IF($E63="Wednesday",Rates!$C$9,INDEX(Rates!$C$4:$C$7,MIN($K63,4))/$K63))) -> 17.25 | M63: =ROUND($L63*$I63,2) -> 362.25 | N63: 0 | O63: supplies | P63: =IF(ISNUMBER(SEARCH("reg",$O63)),Rates!$C$11,0) -> 0 | Q63: =IF(ISNUMBER(SEARCH("supplies",$O63)),Rates!$C$12,0) -> 25 | R63: =$M63-$N63+$P63+$Q63 -> 387.25 | S63: 387.25 | T63: =ROUND($R63-$S63,2) -> 0 | U63: =IF(ABS($T63)<0.02,"OK","CHECK") -> OK | V63: roster PAID: part paid
A64: CH-061 | B64: FAM-037 | C64: LACHAPELLE | D64: Sable | E64: Saturday | F64: Enrolled | G64: JAN-2026 | H64: 2026-028a | I64: =IF($J64<>"",$J64,IF($E64="Wednesday",INDEX(Terms!$D$4:$D$5,MATCH($G64,Terms!$A$4:$A$5,0)),INDEX(Terms!$C$4:$C$5,MATCH($G64,Terms!$A$4:$A$5,0)))) -> 21 | K64: =COUNTIFS($B$4:$B$500,$B64,$F$4:$F$500,"Enrolled") -> 2 | L64: =IF($F64<>"Enrolled",0,IF($K64=0,0,IF($E64="Wednesday",Rates!$C$9,INDEX(Rates!$C$4:$C$7,MIN($K64,4))/$K64))) -> 17.25 | M64: =ROUND($L64*$I64,2) -> 362.25 | N64: 0 | O64: supplies | P64: =IF(ISNUMBER(SEARCH("reg",$O64)),Rates!$C$11,0) -> 0 | Q64: =IF(ISNUMBER(SEARCH("supplies",$O64)),Rates!$C$12,0) -> 25 | R64: =$M64-$N64+$P64+$Q64 -> 387.25 | S64: 387.25 | T64: =ROUND($R64-$S64,2) -> 0 | U64: =IF(ABS($T64)<0.02,"OK","CHECK") -> OK | V64: roster PAID: paid
A65: CH-062 | B65: FAM-038 | C65: LINDQVIST | D65: Quentin | E65: Saturday | F65: Enrolled | G65: JAN-2026 | H65: 2026-029a | I65: =IF($J65<>"",$J65,IF($E65="Wednesday",INDEX(Terms!$D$4:$D$5,MATCH($G65,Terms!$A$4:$A$5,0)),INDEX(Terms!$C$4:$C$5,MATCH($G65,Terms!$A$4:$A$5,0)))) -> 21 | K65: =COUNTIFS($B$4:$B$500,$B65,$F$4:$F$500,"Enrolled") -> 2 | L65: =IF($F65<>"Enrolled",0,IF($K65=0,0,IF($E65="Wednesday",Rates!$C$9,INDEX(Rates!$C$4:$C$7,MIN($K65,4))/$K65))) -> 17.25 | M65: =ROUND($L65*$I65,2) -> 362.25 | N65: 0 | O65: supplies | P65: =IF(ISNUMBER(SEARCH("reg",$O65)),Rates!$C$11,0) -> 0 | Q65: =IF(ISNUMBER(SEARCH("supplies",$O65)),Rates!$C$12,0) -> 25 | R65: =$M65-$N65+$P65+$Q65 -> 387.25 | S65: 387.25 | T65: =ROUND($R65-$S65,2) -> 0 | U65: =IF(ABS($T65)<0.02,"OK","CHECK") -> OK
A66: CH-063 | B66: FAM-038 | C66: LINDQVIST | D66: Uma | E66: Saturday | F66: Enrolled | G66: JAN-2026 | H66: 2026-029 | I66: =IF($J66<>"",$J66,IF($E66="Wednesday",INDEX(Terms!$D$4:$D$5,MATCH($G66,Terms!$A$4:$A$5,0)),INDEX(Terms!$C$4:$C$5,MATCH($G66,Terms!$A$4:$A$5,0)))) -> 21 | K66: =COUNTIFS($B$4:$B$500,$B66,$F$4:$F$500,"Enrolled") -> 2 | L66: =IF($F66<>"Enrolled",0,IF($K66=0,0,IF($E66="Wednesday",Rates!$C$9,INDEX(Rates!$C$4:$C$7,MIN($K66,4))/$K66))) -> 17.25 | M66: =ROUND($L66*$I66,2) -> 362.25 | N66: 0 | O66: reg, supplies | P66: =IF(ISNUMBER(SEARCH("reg",$O66)),Rates!$C$11,0) -> 25 | Q66: =IF(ISNUMBER(SEARCH("supplies",$O66)),Rates!$C$12,0) -> 25 | R66: =$M66-$N66+$P66+$Q66 -> 412.25 | S66: 412.25 | T66: =ROUND($R66-$S66,2) -> 0 | U66: =IF(ABS($T66)<0.02,"OK","CHECK") -> OK
A67: CH-064 | B67: FAM-039 | C67: MAALOUF | D67: Bastien | E67: Saturday | F67: Enrolled | G67: JAN-2026 | H67: 2026-030a | I67: =IF($J67<>"",$J67,IF($E67="Wednesday",INDEX(Terms!$D$4:$D$5,MATCH($G67,Terms!$A$4:$A$5,0)),INDEX(Terms!$C$4:$C$5,MATCH($G67,Terms!$A$4:$A$5,0)))) -> 21 | K67: =COUNTIFS($B$4:$B$500,$B67,$F$4:$F$500,"Enrolled") -> 2 | L67: =IF($F67<>"Enrolled",0,IF($K67=0,0,IF($E67="Wednesday",Rates!$C$9,INDEX(Rates!$C$4:$C$7,MIN($K67,4))/$K67))) -> 17.25 | M67: =ROUND($L67*$I67,2) -> 362.25 | N67: 0 | O67: supplies | P67: =IF(ISNUMBER(SEARCH("reg",$O67)),Rates!$C$11,0) -> 0 | Q67: =IF(ISNUMBER(SEARCH("supplies",$O67)),Rates!$C$12,0) -> 25 | R67: =$M67-$N67+$P67+$Q67 -> 387.25 | S67: 387.25 | T67: =ROUND($R67-$S67,2) -> 0 | U67: =IF(ABS($T67)<0.02,"OK","CHECK") -> OK | V67: roster PAID: paid
A68: CH-065 | B68: FAM-039 | C68: MAALOUF | D68: Kwame | E68: Saturday | F68: Enrolled | G68: JAN-2026 | H68: 2026-030 | I68: =IF($J68<>"",$J68,IF($E68="Wednesday",INDEX(Terms!$D$4:$D$5,MATCH($G68,Terms!$A$4:$A$5,0)),INDEX(Terms!$C$4:$C$5,MATCH($G68,Terms!$A$4:$A$5,0)))) -> 21 | K68: =COUNTIFS($B$4:$B$500,$B68,$F$4:$F$500,"Enrolled") -> 2 | L68: =IF($F68<>"Enrolled",0,IF($K68=0,0,IF($E68="Wednesday",Rates!$C$9,INDEX(Rates!$C$4:$C$7,MIN($K68,4))/$K68))) -> 17.25 | M68: =ROUND($L68*$I68,2) -> 362.25 | N68: 0 | O68: supplies | P68: =IF(ISNUMBER(SEARCH("reg",$O68)),Rates!$C$11,0) -> 0 | Q68: =IF(ISNUMBER(SEARCH("supplies",$O68)),Rates!$C$12,0) -> 25 | R68: =$M68-$N68+$P68+$Q68 -> 387.25 | S68: 387.25 | T68: =ROUND($R68-$S68,2) -> 0 | U68: =IF(ABS($T68)<0.02,"OK","CHECK") -> OK
A69: CH-066 | B69: FAM-040 | C69: MARCHETTI | D69: Ingvar | E69: Saturday | F69: Enrolled | G69: JAN-2026 | H69: 2026-031 | I69: =IF($J69<>"",$J69,IF($E69="Wednesday",INDEX(Terms!$D$4:$D$5,MATCH($G69,Terms!$A$4:$A$5,0)),INDEX(Terms!$C$4:$C$5,MATCH($G69,Terms!$A$4:$A$5,0)))) -> 21 | K69: =COUNTIFS($B$4:$B$500,$B69,$F$4:$F$500,"Enrolled") -> 1 | L69: =IF($F69<>"Enrolled",0,IF($K69=0,0,IF($E69="Wednesday",Rates!$C$9,INDEX(Rates!$C$4:$C$7,MIN($K69,4))/$K69))) -> 19.5 | M69: =ROUND($L69*$I69,2) -> 409.5 | N69: 0 | O69: supplies | P69: =IF(ISNUMBER(SEARCH("reg",$O69)),Rates!$C$11,0) -> 0 | Q69: =IF(ISNUMBER(SEARCH("supplies",$O69)),Rates!$C$12,0) -> 25 | R69: =$M69-$N69+$P69+$Q69 -> 434.5 | S69: 434.5 | T69: =ROUND($R69-$S69,2) -> 0 | U69: =IF(ABS($T69)<0.02,"OK","CHECK") -> OK | V69: roster PAID: paid
A70: CH-067 | B70: FAM-041 | C70: NAKASHIMA | D70: Hektor | E70: Saturday | F70: Enrolled | G70: JAN-2026 | H70: 2026-032 | I70: =IF($J70<>"",$J70,IF($E70="Wednesday",INDEX(Terms!$D$4:$D$5,MATCH($G70,Terms!$A$4:$A$5,0)),INDEX(Terms!$C$4:$C$5,MATCH($G70,Terms!$A$4:$A$5,0)))) -> 21 | K70: =COUNTIFS($B$4:$B$500,$B70,$F$4:$F$500,"Enrolled") -> 1 | L70: =IF($F70<>"Enrolled",0,IF($K70=0,0,IF($E70="Wednesday",Rates!$C$9,INDEX(Rates!$C$4:$C$7,MIN($K70,4))/$K70))) -> 19.5 | M70: =ROUND($L70*$I70,2) -> 409.5 | N70: 0 | O70: supplies | P70: =IF(ISNUMBER(SEARCH("reg",$O70)),Rates!$C$11,0) -> 0 | Q70: =IF(ISNUMBER(SEARCH("supplies",$O70)),Rates!$C$12,0) -> 25 | R70: =$M70-$N70+$P70+$Q70 -> 434.5 | S70: 434.5 | T70: =ROUND($R70-$S70,2) -> 0 | U70: =IF(ABS($T70)<0.02,"OK","CHECK") -> OK | V70: roster PAID: part paid
A71: CH-068 | B71: FAM-042 | C71: NAKASHIMA-PELLETIER | D71: Anouk | E71: Saturday | F71: Enrolled | G71: JAN-2026 | H71: 2026-003a | I71: =IF($J71<>"",$J71,IF($E71="Wednesday",INDEX(Terms!$D$4:$D$5,MATCH($G71,Terms!$A$4:$A$5,0)),INDEX(Terms!$C$4:$C$5,MATCH($G71,Terms!$A$4:$A$5,0)))) -> 21 | K71: =COUNTIFS($B$4:$B$500,$B71,$F$4:$F$500,"Enrolled") -> 2 | L71: =IF($F71<>"Enrolled",0,IF($K71=0,0,IF($E71="Wednesday",Rates!$C$9,INDEX(Rates!$C$4:$C$7,MIN($K71,4))/$K71))) -> 17.25 | M71: =ROUND($L71*$I71,2) -> 362.25 | N71: 0 | O71: supplies | P71: =IF(ISNUMBER(SEARCH("reg",$O71)),Rates!$C$11,0) -> 0 | Q71: =IF(ISNUMBER(SEARCH("supplies",$O71)),Rates!$C$12,0) -> 25 | R71: =$M71-$N71+$P71+$Q71 -> 387.25 | S71: 387.25 | T71: =ROUND($R71-$S71,2) -> 0 | U71: =IF(ABS($T71)<0.02,"OK","CHECK") -> OK | V71: roster PAID: part paid
A72: CH-069 | B72: FAM-042 | C72: NAKASHIMA-PELLETIER | D72: Ilaria | E72: Saturday | F72: Enrolled | G72: JAN-2026 | H72: 2026-003 | I72: =IF($J72<>"",$J72,IF($E72="Wednesday",INDEX(Terms!$D$4:$D$5,MATCH($G72,Terms!$A$4:$A$5,0)),INDEX(Terms!$C$4:$C$5,MATCH($G72,Terms!$A$4:$A$5,0)))) -> 21 | K72: =COUNTIFS($B$4:$B$500,$B72,$F$4:$F$500,"Enrolled") -> 2 | L72: =IF($F72<>"Enrolled",0,IF($K72=0,0,IF($E72="Wednesday",Rates!$C$9,INDEX(Rates!$C$4:$C$7,MIN($K72,4))/$K72))) -> 17.25 | M72: =ROUND($L72*$I72,2) -> 362.25 | N72: 0 | O72: supplies | P72: =IF(ISNUMBER(SEARCH("reg",$O72)),Rates!$C$11,0) -> 0 | Q72: =IF(ISNUMBER(SEARCH("supplies",$O72)),Rates!$C$12,0) -> 25 | R72: =$M72-$N72+$P72+$Q72 -> 387.25 | S72: 380.25 | T72: =ROUND($R72-$S72,2) -> 7 | U72: =IF(ABS($T72)<0.02,"OK","CHECK") -> CHECK | V72: roster PAID: paid
A73: CH-070 | B73: FAM-043 | C73: NWACHUKWU | D73: Giulia | E73: Saturday | F73: Enrolled | G73: JAN-2026 | H73: 2026-033 | I73: =IF($J73<>"",$J73,IF($E73="Wednesday",INDEX(Terms!$D$4:$D$5,MATCH($G73,Terms!$A$4:$A$5,0)),INDEX(Terms!$C$4:$C$5,MATCH($G73,Terms!$A$4:$A$5,0)))) -> 21 | K73: =COUNTIFS($B$4:$B$500,$B73,$F$4:$F$500,"Enrolled") -> 1 | L73: =IF($F73<>"Enrolled",0,IF($K73=0,0,IF($E73="Wednesday",Rates!$C$9,INDEX(Rates!$C$4:$C$7,MIN($K73,4))/$K73))) -> 19.5 | M73: =ROUND($L73*$I73,2) -> 409.5 | N73: 0 | P73: =IF(ISNUMBER(SEARCH("reg",$O73)),Rates!$C$11,0) -> 0 | Q73: =IF(ISNUMBER(SEARCH("supplies",$O73)),Rates!$C$12,0) -> 0 | R73: =$M73-$N73+$P73+$Q73 -> 409.5 | S73: 409.5 | T73: =ROUND($R73-$S73,2) -> 0 | U73: =IF(ABS($T73)<0.02,"OK","CHECK") -> OK | V73: roster PAID: paid
A74: CH-071 | B74: FAM-044 | C74: OKONKWO | D74: Juniper | E74: Saturday | F74: Enrolled | G74: JAN-2026 | H74: 2026-034 | I74: =IF($J74<>"",$J74,IF($E74="Wednesday",INDEX(Terms!$D$4:$D$5,MATCH($G74,Terms!$A$4:$A$5,0)),INDEX(Terms!$C$4:$C$5,MATCH($G74,Terms!$A$4:$A$5,0)))) -> 21 | K74: =COUNTIFS($B$4:$B$500,$B74,$F$4:$F$500,"Enrolled") -> 1 | L74: =IF($F74<>"Enrolled",0,IF($K74=0,0,IF($E74="Wednesday",Rates!$C$9,INDEX(Rates!$C$4:$C$7,MIN($K74,4))/$K74))) -> 19.5 | M74: =ROUND($L74*$I74,2) -> 409.5 | N74: 0 | O74: supplies | P74: =IF(ISNUMBER(SEARCH("reg",$O74)),Rates!$C$11,0) -> 0 | Q74: =IF(ISNUMBER(SEARCH("supplies",$O74)),Rates!$C$12,0) -> 25 | R74: =$M74-$N74+$P74+$Q74 -> 434.5 | S74: 434.5 | T74: =ROUND($R74-$S74,2) -> 0 | U74: =IF(ABS($T74)<0.02,"OK","CHECK") -> OK | V74: roster PAID: part paid
A75: CH-072 | B75: FAM-045 | C75: PELLETIER | D75: Otto | E75: Saturday | F75: Enrolled | G75: JAN-2026 | H75: 2026-008 | I75: =IF($J75<>"",$J75,IF($E75="Wednesday",INDEX(Terms!$D$4:$D$5,MATCH($G75,Terms!$A$4:$A$5,0)),INDEX(Terms!$C$4:$C$5,MATCH($G75,Terms!$A$4:$A$5,0)))) -> 21 | K75: =COUNTIFS($B$4:$B$500,$B75,$F$4:$F$500,"Enrolled") -> 1 | L75: =IF($F75<>"Enrolled",0,IF($K75=0,0,IF($E75="Wednesday",Rates!$C$9,INDEX(Rates!$C$4:$C$7,MIN($K75,4))/$K75))) -> 19.5 | M75: =ROUND($L75*$I75,2) -> 409.5 | N75: 0 | P75: =IF(ISNUMBER(SEARCH("reg",$O75)),Rates!$C$11,0) -> 0 | Q75: =IF(ISNUMBER(SEARCH("supplies",$O75)),Rates!$C$12,0) -> 0 | R75: =$M75-$N75+$P75+$Q75 -> 409.5 | S75: 409.5 | T75: =ROUND($R75-$S75,2) -> 0 | U75: =IF(ABS($T75)<0.02,"OK","CHECK") -> OK | V75: roster PAID: part paid
A76: CH-073 | B76: FAM-046 | C76: PERREAULT | D76: Amara | E76: Saturday | F76: Enrolled | G76: JAN-2026 | H76: 2026-036 | I76: =IF($J76<>"",$J76,IF($E76="Wednesday",INDEX(Terms!$D$4:$D$5,MATCH($G76,Terms!$A$4:$A$5,0)),INDEX(Terms!$C$4:$C$5,MATCH($G76,Terms!$A$4:$A$5,0)))) -> 21 | K76: =COUNTIFS($B$4:$B$500,$B76,$F$4:$F$500,"Enrolled") -> 2 | L76: =IF($F76<>"Enrolled",0,IF($K76=0,0,IF($E76="Wednesday",Rates!$C$9,INDEX(Rates!$C$4:$C$7,MIN($K76,4))/$K76))) -> 17.25 | M76: =ROUND($L76*$I76,2) -> 362.25 | N76: 0 | O76: reg | P76: =IF(ISNUMBER(SEARCH("reg",$O76)),Rates!$C$11,0) -> 25 | Q76: =IF(ISNUMBER(SEARCH("supplies",$O76)),Rates!$C$12,0) -> 0 | R76: =$M76-$N76+$P76+$Q76 -> 387.25 | S76: 387.25 | T76: =ROUND($R76-$S76,2) -> 0 | U76: =IF(ABS($T76)<0.02,"OK","CHECK") -> OK | V76: roster PAID: paid
A77: CH-074 | B77: FAM-046 | C77: PERREAULT | D77: Valentin | E77: Saturday | F77: Enrolled | G77: JAN-2026 | H77: 2026-036a | I77: =IF($J77<>"",$J77,IF($E77="Wednesday",INDEX(Terms!$D$4:$D$5,MATCH($G77,Terms!$A$4:$A$5,0)),INDEX(Terms!$C$4:$C$5,MATCH($G77,Terms!$A$4:$A$5,0)))) -> 21 | K77: =COUNTIFS($B$4:$B$500,$B77,$F$4:$F$500,"Enrolled") -> 2 | L77: =IF($F77<>"Enrolled",0,IF($K77=0,0,IF($E77="Wednesday",Rates!$C$9,INDEX(Rates!$C$4:$C$7,MIN($K77,4))/$K77))) -> 17.25 | M77: =ROUND($L77*$I77,2) -> 362.25 | N77: 0 | O77: supplies | P77: =IF(ISNUMBER(SEARCH("reg",$O77)),Rates!$C$11,0) -> 0 | Q77: =IF(ISNUMBER(SEARCH("supplies",$O77)),Rates!$C$12,0) -> 25 | R77: =$M77-$N77+$P77+$Q77 -> 387.25 | S77: 387.25 | T77: =ROUND($R77-$S77,2) -> 0 | U77: =IF(ABS($T77)<0.02,"OK","CHECK") -> OK
A78: CH-075 | B78: FAM-047 | C78: QUILLIAM | D78: Anouk | E78: Saturday | F78: Enrolled | G78: JAN-2026 | H78: 2026-037 | I78: =IF($J78<>"",$J78,IF($E78="Wednesday",INDEX(Terms!$D$4:$D$5,MATCH($G78,Terms!$A$4:$A$5,0)),INDEX(Terms!$C$4:$C$5,MATCH($G78,Terms!$A$4:$A$5,0)))) -> 21 | K78: =COUNTIFS($B$4:$B$500,$B78,$F$4:$F$500,"Enrolled") -> 2 | L78: =IF($F78<>"Enrolled",0,IF($K78=0,0,IF($E78="Wednesday",Rates!$C$9,INDEX(Rates!$C$4:$C$7,MIN($K78,4))/$K78))) -> 17.25 | M78: =ROUND($L78*$I78,2) -> 362.25 | N78: 0 | O78: supplies | P78: =IF(ISNUMBER(SEARCH("reg",$O78)),Rates!$C$11,0) -> 0 | Q78: =IF(ISNUMBER(SEARCH("supplies",$O78)),Rates!$C$12,0) -> 25 | R78: =$M78-$N78+$P78+$Q78 -> 387.25 | S78: 387.25 | T78: =ROUND($R78-$S78,2) -> 0 | U78: =IF(ABS($T78)<0.02,"OK","CHECK") -> OK | V78: roster PAID: paid
A79: CH-076 | B79: FAM-047 | C79: QUILLIAM | D79: Fabienne | E79: Saturday | F79: Enrolled | G79: JAN-2026 | H79: 2026-037a | I79: =IF($J79<>"",$J79,IF($E79="Wednesday",INDEX(Terms!$D$4:$D$5,MATCH($G79,Terms!$A$4:$A$5,0)),INDEX(Terms!$C$4:$C$5,MATCH($G79,Terms!$A$4:$A$5,0)))) -> 21 | K79: =COUNTIFS($B$4:$B$500,$B79,$F$4:$F$500,"Enrolled") -> 2 | L79: =IF($F79<>"Enrolled",0,IF($K79=0,0,IF($E79="Wednesday",Rates!$C$9,INDEX(Rates!$C$4:$C$7,MIN($K79,4))/$K79))) -> 17.25 | M79: =ROUND($L79*$I79,2) -> 362.25 | N79: 0 | O79: supplies | P79: =IF(ISNUMBER(SEARCH("reg",$O79)),Rates!$C$11,0) -> 0 | Q79: =IF(ISNUMBER(SEARCH("supplies",$O79)),Rates!$C$12,0) -> 25 | R79: =$M79-$N79+$P79+$Q79 -> 387.25 | S79: 387.25 | T79: =ROUND($R79-$S79,2) -> 0 | U79: =IF(ABS($T79)<0.02,"OK","CHECK") -> OK | V79: roster PAID: paid
A80: CH-077 | B80: FAM-048 | C80: RASMUSSEN | D80: Valentin | E80: Saturday | F80: Enrolled | G80: JAN-2026 | H80: 2026-038 | I80: =IF($J80<>"",$J80,IF($E80="Wednesday",INDEX(Terms!$D$4:$D$5,MATCH($G80,Terms!$A$4:$A$5,0)),INDEX(Terms!$C$4:$C$5,MATCH($G80,Terms!$A$4:$A$5,0)))) -> 21 | K80: =COUNTIFS($B$4:$B$500,$B80,$F$4:$F$500,"Enrolled") -> 1 | L80: =IF($F80<>"Enrolled",0,IF($K80=0,0,IF($E80="Wednesday",Rates!$C$9,INDEX(Rates!$C$4:$C$7,MIN($K80,4))/$K80))) -> 19.5 | M80: =ROUND($L80*$I80,2) -> 409.5 | N80: 0 | O80: reg, supplies | P80: =IF(ISNUMBER(SEARCH("reg",$O80)),Rates!$C$11,0) -> 25 | Q80: =IF(ISNUMBER(SEARCH("supplies",$O80)),Rates!$C$12,0) -> 25 | R80: =$M80-$N80+$P80+$Q80 -> 459.5 | S80: 459.5 | T80: =ROUND($R80-$S80,2) -> 0 | U80: =IF(ABS($T80)<0.02,"OK","CHECK") -> OK | V80: roster PAID: part paid
A81: CH-078 | B81: FAM-049 | C81: ROCHETEAU | D81: Valentin | E81: Saturday | F81: Enrolled | G81: JAN-2026 | H81: 2026-039 | I81: =IF($J81<>"",$J81,IF($E81="Wednesday",INDEX(Terms!$D$4:$D$5,MATCH($G81,Terms!$A$4:$A$5,0)),INDEX(Terms!$C$4:$C$5,MATCH($G81,Terms!$A$4:$A$5,0)))) -> 21 | K81: =COUNTIFS($B$4:$B$500,$B81,$F$4:$F$500,"Enrolled") -> 1 | L81: =IF($F81<>"Enrolled",0,IF($K81=0,0,IF($E81="Wednesday",Rates!$C$9,INDEX(Rates!$C$4:$C$7,MIN($K81,4))/$K81))) -> 19.5 | M81: =ROUND($L81*$I81,2) -> 409.5 | N81: 0 | O81: supplies | P81: =IF(ISNUMBER(SEARCH("reg",$O81)),Rates!$C$11,0) -> 0 | Q81: =IF(ISNUMBER(SEARCH("supplies",$O81)),Rates!$C$12,0) -> 25 | R81: =$M81-$N81+$P81+$Q81 -> 434.5 | S81: 434.5 | T81: =ROUND($R81-$S81,2) -> 0 | U81: =IF(ABS($T81)<0.02,"OK","CHECK") -> OK | V81: roster PAID: part paid
A82: CH-079 | B82: FAM-050 | C82: SANDOVAL | D82: Juniper | E82: Saturday | F82: Enrolled | G82: JAN-2026 | H82: 2026-040a | I82: =IF($J82<>"",$J82,IF($E82="Wednesday",INDEX(Terms!$D$4:$D$5,MATCH($G82,Terms!$A$4:$A$5,0)),INDEX(Terms!$C$4:$C$5,MATCH($G82,Terms!$A$4:$A$5,0)))) -> 21 | K82: =COUNTIFS($B$4:$B$500,$B82,$F$4:$F$500,"Enrolled") -> 2 | L82: =IF($F82<>"Enrolled",0,IF($K82=0,0,IF($E82="Wednesday",Rates!$C$9,INDEX(Rates!$C$4:$C$7,MIN($K82,4))/$K82))) -> 17.25 | M82: =ROUND($L82*$I82,2) -> 362.25 | N82: 0 | O82: supplies | P82: =IF(ISNUMBER(SEARCH("reg",$O82)),Rates!$C$11,0) -> 0 | Q82: =IF(ISNUMBER(SEARCH("supplies",$O82)),Rates!$C$12,0) -> 25 | R82: =$M82-$N82+$P82+$Q82 -> 387.25 | S82: 387.25 | T82: =ROUND($R82-$S82,2) -> 0 | U82: =IF(ABS($T82)<0.02,"OK","CHECK") -> OK | V82: roster PAID: paid
A83: CH-080 | B83: FAM-050 | C83: SANDOVAL | D83: Kaia | E83: Saturday | F83: Enrolled | G83: JAN-2026 | H83: 2026-040 | I83: =IF($J83<>"",$J83,IF($E83="Wednesday",INDEX(Terms!$D$4:$D$5,MATCH($G83,Terms!$A$4:$A$5,0)),INDEX(Terms!$C$4:$C$5,MATCH($G83,Terms!$A$4:$A$5,0)))) -> 21 | K83: =COUNTIFS($B$4:$B$500,$B83,$F$4:$F$500,"Enrolled") -> 2 | L83: =IF($F83<>"Enrolled",0,IF($K83=0,0,IF($E83="Wednesday",Rates!$C$9,INDEX(Rates!$C$4:$C$7,MIN($K83,4))/$K83))) -> 17.25 | M83: =ROUND($L83*$I83,2) -> 362.25 | N83: 0 | O83: supplies | P83: =IF(ISNUMBER(SEARCH("reg",$O83)),Rates!$C$11,0) -> 0 | Q83: =IF(ISNUMBER(SEARCH("supplies",$O83)),Rates!$C$12,0) -> 25 | R83: =$M83-$N83+$P83+$Q83 -> 387.25 | S83: 387.25 | T83: =ROUND($R83-$S83,2) -> 0 | U83: =IF(ABS($T83)<0.02,"OK","CHECK") -> OK | V83: roster PAID: paid
A84: CH-081 | B84: FAM-051 | C84: SIGURDSSON | D84: Anouk | E84: Saturday | F84: Enrolled | G84: JAN-2026 | H84: 2026-041a | I84: =IF($J84<>"",$J84,IF($E84="Wednesday",INDEX(Terms!$D$4:$D$5,MATCH($G84,Terms!$A$4:$A$5,0)),INDEX(Terms!$C$4:$C$5,MATCH($G84,Terms!$A$4:$A$5,0)))) -> 21 | K84: =COUNTIFS($B$4:$B$500,$B84,$F$4:$F$500,"Enrolled") -> 2 | L84: =IF($F84<>"Enrolled",0,IF($K84=0,0,IF($E84="Wednesday",Rates!$C$9,INDEX(Rates!$C$4:$C$7,MIN($K84,4))/$K84))) -> 17.25 | M84: =ROUND($L84*$I84,2) -> 362.25 | N84: 0 | P84: =IF(ISNUMBER(SEARCH("reg",$O84)),Rates!$C$11,0) -> 0 | Q84: =IF(ISNUMBER(SEARCH("supplies",$O84)),Rates!$C$12,0) -> 0 | R84: =$M84-$N84+$P84+$Q84 -> 362.25 | S84: 362.25 | T84: =ROUND($R84-$S84,2) -> 0 | U84: =IF(ABS($T84)<0.02,"OK","CHECK") -> OK | V84: roster PAID: paid
A85: CH-082 | B85: FAM-051 | C85: SIGURDSSON | D85: Piero | E85: Saturday | F85: Enrolled | G85: JAN-2026 | H85: 2026-041 | I85: =IF($J85<>"",$J85,IF($E85="Wednesday",INDEX(Terms!$D$4:$D$5,MATCH($G85,Terms!$A$4:$A$5,0)),INDEX(Terms!$C$4:$C$5,MATCH($G85,Terms!$A$4:$A$5,0)))) -> 21 | K85: =COUNTIFS($B$4:$B$500,$B85,$F$4:$F$500,"Enrolled") -> 2 | L85: =IF($F85<>"Enrolled",0,IF($K85=0,0,IF($E85="Wednesday",Rates!$C$9,INDEX(Rates!$C$4:$C$7,MIN($K85,4))/$K85))) -> 17.25 | M85: =ROUND($L85*$I85,2) -> 362.25 | N85: 0 | O85: supplies | P85: =IF(ISNUMBER(SEARCH("reg",$O85)),Rates!$C$11,0) -> 0 | Q85: =IF(ISNUMBER(SEARCH("supplies",$O85)),Rates!$C$12,0) -> 25 | R85: =$M85-$N85+$P85+$Q85 -> 387.25 | S85: 387.25 | T85: =ROUND($R85-$S85,2) -> 0 | U85: =IF(ABS($T85)<0.02,"OK","CHECK") -> OK | V85: roster PAID: paid
A86: CH-083 | B86: FAM-052 | C86: THIBODEAUX | D86: Kaia | E86: Saturday | F86: Enrolled | G86: JAN-2026 | H86: 2026-042 | I86: =IF($J86<>"",$J86,IF($E86="Wednesday",INDEX(Terms!$D$4:$D$5,MATCH($G86,Terms!$A$4:$A$5,0)),INDEX(Terms!$C$4:$C$5,MATCH($G86,Terms!$A$4:$A$5,0)))) -> 21 | K86: =COUNTIFS($B$4:$B$500,$B86,$F$4:$F$500,"Enrolled") -> 1 | L86: =IF($F86<>"Enrolled",0,IF($K86=0,0,IF($E86="Wednesday",Rates!$C$9,INDEX(Rates!$C$4:$C$7,MIN($K86,4))/$K86))) -> 19.5 | M86: =ROUND($L86*$I86,2) -> 409.5 | N86: 0 | P86: =IF(ISNUMBER(SEARCH("reg",$O86)),Rates!$C$11,0) -> 0 | Q86: =IF(ISNUMBER(SEARCH("supplies",$O86)),Rates!$C$12,0) -> 0 | R86: =$M86-$N86+$P86+$Q86 -> 409.5 | S86: 409.5 | T86: =ROUND($R86-$S86,2) -> 0 | U86: =IF(ABS($T86)<0.02,"OK","CHECK") -> OK
A87: CH-084 | B87: FAM-053 | C87: TREVELYAN | D87: Ezra | E87: Saturday | F87: Enrolled | G87: JAN-2026 | H87: 2026-043a | I87: =IF($J87<>"",$J87,IF($E87="Wednesday",INDEX(Terms!$D$4:$D$5,MATCH($G87,Terms!$A$4:$A$5,0)),INDEX(Terms!$C$4:$C$5,MATCH($G87,Terms!$A$4:$A$5,0)))) -> 21 | K87: =COUNTIFS($B$4:$B$500,$B87,$F$4:$F$500,"Enrolled") -> 2 | L87: =IF($F87<>"Enrolled",0,IF($K87=0,0,IF($E87="Wednesday",Rates!$C$9,INDEX(Rates!$C$4:$C$7,MIN($K87,4))/$K87))) -> 17.25 | M87: =ROUND($L87*$I87,2) -> 362.25 | N87: 0 | O87: supplies | P87: =IF(ISNUMBER(SEARCH("reg",$O87)),Rates!$C$11,0) -> 0 | Q87: =IF(ISNUMBER(SEARCH("supplies",$O87)),Rates!$C$12,0) -> 25 | R87: =$M87-$N87+$P87+$Q87 -> 387.25 | S87: 387.25 | T87: =ROUND($R87-$S87,2) -> 0 | U87: =IF(ABS($T87)<0.02,"OK","CHECK") -> OK
A88: CH-085 | B88: FAM-053 | C88: TREVELYAN | D88: Fionn | E88: Saturday | F88: Enrolled | G88: JAN-2026 | H88: 2026-043 | I88: =IF($J88<>"",$J88,IF($E88="Wednesday",INDEX(Terms!$D$4:$D$5,MATCH($G88,Terms!$A$4:$A$5,0)),INDEX(Terms!$C$4:$C$5,MATCH($G88,Terms!$A$4:$A$5,0)))) -> 21 | K88: =COUNTIFS($B$4:$B$500,$B88,$F$4:$F$500,"Enrolled") -> 2 | L88: =IF($F88<>"Enrolled",0,IF($K88=0,0,IF($E88="Wednesday",Rates!$C$9,INDEX(Rates!$C$4:$C$7,MIN($K88,4))/$K88))) -> 17.25 | M88: =ROUND($L88*$I88,2) -> 362.25 | N88: 0 | O88: reg, supplies | P88: =IF(ISNUMBER(SEARCH("reg",$O88)),Rates!$C$11,0) -> 25 | Q88: =IF(ISNUMBER(SEARCH("supplies",$O88)),Rates!$C$12,0) -> 25 | R88: =$M88-$N88+$P88+$Q88 -> 412.25 | S88: 412.25 | T88: =ROUND($R88-$S88,2) -> 0 | U88: =IF(ABS($T88)<0.02,"OK","CHECK") -> OK
A89: CH-086 | B89: FAM-054 | C89: UCHENDU | D89: Valentin | E89: Saturday | F89: Enrolled | G89: JAN-2026 | H89: 2026-044 | I89: =IF($J89<>"",$J89,IF($E89="Wednesday",INDEX(Terms!$D$4:$D$5,MATCH($G89,Terms!$A$4:$A$5,0)),INDEX(Terms!$C$4:$C$5,MATCH($G89,Terms!$A$4:$A$5,0)))) -> 21 | K89: =COUNTIFS($B$4:$B$500,$B89,$F$4:$F$500,"Enrolled") -> 1 | L89: =IF($F89<>"Enrolled",0,IF($K89=0,0,IF($E89="Wednesday",Rates!$C$9,INDEX(Rates!$C$4:$C$7,MIN($K89,4))/$K89))) -> 19.5 | M89: =ROUND($L89*$I89,2) -> 409.5 | N89: 0 | O89: supplies | P89: =IF(ISNUMBER(SEARCH("reg",$O89)),Rates!$C$11,0) -> 0 | Q89: =IF(ISNUMBER(SEARCH("supplies",$O89)),Rates!$C$12,0) -> 25 | R89: =$M89-$N89+$P89+$Q89 -> 434.5 | S89: 434.5 | T89: =ROUND($R89-$S89,2) -> 0 | U89: =IF(ABS($T89)<0.02,"OK","CHECK") -> OK | V89: roster PAID: paid
A90: CH-087 | B90: FAM-055 | C90: VANTERPOOL | D90: Halima | E90: Saturday | F90: Enrolled | G90: JAN-2026 | H90: 2026-045 | I90: =IF($J90<>"",$J90,IF($E90="Wednesday",INDEX(Terms!$D$4:$D$5,MATCH($G90,Terms!$A$4:$A$5,0)),INDEX(Terms!$C$4:$C$5,MATCH($G90,Terms!$A$4:$A$5,0)))) -> 21 | K90: =COUNTIFS($B$4:$B$500,$B90,$F$4:$F$500,"Enrolled") -> 1 | L90: =IF($F90<>"Enrolled",0,IF($K90=0,0,IF($E90="Wednesday",Rates!$C$9,INDEX(Rates!$C$4:$C$7,MIN($K90,4))/$K90))) -> 19.5 | M90: =ROUND($L90*$I90,2) -> 409.5 | N90: 0 | O90: supplies | P90: =IF(ISNUMBER(SEARCH("reg",$O90)),Rates!$C$11,0) -> 0 | Q90: =IF(ISNUMBER(SEARCH("supplies",$O90)),Rates!$C$12,0) -> 25 | R90: =$M90-$N90+$P90+$Q90 -> 434.5 | S90: 434.5 | T90: =ROUND($R90-$S90,2) -> 0 | U90: =IF(ABS($T90)<0.02,"OK","CHECK") -> OK | V90: roster PAID: paid
A91: CH-088 | B91: FAM-056 | C91: VILLALOBOS | D91: Celestine | E91: Saturday | F91: Enrolled | G91: JAN-2026 | H91: 2026-046 | I91: =IF($J91<>"",$J91,IF($E91="Wednesday",INDEX(Terms!$D$4:$D$5,MATCH($G91,Terms!$A$4:$A$5,0)),INDEX(Terms!$C$4:$C$5,MATCH($G91,Terms!$A$4:$A$5,0)))) -> 21 | K91: =COUNTIFS($B$4:$B$500,$B91,$F$4:$F$500,"Enrolled") -> 1 | L91: =IF($F91<>"Enrolled",0,IF($K91=0,0,IF($E91="Wednesday",Rates!$C$9,INDEX(Rates!$C$4:$C$7,MIN($K91,4))/$K91))) -> 19.5 | M91: =ROUND($L91*$I91,2) -> 409.5 | N91: 0 | P91: =IF(ISNUMBER(SEARCH("reg",$O91)),Rates!$C$11,0) -> 0 | Q91: =IF(ISNUMBER(SEARCH("supplies",$O91)),Rates!$C$12,0) -> 0 | R91: =$M91-$N91+$P91+$Q91 -> 409.5 | S91: 409.5 | T91: =ROUND($R91-$S91,2) -> 0 | U91: =IF(ABS($T91)<0.02,"OK","CHECK") -> OK | V91: roster PAID: paid
A92: CH-089 | B92: FAM-057 | C92: WENDELIN | D92: Thibault | E92: Saturday | F92: Enrolled | G92: JAN-2026 | H92: 2026-047 | I92: =IF($J92<>"",$J92,IF($E92="Wednesday",INDEX(Terms!$D$4:$D$5,MATCH($G92,Terms!$A$4:$A$5,0)),INDEX(Terms!$C$4:$C$5,MATCH($G92,Terms!$A$4:$A$5,0)))) -> 21 | K92: =COUNTIFS($B$4:$B$500,$B92,$F$4:$F$500,"Enrolled") -> 1 | L92: =IF($F92<>"Enrolled",0,IF($K92=0,0,IF($E92="Wednesday",Rates!$C$9,INDEX(Rates!$C$4:$C$7,MIN($K92,4))/$K92))) -> 19.5 | M92: =ROUND($L92*$I92,2) -> 409.5 | N92: 0 | O92: supplies | P92: =IF(ISNUMBER(SEARCH("reg",$O92)),Rates!$C$11,0) -> 0 | Q92: =IF(ISNUMBER(SEARCH("supplies",$O92)),Rates!$C$12,0) -> 25 | R92: =$M92-$N92+$P92+$Q92 -> 434.5 | S92: 434.5 | T92: =ROUND($R92-$S92,2) -> 0 | U92: =IF(ABS($T92)<0.02,"OK","CHECK") -> OK | V92: roster PAID: paid
A93: CH-090 | B93: FAM-058 | C93: WOJCIECHOWSKI | D93: Tamsin | E93: Saturday | F93: Enrolled | G93: JAN-2026 | H93: 2026-048 | I93: =IF($J93<>"",$J93,IF($E93="Wednesday",INDEX(Terms!$D$4:$D$5,MATCH($G93,Terms!$A$4:$A$5,0)),INDEX(Terms!$C$4:$C$5,MATCH($G93,Terms!$A$4:$A$5,0)))) -> 21 | K93: =COUNTIFS($B$4:$B$500,$B93,$F$4:$F$500,"Enrolled") -> 1 | L93: =IF($F93<>"Enrolled",0,IF($K93=0,0,IF($E93="Wednesday",Rates!$C$9,INDEX(Rates!$C$4:$C$7,MIN($K93,4))/$K93))) -> 19.5 | M93: =ROUND($L93*$I93,2) -> 409.5 | N93: 0 | O93: supplies | P93: =IF(ISNUMBER(SEARCH("reg",$O93)),Rates!$C$11,0) -> 0 | Q93: =IF(ISNUMBER(SEARCH("supplies",$O93)),Rates!$C$12,0) -> 25 | R93: =$M93-$N93+$P93+$Q93 -> 434.5 | S93: 434.5 | T93: =ROUND($R93-$S93,2) -> 0 | U93: =IF(ABS($T93)<0.02,"OK","CHECK") -> OK
A94: CH-091 | B94: FAM-059 | C94: YANKOVIC | D94: Kwame | E94: Saturday | F94: Enrolled | G94: JAN-2026 | H94: 2026-049 | I94: =IF($J94<>"",$J94,IF($E94="Wednesday",INDEX(Terms!$D$4:$D$5,MATCH($G94,Terms!$A$4:$A$5,0)),INDEX(Terms!$C$4:$C$5,MATCH($G94,Terms!$A$4:$A$5,0)))) -> 21 | K94: =COUNTIFS($B$4:$B$500,$B94,$F$4:$F$500,"Enrolled") -> 1 | L94: =IF($F94<>"Enrolled",0,IF($K94=0,0,IF($E94="Wednesday",Rates!$C$9,INDEX(Rates!$C$4:$C$7,MIN($K94,4))/$K94))) -> 19.5 | M94: =ROUND($L94*$I94,2) -> 409.5 | N94: 0 | P94: =IF(ISNUMBER(SEARCH("reg",$O94)),Rates!$C$11,0) -> 0 | Q94: =IF(ISNUMBER(SEARCH("supplies",$O94)),Rates!$C$12,0) -> 0 | R94: =$M94-$N94+$P94+$Q94 -> 409.5 | S94: 409.5 | T94: =ROUND($R94-$S94,2) -> 0 | U94: =IF(ABS($T94)<0.02,"OK","CHECK") -> OK | V94: roster PAID: paid
A95: CH-092 | B95: FAM-060 | C95: ZABALA | D95: Celestine | E95: Saturday | F95: Enrolled | G95: JAN-2026 | H95: 2026-050a | I95: =IF($J95<>"",$J95,IF($E95="Wednesday",INDEX(Terms!$D$4:$D$5,MATCH($G95,Terms!$A$4:$A$5,0)),INDEX(Terms!$C$4:$C$5,MATCH($G95,Terms!$A$4:$A$5,0)))) -> 21 | K95: =COUNTIFS($B$4:$B$500,$B95,$F$4:$F$500,"Enrolled") -> 2 | L95: =IF($F95<>"Enrolled",0,IF($K95=0,0,IF($E95="Wednesday",Rates!$C$9,INDEX(Rates!$C$4:$C$7,MIN($K95,4))/$K95))) -> 17.25 | M95: =ROUND($L95*$I95,2) -> 362.25 | N95: 0 | O95: supplies | P95: =IF(ISNUMBER(SEARCH("reg",$O95)),Rates!$C$11,0) -> 0 | Q95: =IF(ISNUMBER(SEARCH("supplies",$O95)),Rates!$C$12,0) -> 25 | R95: =$M95-$N95+$P95+$Q95 -> 387.25 | S95: 387.25 | T95: =ROUND($R95-$S95,2) -> 0 | U95: =IF(ABS($T95)<0.02,"OK","CHECK") -> OK
A96: CH-093 | B96: FAM-060 | C96: ZABALA | D96: Dario | E96: Saturday | F96: Enrolled | G96: JAN-2026 | H96: 2026-050 | I96: =IF($J96<>"",$J96,IF($E96="Wednesday",INDEX(Terms!$D$4:$D$5,MATCH($G96,Terms!$A$4:$A$5,0)),INDEX(Terms!$C$4:$C$5,MATCH($G96,Terms!$A$4:$A$5,0)))) -> 21 | K96: =COUNTIFS($B$4:$B$500,$B96,$F$4:$F$500,"Enrolled") -> 2 | L96: =IF($F96<>"Enrolled",0,IF($K96=0,0,IF($E96="Wednesday",Rates!$C$9,INDEX(Rates!$C$4:$C$7,MIN($K96,4))/$K96))) -> 17.25 | M96: =ROUND($L96*$I96,2) -> 362.25 | N96: 0 | P96: =IF(ISNUMBER(SEARCH("reg",$O96)),Rates!$C$11,0) -> 0 | Q96: =IF(ISNUMBER(SEARCH("supplies",$O96)),Rates!$C$12,0) -> 0 | R96: =$M96-$N96+$P96+$Q96 -> 362.25 | S96: 362.25 | T96: =ROUND($R96-$S96,2) -> 0 | U96: =IF(ABS($T96)<0.02,"OK","CHECK") -> OK | V96: roster PAID: part paid
A97: CH-094 | B97: FAM-061 | C97: ZIMMERLI | D97: Uma | E97: Saturday | F97: Enrolled | G97: JAN-2026 | H97: 2026-051 | I97: =IF($J97<>"",$J97,IF($E97="Wednesday",INDEX(Terms!$D$4:$D$5,MATCH($G97,Terms!$A$4:$A$5,0)),INDEX(Terms!$C$4:$C$5,MATCH($G97,Terms!$A$4:$A$5,0)))) -> 21 | K97: =COUNTIFS($B$4:$B$500,$B97,$F$4:$F$500,"Enrolled") -> 1 | L97: =IF($F97<>"Enrolled",0,IF($K97=0,0,IF($E97="Wednesday",Rates!$C$9,INDEX(Rates!$C$4:$C$7,MIN($K97,4))/$K97))) -> 19.5 | M97: =ROUND($L97*$I97,2) -> 409.5 | N97: 0 | P97: =IF(ISNUMBER(SEARCH("reg",$O97)),Rates!$C$11,0) -> 0 | Q97: =IF(ISNUMBER(SEARCH("supplies",$O97)),Rates!$C$12,0) -> 0 | R97: =$M97-$N97+$P97+$Q97 -> 409.5 | S97: 409.5 | T97: =ROUND($R97-$S97,2) -> 0 | U97: =IF(ABS($T97)<0.02,"OK","CHECK") -> OK | V97: roster PAID: part paid

Sheet Receipts
A1: Receipts — one row per bank line. Blue = from the bank file. Yellow = your decision. Everything else is written by the engine.
A3: Date | B3: Amount | C3: Payer (bank) | D3: Reference (bank) | E3: Term | F3: Family override (fill in) | G3: Family | H3: Allocated | I3: Tier | J3: Candidates | K3: Why | L3: Amount check | M3: Flags | N3: Full memo
A4: 46029 | B4: 434.5 | C4: ZORA VANTERPOOL | D4: Halima | E4: JAN-2026 | G4: =IF($F4<>"",$F4,$J4) -> FAM-055 | H4: =IF($G4<>"","yes","") -> yes | I4: B | J4: FAM-055 | L4: surname VANTERPOOL | M4: matches expected; JAN-2026 amount | N4: ZORA VANTERPOOL Halima BGC
A5: 46034 | B5: 434.5 | C5: VERA FALZON | D5: 2026018 | E5: JAN-2026 | G5: =IF($F5<>"",$F5,$J5) -> FAM-024 | H5: =IF($G5<>"","yes","") -> yes | I5: A | J5: FAM-024 | L5: invoice reference 2026-018 | M5: matches expected; JAN-2026 amount | N5: VERA FALZON 2026018 BGC
A6: 46038 | B6: 229.75 | C6: MARGIT RASMUSSEN | D6: 2026-039 | E6: JAN-2026 | G6: =IF($F6<>"",$F6,$J6) -> 0 | H6: =IF($G6<>"","yes","") | I6: X | K6: FAM-048, FAM-049 | L6: reference 2026-039 points to FAM-049 but the memo names FAM-048 — parent may have typed the wrong invoice number | N6: MARGIT RASMUSSEN 2026-039 BGC
A7: 46041 | B7: 217.25 | C7: INGRID ERIKSEN | D7: ERIKSE2026-017 | E7: JAN-2026 | G7: =IF($F7<>"",$F7,$J7) -> FAM-023 | H7: =IF($G7<>"","yes","") -> yes | I7: A | J7: FAM-023 | L7: invoice reference 2026-017 | M7: half of expected | N7: INGRID ERIKSEN ERIKSE2026-017 BGC
A8: 46042 | B8: 1184 | C8: GENEVIEVE BELHADJ | D8: 2026-008 | E8: JAN-2026 | G8: =IF($F8<>"",$F8,$J8) -> FAM-008 | H8: =IF($G8<>"","yes","") -> yes | I8: A | J8: FAM-008 | L8: invoice reference 2026-008 | M8: unusual (expected £774.50) | N8: GENEVIEVE BELHADJ 2026-008 BGC
A9: 46044 | B9: 217.25 | C9: MARGIT GAILLARD | D9: Esben | E9: JAN-2026 | G9: =IF($F9<>"",$F9,$J9) -> FAM-027 | H9: =IF($G9<>"","yes","") -> yes | I9: B | J9: FAM-027 | L9: child first name Esben, surname GAILLARD | M9: half of expected | N9: MARGIT GAILLARD Esben BGC
A10: 46044 | B10: 434.5 | C10: LUDOVIC ASHWORTH | D10: ASHWORTH FRENCH SCHOO | E10: JAN-2026 | G10: =IF($F10<>"",$F10,$J10) -> FAM-004 | H10: =IF($G10<>"","yes","") -> yes | I10: B | J10: FAM-004 | L10: surname ASHWORTH | M10: matches expected; JAN-2026 amount | N10: LUDOVIC ASHWORTH ASHWORTH FRENCH SCHOO BGC
A11: 46048 | B11: 204.75 | C11: KATRIN DUPLANTIER | D11: 2025-608 | E11: AUT-2025 | G11: =IF($F11<>"",$F11,$J11) -> FAM-021 | H11: =IF($G11<>"","yes","") -> yes | I11: B | J11: FAM-021 | L11: surname DUPLANTIER (prior-term reference 2025-608 — family identified, invoice not loaded) | M11: JAN-2026 amount | N11: KATRIN DUPLANTIER 2025-608 BGC
A12: 46048 | B12: 387.25 | C12: GENEVIEVE MAALOUF | D12: MAALOU2026-030 | E12: JAN-2026 | G12: =IF($F12<>"",$F12,$J12) -> FAM-039 | H12: =IF($G12<>"","yes","") -> yes | I12: A | J12: FAM-039 | L12: invoice reference 2026-030 | M12: half of expected | N12: GENEVIEVE MAALOUF MAALOU2026-030 BGC
A13: 46053 | B13: 434.5 | C13: ELODIE HASANOVIC | D13: 060 | E13: JAN-2026 | G13: =IF($F13<>"",$F13,$J13) -> FAM-031 | H13: =IF($G13<>"","yes","") -> yes | I13: B | J13: FAM-031 | L13: surname HASANOVIC | M13: matches expected; JAN-2026 amount | N13: ELODIE HASANOVIC 060 BGC
A14: 46053 | B14: 374.75 | C14: CAMILLE SIGURDSSON | D14: 2026041 | E14: JAN-2026 | G14: =IF($F14<>"",$F14,$J14) -> FAM-051 | H14: =IF($G14<>"","yes","") -> yes | I14: A | J14: FAM-051 | L14: invoice reference 2026-041 | M14: half of expected | N14: CAMILLE SIGURDSSON 2026041 BGC
A15: 46053 | B15: 1041 | C15: BETTINA DELACROIX | D15: 2026-015 | E15: JAN-2026 | G15: =IF($F15<>"",$F15,$J15) -> FAM-020 | H15: =IF($G15<>"","yes","") -> yes | I15: A | J15: FAM-020 | L15: invoice reference 2026-015 | M15: matches expected; JAN-2026 amount | N15: BETTINA DELACROIX 2026-015 BGC
A16: 46054 | B16: 434.5 | C16: NILS OKONKWO | D16: 2025-508 | E16: AUT-2025 | G16: =IF($F16<>"",$F16,$J16) -> FAM-044 | H16: =IF($G16<>"","yes","") -> yes | I16: B | J16: FAM-044 | L16: surname OKONKWO (prior-term reference 2025-508 — family identified, invoice not loaded) | M16: JAN-2026 amount | N16: NILS OKONKWO 2025-508 BGC
A17: 46057 | B17: 434.5 | C17: NILS DZIEDZIC | D17: 2026057 | E17: JAN-2026 | G17: =IF($F17<>"",$F17,$J17) -> FAM-022 | H17: =IF($G17<>"","yes","") -> yes | I17: A | J17: FAM-022 | L17: invoice reference 2026-057 | M17: matches expected; JAN-2026 amount | N17: NILS DZIEDZIC 2026057 BGC
A18: 46058 | B18: 520.5 | C18: GENEVIEVE KILBRIDE | D18: 2025-611 | E18: AUT-2025 | G18: =IF($F18<>"",$F18,$J18) -> FAM-036 | H18: =IF($G18<>"","yes","") -> yes | I18: A | J18: FAM-036 | L18: payer name previously seen with a verified reference for this family (prior-term reference 2025-611 — family identified, invoice not loaded) | N18: GENEVIEVE KILBRIDE 2025-611 BGC
A19: 46059 | B19: 229.75 | C19: MARGIT RASMUSSEN | D19: Rasmussen | E19: JAN-2026 | G19: =IF($F19<>"",$F19,$J19) -> FAM-048 | H19: =IF($G19<>"","yes","") -> yes | I19: B | J19: FAM-048 | L19: surname RASMUSSEN | M19: half of expected | N19: MARGIT RASMUSSEN Rasmussen BGC
A20: 46060 | B20: 409.5 | C20: BETTINA VILLALOBOS | D20: 2025-578 | E20: AUT-2025 | G20: =IF($F20<>"",$F20,$J20) -> FAM-056 | H20: =IF($G20<>"","yes","") -> yes | I20: B | J20: FAM-056 | L20: surname VILLALOBOS (prior-term reference 2025-578 — family identified, invoice not loaded) | M20: JAN-2026 amount | N20: BETTINA VILLALOBOS 2025-578 BGC
A21: 46060 | B21: 217.25 | C21: INGRID ERIKSEN | D21: Eriksen 2nd | E21: JAN-2026 | G21: =IF($F21<>"",$F21,$J21) -> FAM-023 | H21: =IF($G21<>"","yes","") -> yes | I21: A | J21: FAM-023 | L21: payer name previously seen with a verified reference for this family | M21: half of expected | N21: INGRID ERIKSEN Eriksen 2nd BGC
A22: 46063 | B22: 434.5 | C22: KATRIN NAKASHIMA | D22: 2026-032 | E22: JAN-2026 | G22: =IF($F22<>"",$F22,$J22) -> FAM-041 | H22: =IF($G22<>"","yes","") -> yes | I22: A | J22: FAM-041 | L22: invoice reference 2026-032 | M22: matches expected; JAN-2026 amount | N22: KATRIN NAKASHIMA 2026-032 BGC
A23: 46063 | B23: 387.25 | C23: GENEVIEVE MAALOUF | D23: 2nd payment | E23: JAN-2026 | G23: =IF($F23<>"",$F23,$J23) -> FAM-039 | H23: =IF($G23<>"","yes","") -> yes | I23: A | J23: FAM-039 | L23: payer name previously seen with a verified reference for this family | M23: half of expected | N23: GENEVIEVE MAALOUF 2nd payment BGC
A24: 46064 | B24: 204.75 | C24: KATRIN DUPLANTIER | D24: 2nd payment | E24: JAN-2026 | G24: =IF($F24<>"",$F24,$J24) -> FAM-021 | H24: =IF($G24<>"","yes","") -> yes | I24: B | J24: FAM-021 | L24: surname DUPLANTIER | M24: half of expected; JAN-2026 amount | N24: KATRIN DUPLANTIER 2nd payment BGC
A25: 46064 | B25: 409.5 | C25: TOVE YANKOVIC | D25: Yankovic | E25: JAN-2026 | G25: =IF($F25<>"",$F25,$J25) -> FAM-059 | H25: =IF($G25<>"","yes","") -> yes | I25: B | J25: FAM-059 | L25: surname YANKOVIC | M25: matches expected; JAN-2026 amount | N25: TOVE YANKOVIC Yankovic BGC
A26: 46065 | B26: 719.5 | C26: STEFAN BERGQVIST | D26: BERGQV2026-009 | E26: JAN-2026 | G26: =IF($F26<>"",$F26,$J26) -> FAM-010 | H26: =IF($G26<>"","yes","") -> yes | I26: A | J26: FAM-010 | L26: invoice reference 2026-009 | M26: matches expected | N26: STEFAN BERGQVIST BERGQV2026-009 BGC
A27: 46068 | B27: 767.5 | C27: ROSALIND NAKASHIMA-PELL | D27: 2025-641 | E27: AUT-2025 | G27: =IF($F27<>"",$F27,$J27) -> FAM-042 | H27: =IF($G27<>"","yes","") -> yes | I27: B | J27: FAM-042 | L27: 'PELL' starts PELLETIER, surname NAKASHIMA (prior-term reference 2025-641 — family identified, invoice not loaded) | N27: ROSALIND NAKASHIMA-PELL 2025-641 BGC
A28: 46069 | B28: 409.5 | C28: MARGIT NWACHUKWU | D28: Giulia | E28: JAN-2026 | G28: =IF($F28<>"",$F28,$J28) -> FAM-043 | H28: =IF($G28<>"","yes","") -> yes | I28: B | J28: FAM-043 | L28: surname NWACHUKWU | M28: matches expected; JAN-2026 amount | N28: MARGIT NWACHUKWU Giulia BGC
A29: 46070 | B29: 434.5 | C29: KATRIN BEAUCHAMP | D29: 2026-008 | E29: JAN-2026 | G29: =IF($F29<>"",$F29,$J29) -> 0 | H29: =IF($G29<>"","yes","") | I29: D | K29: FAM-008, FAM-045 | L29: reference 2026-008 is shared by FAM-008, FAM-045 | M29: JAN-2026 amount | N29: KATRIN BEAUCHAMP 2026-008 BGC
A30: 46070 | B30: 774.5 | C30: ULRICH QUILLIAM | D30: school fees | E30: JAN-2026 | G30: =IF($F30<>"",$F30,$J30) -> FAM-047 | H30: =IF($G30<>"","yes","") -> yes | I30: B | J30: FAM-047 | L30: surname QUILLIAM | M30: matches expected; JAN-2026 amount | N30: ULRICH QUILLIAM school fees BGC
A31: 46070 | B31: 204.75 | C31: LUDOVIC THIBODEAUX | D31: Thibodeaux fees | E31: JAN-2026 | G31: =IF($F31<>"",$F31,$J31) -> FAM-052 | H31: =IF($G31<>"","yes","") -> yes | I31: B | J31: FAM-052 | L31: surname THIBODEAUX | M31: half of expected; JAN-2026 amount | N31: LUDOVIC THIBODEAUX Thibodeaux fees BGC
A32: 46071 | B32: 799.5 | C32: ULRICH TREVELYAN | D32: Trevelyan | E32: JAN-2026 | G32: =IF($F32<>"",$F32,$J32) -> 0 | H32: =IF($G32<>"","yes","") | I32: D | K32: FAM-009, FAM-053 | L32: several families fit: FAM-009 (surname TREVELYAN); FAM-053 (surname TREVELYAN) | M32: JAN-2026 amount | N32: ULRICH TREVELYAN Trevelyan BGC
A33: 46073 | B33: 1299.12 | C33: PASCAL HALVORSEN | D33: HALVOR2026-022 | E33: JAN-2026 | G33: =IF($F33<>"",$F33,$J33) -> FAM-030 | H33: =IF($G33<>"","yes","") -> yes | I33: A | J33: FAM-030 | L33: invoice reference 2026-022 | M33: matches expected | N33: PASCAL HALVORSEN HALVOR2026-022 BGC
A34: 46075 | B34: 1041 | C34: PASCAL GRIMALDSEN | D34: Grimaldsen fees | E34: JAN-2026 | G34: =IF($F34<>"",$F34,$J34) -> FAM-028 | H34: =IF($G34<>"","yes","") -> yes | I34: B | J34: FAM-028 | L34: surname GRIMALDSEN | M34: matches expected; JAN-2026 amount | N34: PASCAL GRIMALDSEN Grimaldsen fees BGC
A35: 46075 | B35: 217.25 | C35: TOVE FITZHUGH | D35: 2026-019 | E35: JAN-2026 | G35: =IF($F35<>"",$F35,$J35) -> FAM-026 | H35: =IF($G35<>"","yes","") -> yes | I35: A | J35: FAM-026 | L35: invoice reference 2026-019 | M35: half of expected | N35: TOVE FITZHUGH 2026-019 BGC
A36: 46077 | B36: 434.5 | C36: GENEVIEVE HOLLINGWORTH | D36: 2026-024 | E36: JAN-2026 | G36: =IF($F36<>"",$F36,$J36) -> 0 | H36: =IF($G36<>"","yes","") | I36: X | K36: FAM-032, FAM-033 | L36: reference 2026-024 points to FAM-033 but the memo names FAM-032 — parent may have typed the wrong invoice number | M36: JAN-2026 amount | N36: GENEVIEVE HOLLINGWORTH 2026-024 BGC
A37: 46077 | B37: 434.5 | C37: HUGO WOJCIECHOWSKI | D37: 048 | E37: JAN-2026 | G37: =IF($F37<>"",$F37,$J37) -> FAM-058 | H37: =IF($G37<>"","yes","") -> yes | I37: B | J37: FAM-058 | L37: surname WOJCIECHOWSKI | M37: matches expected; JAN-2026 amount | N37: HUGO WOJCIECHOWSKI 048 BGC
A38: 46078 | B38: 520.5 | C38: GENEVIEVE KILBRIDE | D38: 2026-027 | E38: JAN-2026 | G38: =IF($F38<>"",$F38,$J38) -> FAM-036 | H38: =IF($G38<>"","yes","") -> yes | I38: A | J38: FAM-036 | L38: invoice reference 2026-027 | M38: half of expected | N38: GENEVIEVE KILBRIDE 2026-027 BGC
A39: 46080 | B39: 204.75 | C39: ZORA ZIMMERLI | D39: 2025-574 | E39: AUT-2025 | G39: =IF($F39<>"",$F39,$J39) -> FAM-061 | H39: =IF($G39<>"","yes","") -> yes | I39: B | J39: FAM-061 | L39: surname ZIMMERLI (prior-term reference 2025-574 — family identified, invoice not loaded) | M39: JAN-2026 amount | N39: ZORA ZIMMERLI 2025-574 BGC
A40: 46083 | B40: 374.75 | C40: CAMILLE SIGURDSSON | D40: 2nd payment | E40: JAN-2026 | G40: =IF($F40<>"",$F40,$J40) -> FAM-051 | H40: =IF($G40<>"","yes","") -> yes | I40: A | J40: FAM-051 | L40: payer name previously seen with a verified reference for this family | M40: half of expected | N40: CAMILLE SIGURDSSON 2nd payment BGC
A41: 46085 | B41: 217.25 | C41: MARGIT GAILLARD | D41: Gaillard | E41: JAN-2026 | G41: =IF($F41<>"",$F41,$J41) -> FAM-027 | H41: =IF($G41<>"","yes","") -> yes | I41: B | J41: FAM-027 | L41: surname GAILLARD | M41: half of expected | N41: MARGIT GAILLARD Gaillard BGC
A42: 46086 | B42: 434.5 | C42: ZORA MARCHETTI | D42: 2026-031 | E42: JAN-2026 | G42: =IF($F42<>"",$F42,$J42) -> FAM-040 | H42: =IF($G42<>"","yes","") -> yes | I42: A | J42: FAM-040 | L42: invoice reference 2026-031 | M42: matches expected; JAN-2026 amount | N42: ZORA MARCHETTI 2026-031 BGC
A43: 46087 | B43: 799.5 | C43: CAMILLE LINDQVIST | D43: LINDQVIST FRENCH SCHO | E43: JAN-2026 | G43: =IF($F43<>"",$F43,$J43) -> FAM-038 | H43: =IF($G43<>"","yes","") -> yes | I43: B | J43: FAM-038 | L43: surname LINDQVIST | M43: matches expected; JAN-2026 amount | N43: CAMILLE LINDQVIST LINDQVIST FRENCH SCHO BGC
A44: 46090 | B44: 774.5 | C44: KATRIN CASTELLANE | D44: 2026-056 | E44: JAN-2026 | G44: =IF($F44<>"",$F44,$J44) -> FAM-015 | H44: =IF($G44<>"","yes","") -> yes | I44: A | J44: FAM-015 | L44: invoice reference 2026-056 | M44: matches expected; JAN-2026 amount | N44: KATRIN CASTELLANE 2026-056 BGC
A45: 46092 | B45: -409.5 | C45: REFUND | D45: withdrawal refund | E45: JAN-2026 | G45: =IF($F45<>"",$F45,$J45) -> 0 | H45: =IF($G45<>"","yes","") | I45: D | L45: no roster surname or child name (from the bank-sheet note, not the memo) | M45: outflow / refund; bank truncated the reference field | N45: REFUND withdrawal refund BGC
A46: 46094 | B46: 204.75 | C46: LUDOVIC THIBODEAUX | D46: Thibodeaux 2nd | E46: JAN-2026 | G46: =IF($F46<>"",$F46,$J46) -> FAM-052 | H46: =IF($G46<>"","yes","") -> yes | I46: B | J46: FAM-052 | L46: surname THIBODEAUX | M46: half of expected; JAN-2026 amount | N46: LUDOVIC THIBODEAUX Thibodeaux 2nd BGC
A47: 46101 | B47: 204.75 | C47: ZORA ZIMMERLI | D47: 2nd payment | E47: JAN-2026 | G47: =IF($F47<>"",$F47,$J47) -> FAM-061 | H47: =IF($G47<>"","yes","") -> yes | I47: B | J47: FAM-061 | L47: surname ZIMMERLI | M47: half of expected; JAN-2026 amount | N47: ZORA ZIMMERLI 2nd payment BGC
A48: 46101 | B48: 217.25 | C48: FERGUS DARRIEUSSECQ | D48: Darrieussecq | E48: JAN-2026 | G48: =IF($F48<>"",$F48,$J48) -> FAM-019 | H48: =IF($G48<>"","yes","") -> yes | I48: A | J48: FAM-019 | L48: payer name previously seen with a verified reference for this family | M48: half of expected | N48: FERGUS DARRIEUSSECQ Darrieussecq BGC
A49: 46103 | B49: 434.5 | C49: YOLANDE ACHTERBERG | D49: Achterberg | E49: JAN-2026 | G49: =IF($F49<>"",$F49,$J49) -> 0 | H49: =IF($G49<>"","yes","") | I49: D | K49: FAM-002, FAM-003 | L49: several families fit: FAM-002 (surname ACHTERBERG); FAM-003 (surname ACHTERBERG) | M49: JAN-2026 amount | N49: YOLANDE ACHTERBERG Achterberg BGC
A50: 46103 | B50: 409.5 | C50: INGRID ABARCA | D50: 2026-004 | E50: JAN-2026 | G50: =IF($F50<>"",$F50,$J50) -> FAM-001 | H50: =IF($G50<>"","yes","") -> yes | I50: A | J50: FAM-001 | L50: invoice reference 2026-004 | M50: matches expected; JAN-2026 amount | N50: INGRID ABARCA 2026-004 BGC
A51: 46104 | B51: 217.25 | C51: JEROME JANKOWSKI | D51: 2026025 | E51: JAN-2026 | G51: =IF($F51<>"",$F51,$J51) -> FAM-034 | H51: =IF($G51<>"","yes","") -> yes | I51: A | J51: FAM-034 | L51: invoice reference 2026-025 | M51: half of expected | N51: JEROME JANKOWSKI 2026025 BGC
A52: 46111 | B52: 374.75 | C52: STEFAN BOSANQUET | D52: 053 | E52: JAN-2026 | G52: =IF($F52<>"",$F52,$J52) -> FAM-012 | H52: =IF($G52<>"","yes","") -> yes | I52: A | J52: FAM-012 | L52: payer name previously seen with a verified reference for this family | M52: half of expected | N52: STEFAN BOSANQUET 053 BGC
A53: 46112 | B53: 434.5 | C53: PASCAL IBARRA | D53: 2026-024 | E53: JAN-2026 | G53: =IF($F53<>"",$F53,$J53) -> FAM-033 | H53: =IF($G53<>"","yes","") -> yes | I53: A | J53: FAM-033 | L53: invoice reference 2026-024 | M53: matches expected; JAN-2026 amount | N53: PASCAL IBARRA 2026-024 BGC
A54: 46114 | B54: 434.5 | C54: MARGIT WENDELIN | D54: 2026-047 | E54: JAN-2026 | G54: =IF($F54<>"",$F54,$J54) -> FAM-057 | H54: =IF($G54<>"","yes","") -> yes | I54: A | J54: FAM-057 | L54: invoice reference 2026-047 | M54: matches expected; JAN-2026 amount | N54: MARGIT WENDELIN 2026-047 BGC
A55: 46115 | B55: 409.5 | C55: ROSALIND GRYNBERG | D55: Grynberg fees | E55: JAN-2026 | G55: =IF($F55<>"",$F55,$J55) -> FAM-029 | H55: =IF($G55<>"","yes","") -> yes | I55: B | J55: FAM-029 | L55: surname GRYNBERG | M55: matches expected; JAN-2026 amount | N55: ROSALIND GRYNBERG Grynberg fees BGC
A56: 46116 | B56: 387.25 | C56: CAMILLE LACHAPELLE | D56: LACHAP2026-028 | E56: JAN-2026 | G56: =IF($F56<>"",$F56,$J56) -> FAM-037 | H56: =IF($G56<>"","yes","") -> yes | I56: A | J56: FAM-037 | L56: invoice reference 2026-028 | M56: half of expected | N56: CAMILLE LACHAPELLE LACHAP2026-028 BGC
A57: 46116 | B57: 749.5 | C57: DERMOT AUCLAIR | D57: 2026-054 | E57: JAN-2026 | G57: =IF($F57<>"",$F57,$J57) -> FAM-005 | H57: =IF($G57<>"","yes","") -> yes | I57: A | J57: FAM-005 | L57: invoice reference 2026-054 | M57: matches expected; JAN-2026 amount | N57: DERMOT AUCLAIR 2026-054 BGC
A58: 46118 | B58: 774.5 | C58: HUGO SANDOVAL | D58: 2026-040 | E58: JAN-2026 | G58: =IF($F58<>"",$F58,$J58) -> FAM-050 | H58: =IF($G58<>"","yes","") -> yes | I58: A | J58: FAM-050 | L58: invoice reference 2026-040 | M58: matches expected; JAN-2026 amount | N58: HUGO SANDOVAL 2026-040 BGC
A59: 46118 | B59: 217.25 | C59: TOVE FITZHUGH | D59: Fitzhugh 2nd | E59: JAN-2026 | G59: =IF($F59<>"",$F59,$J59) -> FAM-026 | H59: =IF($G59<>"","yes","") -> yes | I59: A | J59: FAM-026 | L59: payer name previously seen with a verified reference for this family | M59: half of expected | N59: TOVE FITZHUGH Fitzhugh 2nd BGC
A60: 46121 | B60: 434.5 | C60: ELODIE ROCHETEAU | D60: 039 | E60: JAN-2026 | G60: =IF($F60<>"",$F60,$J60) -> FAM-049 | H60: =IF($G60<>"","yes","") -> yes | I60: B | J60: FAM-049 | L60: surname ROCHETEAU | M60: matches expected; JAN-2026 amount | N60: ELODIE ROCHETEAU 039 BGC
A61: 46121 | B61: 217.25 | C61: JEROME JANKOWSKI | D61: 2nd payment | E61: JAN-2026 | G61: =IF($F61<>"",$F61,$J61) -> FAM-034 | H61: =IF($G61<>"","yes","") -> yes | I61: A | J61: FAM-034 | L61: payer name previously seen with a verified reference for this family | M61: half of expected | N61: JEROME JANKOWSKI 2nd payment BGC
A62: 46123 | B62: 217.25 | C62: CAMILLE FERREIRO | D62: 2025-503 | E62: AUT-2025 | G62: =IF($F62<>"",$F62,$J62) -> FAM-025 | H62: =IF($G62<>"","yes","") -> yes | I62: B | J62: FAM-025 | L62: surname FERREIRO (prior-term reference 2025-503 — family identified, invoice not loaded) | N62: CAMILLE FERREIRO 2025-503 BGC
A63: 46129 | B63: 434.5 | C63: ADRIEN ACHTERBERG-MARCH | D63: 2026-001 | E63: JAN-2026 | G63: =IF($F63<>"",$F63,$J63) -> FAM-003 | H63: =IF($G63<>"","yes","") -> yes | I63: A | J63: FAM-003 | L63: invoice reference 2026-001 | M63: matches expected; JAN-2026 amount | N63: ADRIEN ACHTERBERG-MARCH 2026-001 BGC
A64: 46132 | B64: 374.75 | C64: STEFAN BOSANQUET | D64: 2026-053 | E64: JAN-2026 | G64: =IF($F64<>"",$F64,$J64) -> FAM-012 | H64: =IF($G64<>"","yes","") -> yes | I64: A | J64: FAM-012 | L64: invoice reference 2026-053 | M64: half of expected | N64: STEFAN BOSANQUET 2026-053 BGC
A65: 46132 | B65: 774.5 | C65: JEROME PERREAULT | D65: 2025-641 | E65: AUT-2025 | G65: =IF($F65<>"",$F65,$J65) -> FAM-046 | H65: =IF($G65<>"","yes","") -> yes | I65: B | J65: FAM-046 | L65: surname PERREAULT (prior-term reference 2025-641 — family identified, invoice not loaded) | M65: JAN-2026 amount | N65: JEROME PERREAULT 2025-641 BGC
A66: 46133 | B66: 1249.12 | C66: PASCAL BRANNIGAN | D66: Brannigan | E66: JAN-2026 | G66: =IF($F66<>"",$F66,$J66) -> FAM-013 | H66: =IF($G66<>"","yes","") -> yes | I66: B | J66: FAM-013 | L66: surname BRANNIGAN | M66: matches expected | N66: PASCAL BRANNIGAN Brannigan BGC
A67: 46133 | B67: 434.5 | C67: MARGIT BELHADJ-TREVELYA | D67: 2026-003 | E67: JAN-2026 | G67: =IF($F67<>"",$F67,$J67) -> 0 | H67: =IF($G67<>"","yes","") | I67: X | K67: FAM-008, FAM-009, FAM-042 | L67: reference 2026-003 points to FAM-042 but the memo names FAM-008, FAM-009 — parent may have typed the wrong invoice number | M67: JAN-2026 amount | N67: MARGIT BELHADJ-TREVELYA 2026-003 BGC
A68: 46133 | B68: 347 | C68: TOVE CHIDOZIE | D68: CHIDOZIE FRENCH SCHOO | E68: JAN-2026 | G68: =IF($F68<>"",$F68,$J68) -> 0 | H68: =IF($G68<>"","yes","") | I68: C | K68: FAM-017 | L68: surname CHIDOZIE — chosen over FAM-016 because only this family is billed this term | M68: half of expected | N68: TOVE CHIDOZIE CHIDOZIE FRENCH SCHOO BGC
A69: 46135 | B69: 387.25 | C69: CAMILLE LACHAPELLE | D69: 2026-028 | E69: JAN-2026 | G69: =IF($F69<>"",$F69,$J69) -> FAM-037 | H69: =IF($G69<>"","yes","") -> yes | I69: A | J69: FAM-037 | L69: invoice reference 2026-028 | M69: half of expected | N69: CAMILLE LACHAPELLE 2026-028 BGC
A70: 46137 | B70: 1041 | C70: ULRICH CARDOSO | D70: CARDOSO FRENCH SCHOOL | E70: JAN-2026 | G70: =IF($F70<>"",$F70,$J70) -> FAM-014 | H70: =IF($G70<>"","yes","") -> yes | I70: B | J70: FAM-014 | L70: surname CARDOSO | M70: matches expected; JAN-2026 amount | N70: ULRICH CARDOSO CARDOSO FRENCH SCHOOL BGC
A71: 46137 | B71: 387.25 | C71: INGRID BAPTISTE | D71: 2026-006 | E71: JAN-2026 | G71: =IF($F71<>"",$F71,$J71) -> FAM-006 | H71: =IF($G71<>"","yes","") -> yes | I71: A | J71: FAM-006 | L71: invoice reference 2026-006 | M71: half of expected | N71: INGRID BAPTISTE 2026-006 BGC
A72: 46138 | B72: 434.5 | C72: NILS BLOMFIELD | D72: BLOMFIELD FRENCH SCHO | E72: JAN-2026 | G72: =IF($F72<>"",$F72,$J72) -> FAM-011 | H72: =IF($G72<>"","yes","") -> yes | I72: B | J72: FAM-011 | L72: surname BLOMFIELD | M72: matches expected; JAN-2026 amount | N72: NILS BLOMFIELD BLOMFIELD FRENCH SCHO BGC
A73: 46138 | B73: 1041 | C73: ELODIE KACZMAREK | D73: 2026026 | E73: JAN-2026 | G73: =IF($F73<>"",$F73,$J73) -> FAM-035 | H73: =IF($G73<>"","yes","") -> yes | I73: A | J73: FAM-035 | L73: invoice reference 2026-026 | M73: matches expected; JAN-2026 amount | N73: ELODIE KACZMAREK 2026026 BGC
A74: 46139 | B74: 409.5 | C74: ZORA COMEAU | D74: COMEAU2026-013 | E74: JAN-2026 | G74: =IF($F74<>"",$F74,$J74) -> FAM-018 | H74: =IF($G74<>"","yes","") -> yes | I74: A | J74: FAM-018 | L74: invoice reference 2026-013 | M74: matches expected; JAN-2026 amount | N74: ZORA COMEAU COMEAU2026-013 BGC
A75: 46139 | B75: 374.75 | C75: NILS ZABALA | D75: 2026-050 | E75: JAN-2026 | G75: =IF($F75<>"",$F75,$J75) -> FAM-060 | H75: =IF($G75<>"","yes","") -> yes | I75: A | J75: FAM-060 | L75: invoice reference 2026-050 | M75: half of expected | N75: NILS ZABALA 2026-050 BGC
A76: 46140 | B76: 434.5 | C76: GENEVIEVE UCHENDU | D76: 2026-044 | E76: JAN-2026 | G76: =IF($F76<>"",$F76,$J76) -> FAM-054 | H76: =IF($G76<>"","yes","") -> yes | I76: A | J76: FAM-054 | L76: invoice reference 2026-044 | M76: matches expected; JAN-2026 amount | N76: GENEVIEVE UCHENDU 2026-044 BGC
A77: 46141 | B77: 217.25 | C77: FERGUS DARRIEUSSECQ | D77: 2026-014 | E77: JAN-2026 | G77: =IF($F77<>"",$F77,$J77) -> FAM-019 | H77: =IF($G77<>"","yes","") -> yes | I77: A | J77: FAM-019 | L77: invoice reference 2026-014 | M77: half of expected | N77: FERGUS DARRIEUSSECQ 2026-014 BGC
A78: 46143 | B78: 592 | C78: MARGIT PELLETIER | D78: 2025-627 | E78: AUT-2025 | G78: =IF($F78<>"",$F78,$J78) -> 0 | H78: =IF($G78<>"","yes","") | I78: D | K78: FAM-042, FAM-045 | L78: several families fit: FAM-042 (surname PELLETIER); FAM-045 (surname PELLETIER) | N78: MARGIT PELLETIER 2025-627 BGC
A79: 46144 | B79: 217.25 | C79: CAMILLE FERREIRO | D79: Ferreiro 2nd | E79: JAN-2026 | G79: =IF($F79<>"",$F79,$J79) -> FAM-025 | H79: =IF($G79<>"","yes","") -> yes | I79: B | J79: FAM-025 | L79: surname FERREIRO | M79: half of expected | N79: CAMILLE FERREIRO Ferreiro 2nd BGC
A80: 46168 | B80: 347 | C80: TOVE CHIDOZIE | D80: Chidozie | E80: JAN-2026 | G80: =IF($F80<>"",$F80,$J80) -> 0 | H80: =IF($G80<>"","yes","") | I80: C | K80: FAM-017 | L80: surname CHIDOZIE — chosen over FAM-016 because only this family is billed this term | M80: half of expected | N80: TOVE CHIDOZIE Chidozie BGC
A81: 46170 | B81: 592 | C81: MARGIT PELLETIER | D81: Pelletier 2nd | E81: JAN-2026 | G81: =IF($F81<>"",$F81,$J81) -> 0 | H81: =IF($G81<>"","yes","") | I81: D | K81: FAM-042, FAM-045 | L81: several families fit: FAM-042 (surname PELLETIER); FAM-045 (surname PELLETIER) | N81: MARGIT PELLETIER Pelletier 2nd BGC
A82: 46182 | B82: 374.75 | C82: NILS ZABALA | D82: Zabala 2nd | E82: JAN-2026 | G82: =IF($F82<>"",$F82,$J82) -> FAM-060 | H82: =IF($G82<>"","yes","") -> yes | I82: A | J82: FAM-060 | L82: payer name previously seen with a verified reference for this family | M82: half of expected | N82: NILS ZABALA Zabala 2nd BGC
A83: 46182 | B83: 387.25 | C83: INGRID BAPTISTE | D83: Baptiste | E83: JAN-2026 | G83: =IF($F83<>"",$F83,$J83) -> FAM-006 | H83: =IF($G83<>"","yes","") -> yes | I83: A | J83: FAM-006 | L83: payer name previously seen with a verified reference for this family | M83: half of expected | N83: INGRID BAPTISTE Baptiste BGC

Sheet Review
A1: Review queue — receipts the engine would not allocate. Decide, then type the family ID into Receipts column M (row shown) and re-run.
A3: Row in Receipts | B3: Date | C3: Amount | D3: Payer (bank) | E3: Reference (bank) | F3: Term | G3: Tier | H3: Most likely family | I3: Why the engine stopped | J3: Amount check | K3: That family's expected fee
A4: 32 | B4: 46071 | C4: 799.5 | D4: ULRICH TREVELYAN | E4: Trevelyan | F4: JAN-2026 | G4: D | H4: FAM-009 BELHADJ-TREVELYAN, FAM-053 TREVELYAN | I4: several families fit: FAM-009 (surname TREVELYAN); FAM-053 (surname TREVELYAN) | J4: n/a
A5: 78 | B5: 46143 | C5: 592 | D5: MARGIT PELLETIER | E5: 2025-627 | F5: AUT-2025 | G5: D | H5: FAM-042 NAKASHIMA-PELLETIER, FAM-045 PELLETIER | I5: several families fit: FAM-042 (surname PELLETIER); FAM-045 (surname PELLETIER) | J5: n/a
A6: 81 | B6: 46170 | C6: 592 | D6: MARGIT PELLETIER | E6: Pelletier 2nd | F6: JAN-2026 | G6: D | H6: FAM-042 NAKASHIMA-PELLETIER, FAM-045 PELLETIER | I6: several families fit: FAM-042 (surname PELLETIER); FAM-045 (surname PELLETIER) | J6: n/a
A7: 29 | B7: 46070 | C7: 434.5 | D7: KATRIN BEAUCHAMP | E7: 2026-008 | F7: JAN-2026 | G7: D | H7: FAM-008 BELHADJ, FAM-045 PELLETIER | I7: reference 2026-008 is shared by FAM-008, FAM-045 | J7: n/a
A8: 36 | B8: 46077 | C8: 434.5 | D8: GENEVIEVE HOLLINGWORTH | E8: 2026-024 | F8: JAN-2026 | G8: X | H8: FAM-032 HOLLINGWORTH, FAM-033 IBARRA | I8: reference 2026-024 points to FAM-033 but the memo names FAM-032 — parent may have typed the wrong invoice number | J8: n/a
A9: 49 | B9: 46103 | C9: 434.5 | D9: YOLANDE ACHTERBERG | E9: Achterberg | F9: JAN-2026 | G9: D | H9: FAM-002 ACHTERBERG, FAM-003 ACHTERBERG-MARCHETTI | I9: several families fit: FAM-002 (surname ACHTERBERG); FAM-003 (surname ACHTERBERG) | J9: n/a
A10: 67 | B10: 46133 | C10: 434.5 | D10: MARGIT BELHADJ-TREVELYA | E10: 2026-003 | F10: JAN-2026 | G10: X | H10: FAM-008 BELHADJ, FAM-009 BELHADJ-TREVELYAN, FAM-042 NAKASHIMA-PELLETIER | I10: reference 2026-003 points to FAM-042 but the memo names FAM-008, FAM-009 — parent may have typed the wrong invoice number | J10: n/a
A11: 45 | B11: 46092 | C11: -409.5 | D11: REFUND | E11: withdrawal refund | F11: JAN-2026 | G11: D | I11: no roster surname or child name (from the bank-sheet note, not the memo) | J11: n/a
A12: 68 | B12: 46133 | C12: 347 | D12: TOVE CHIDOZIE | E12: CHIDOZIE FRENCH SCHOO | F12: JAN-2026 | G12: C | H12: FAM-017 CHIDOZIE | I12: surname CHIDOZIE — chosen over FAM-016 because only this family is billed this term | J12: half of expected | K12: 694
A13: 80 | B13: 46168 | C13: 347 | D13: TOVE CHIDOZIE | E13: Chidozie | F13: JAN-2026 | G13: C | H13: FAM-017 CHIDOZIE | I13: surname CHIDOZIE — chosen over FAM-016 because only this family is billed this term | J13: half of expected | K13: 694
A14: 6 | B14: 46038 | C14: 229.75 | D14: MARGIT RASMUSSEN | E14: 2026-039 | F14: JAN-2026 | G14: X | H14: FAM-048 RASMUSSEN, FAM-049 ROCHETEAU | I14: reference 2026-039 points to FAM-049 but the memo names FAM-048 — parent may have typed the wrong invoice number | J14: n/a

Sheet Position
A1: Position — JAN-2026. One row per family. Green = settled. Red = owing. Amber = check the last two columns before chasing.
A2: Report date | B2: 46266
A4: Family ID | B4: Family | C4: Children | D4: Invoice no(s) | E4: Expected | F4: Received | G4: Balance | H4: Status | I4: Receipts | J4: Last payment | K4: Days | L4: References used (bank) | M4: Needs a look
A5: FAM-053 | B5: TREVELYAN | C5: 2 | D5: 2026-043 | E5: =SUMIFS(Children!$R$4:$R$500,Children!$B$4:$B$500,$A5,Children!$F$4:$F$500,"Enrolled",Children!$G$4:$G$500,"JAN-2026") -> 799.5 | F5: =SUMIFS(Receipts!$B$4:$B$600,Receipts!$G$4:$G$600,$A5,Receipts!$E$4:$E$600,"JAN-2026") -> 0 | G5: =$E5-$F5 -> 799.5 | H5: =IF($E5=0,"no charge",IF($F5<=0,"unpaid",IF(ABS($G5)<=0.5,"settled",IF($G5>0,"part paid","overpaid")))) -> unpaid | I5: =COUNTIFS(Receipts!$G$4:$G$600,$A5,Receipts!$E$4:$E$600,"JAN-2026") -> 0 | K5: =IF($G5>0.5,$B$2-Terms!$G$5,"") -> 260 | M5: 1 receipt(s) in Review name this family
A6: FAM-046 | B6: PERREAULT | C6: 2 | D6: 2026-036 | E6: =SUMIFS(Children!$R$4:$R$500,Children!$B$4:$B$500,$A6,Children!$F$4:$F$500,"Enrolled",Children!$G$4:$G$500,"JAN-2026") -> 774.5 | F6: =SUMIFS(Receipts!$B$4:$B$600,Receipts!$G$4:$G$600,$A6,Receipts!$E$4:$E$600,"JAN-2026") -> 0 | G6: =$E6-$F6 -> 774.5 | H6: =IF($E6=0,"no charge",IF($F6<=0,"unpaid",IF(ABS($G6)<=0.5,"settled",IF($G6>0,"part paid","overpaid")))) -> unpaid | I6: =COUNTIFS(Receipts!$G$4:$G$600,$A6,Receipts!$E$4:$E$600,"JAN-2026") -> 0 | K6: =IF($G6>0.5,$B$2-Terms!$G$5,"") -> 260 | M6: £774.50 tagged AUT-2025 looks like a JAN-2026 payment
A7: FAM-042 | B7: NAKASHIMA-PELLETIER | C7: 2 | D7: 2026-003 | E7: =SUMIFS(Children!$R$4:$R$500,Children!$B$4:$B$500,$A7,Children!$F$4:$F$500,"Enrolled",Children!$G$4:$G$500,"JAN-2026") -> 774.5 | F7: =SUMIFS(Receipts!$B$4:$B$600,Receipts!$G$4:$G$600,$A7,Receipts!$E$4:$E$600,"JAN-2026") -> 0 | G7: =$E7-$F7 -> 774.5 | H7: =IF($E7=0,"no charge",IF($F7<=0,"unpaid",IF(ABS($G7)<=0.5,"settled",IF($G7>0,"part paid","overpaid")))) -> unpaid | I7: =COUNTIFS(Receipts!$G$4:$G$600,$A7,Receipts!$E$4:$E$600,"JAN-2026") -> 0 | K7: =IF($G7>0.5,$B$2-Terms!$G$5,"") -> 260 | M7: 3 receipt(s) in Review name this family; £767.50 tagged AUT-2025 looks like a JAN-2026 payment
A8: FAM-017 | B8: CHIDOZIE | C8: 2 | D8: 2026-012 | E8: =SUMIFS(Children!$R$4:$R$500,Children!$B$4:$B$500,$A8,Children!$F$4:$F$500,"Enrolled",Children!$G$4:$G$500,"JAN-2026") -> 774.5 | F8: =SUMIFS(Receipts!$B$4:$B$600,Receipts!$G$4:$G$600,$A8,Receipts!$E$4:$E$600,"JAN-2026") -> 0 | G8: =$E8-$F8 -> 774.5 | H8: =IF($E8=0,"no charge",IF($F8<=0,"unpaid",IF(ABS($G8)<=0.5,"settled",IF($G8>0,"part paid","overpaid")))) -> unpaid | I8: =COUNTIFS(Receipts!$G$4:$G$600,$A8,Receipts!$E$4:$E$600,"JAN-2026") -> 0 | K8: =IF($G8>0.5,$B$2-Terms!$G$5,"") -> 260 | M8: 2 receipt(s) in Review name this family
A9: FAM-036 | B9: KILBRIDE | C9: 3 | D9: 2026-027 | E9: =SUMIFS(Children!$R$4:$R$500,Children!$B$4:$B$500,$A9,Children!$F$4:$F$500,"Enrolled",Children!$G$4:$G$500,"JAN-2026") -> 1041 | F9: =SUMIFS(Receipts!$B$4:$B$600,Receipts!$G$4:$G$600,$A9,Receipts!$E$4:$E$600,"JAN-2026") -> 520.5 | G9: =$E9-$F9 -> 520.5 | H9: =IF($E9=0,"no charge",IF($F9<=0,"unpaid",IF(ABS($G9)<=0.5,"settled",IF($G9>0,"part paid","overpaid")))) -> part paid | I9: =COUNTIFS(Receipts!$G$4:$G$600,$A9,Receipts!$E$4:$E$600,"JAN-2026") -> 1 | J9: 46078 | K9: =IF($G9>0.5,$B$2-Terms!$G$5,"") -> 260 | L9: 2026-027 | M9: £520.50 tagged AUT-2025 looks like a JAN-2026 payment
A10: FAM-002 | B10: ACHTERBERG | C10: 1 | D10: 2026-052 | E10: =SUMIFS(Children!$R$4:$R$500,Children!$B$4:$B$500,$A10,Children!$F$4:$F$500,"Enrolled",Children!$G$4:$G$500,"JAN-2026") -> 434.5 | F10: =SUMIFS(Receipts!$B$4:$B$600,Receipts!$G$4:$G$600,$A10,Receipts!$E$4:$E$600,"JAN-2026") -> 0 | G10: =$E10-$F10 -> 434.5 | H10: =IF($E10=0,"no charge",IF($F10<=0,"unpaid",IF(ABS($G10)<=0.5,"settled",IF($G10>0,"part paid","overpaid")))) -> unpaid | I10: =COUNTIFS(Receipts!$G$4:$G$600,$A10,Receipts!$E$4:$E$600,"JAN-2026") -> 0 | K10: =IF($G10>0.5,$B$2-Terms!$G$5,"") -> 260 | M10: 1 receipt(s) in Review name this family
A11: FAM-007 | B11: BEAUCHAMP | C11: 1 | D11: 2026-007 | E11: =SUMIFS(Children!$R$4:$R$500,Children!$B$4:$B$500,$A11,Children!$F$4:$F$500,"Enrolled",Children!$G$4:$G$500,"JAN-2026") -> 434.5 | F11: =SUMIFS(Receipts!$B$4:$B$600,Receipts!$G$4:$G$600,$A11,Receipts!$E$4:$E$600,"JAN-2026") -> 0 | G11: =$E11-$F11 -> 434.5 | H11: =IF($E11=0,"no charge",IF($F11<=0,"unpaid",IF(ABS($G11)<=0.5,"settled",IF($G11>0,"part paid","overpaid")))) -> unpaid | I11: =COUNTIFS(Receipts!$G$4:$G$600,$A11,Receipts!$E$4:$E$600,"JAN-2026") -> 0 | K11: =IF($G11>0.5,$B$2-Terms!$G$5,"") -> 260
A12: FAM-009 | B12: BELHADJ-TREVELYAN | C12: 1 | D12: 2026-002 | E12: =SUMIFS(Children!$R$4:$R$500,Children!$B$4:$B$500,$A12,Children!$F$4:$F$500,"Enrolled",Children!$G$4:$G$500,"JAN-2026") -> 434.5 | F12: =SUMIFS(Receipts!$B$4:$B$600,Receipts!$G$4:$G$600,$A12,Receipts!$E$4:$E$600,"JAN-2026") -> 0 | G12: =$E12-$F12 -> 434.5 | H12: =IF($E12=0,"no charge",IF($F12<=0,"unpaid",IF(ABS($G12)<=0.5,"settled",IF($G12>0,"part paid","overpaid")))) -> unpaid | I12: =COUNTIFS(Receipts!$G$4:$G$600,$A12,Receipts!$E$4:$E$600,"JAN-2026") -> 0 | K12: =IF($G12>0.5,$B$2-Terms!$G$5,"") -> 260 | M12: 2 receipt(s) in Review name this family
A13: FAM-032 | B13: HOLLINGWORTH | C13: 1 | D13: 2026-023 | E13: =SUMIFS(Children!$R$4:$R$500,Children!$B$4:$B$500,$A13,Children!$F$4:$F$500,"Enrolled",Children!$G$4:$G$500,"JAN-2026") -> 434.5 | F13: =SUMIFS(Receipts!$B$4:$B$600,Receipts!$G$4:$G$600,$A13,Receipts!$E$4:$E$600,"JAN-2026") -> 0 | G13: =$E13-$F13 -> 434.5 | H13: =IF($E13=0,"no charge",IF($F13<=0,"unpaid",IF(ABS($G13)<=0.5,"settled",IF($G13>0,"part paid","overpaid")))) -> unpaid | I13: =COUNTIFS(Receipts!$G$4:$G$600,$A13,Receipts!$E$4:$E$600,"JAN-2026") -> 0 | K13: =IF($G13>0.5,$B$2-Terms!$G$5,"") -> 260 | M13: 1 receipt(s) in Review name this family
A14: FAM-044 | B14: OKONKWO | C14: 1 | D14: 2026-034 | E14: =SUMIFS(Children!$R$4:$R$500,Children!$B$4:$B$500,$A14,Children!$F$4:$F$500,"Enrolled",Children!$G$4:$G$500,"JAN-2026") -> 434.5 | F14: =SUMIFS(Receipts!$B$4:$B$600,Receipts!$G$4:$G$600,$A14,Receipts!$E$4:$E$600,"JAN-2026") -> 0 | G14: =$E14-$F14 -> 434.5 | H14: =IF($E14=0,"no charge",IF($F14<=0,"unpaid",IF(ABS($G14)<=0.5,"settled",IF($G14>0,"part paid","overpaid")))) -> unpaid | I14: =COUNTIFS(Receipts!$G$4:$G$600,$A14,Receipts!$E$4:$E$600,"JAN-2026") -> 0 | K14: =IF($G14>0.5,$B$2-Terms!$G$5,"") -> 260 | M14: £434.50 tagged AUT-2025 looks like a JAN-2026 payment
A15: FAM-045 | B15: PELLETIER | C15: 1 | D15: 2026-008 | E15: =SUMIFS(Children!$R$4:$R$500,Children!$B$4:$B$500,$A15,Children!$F$4:$F$500,"Enrolled",Children!$G$4:$G$500,"JAN-2026") -> 409.5 | F15: =SUMIFS(Receipts!$B$4:$B$600,Receipts!$G$4:$G$600,$A15,Receipts!$E$4:$E$600,"JAN-2026") -> 0 | G15: =$E15-$F15 -> 409.5 | H15: =IF($E15=0,"no charge",IF($F15<=0,"unpaid",IF(ABS($G15)<=0.5,"settled",IF($G15>0,"part paid","overpaid")))) -> unpaid | I15: =COUNTIFS(Receipts!$G$4:$G$600,$A15,Receipts!$E$4:$E$600,"JAN-2026") -> 0 | K15: =IF($G15>0.5,$B$2-Terms!$G$5,"") -> 260 | M15: 3 receipt(s) in Review name this family
A16: FAM-056 | B16: VILLALOBOS | C16: 1 | D16: 2026-046 | E16: =SUMIFS(Children!$R$4:$R$500,Children!$B$4:$B$500,$A16,Children!$F$4:$F$500,"Enrolled",Children!$G$4:$G$500,"JAN-2026") -> 409.5 | F16: =SUMIFS(Receipts!$B$4:$B$600,Receipts!$G$4:$G$600,$A16,Receipts!$E$4:$E$600,"JAN-2026") -> 0 | G16: =$E16-$F16 -> 409.5 | H16: =IF($E16=0,"no charge",IF($F16<=0,"unpaid",IF(ABS($G16)<=0.5,"settled",IF($G16>0,"part paid","overpaid")))) -> unpaid | I16: =COUNTIFS(Receipts!$G$4:$G$600,$A16,Receipts!$E$4:$E$600,"JAN-2026") -> 0 | K16: =IF($G16>0.5,$B$2-Terms!$G$5,"") -> 260 | M16: £409.50 tagged AUT-2025 looks like a JAN-2026 payment
A17: FAM-048 | B17: RASMUSSEN | C17: 1 | D17: 2026-038 | E17: =SUMIFS(Children!$R$4:$R$500,Children!$B$4:$B$500,$A17,Children!$F$4:$F$500,"Enrolled",Children!$G$4:$G$500,"JAN-2026") -> 459.5 | F17: =SUMIFS(Receipts!$B$4:$B$600,Receipts!$G$4:$G$600,$A17,Receipts!$E$4:$E$600,"JAN-2026") -> 229.75 | G17: =$E17-$F17 -> 229.75 | H17: =IF($E17=0,"no charge",IF($F17<=0,"unpaid",IF(ABS($G17)<=0.5,"settled",IF($G17>0,"part paid","overpaid")))) -> part paid | I17: =COUNTIFS(Receipts!$G$4:$G$600,$A17,Receipts!$E$4:$E$600,"JAN-2026") -> 1 | J17: 46059 | K17: =IF($G17>0.5,$B$2-Terms!$G$5,"") -> 260 | L17: Rasmussen | M17: 1 receipt(s) in Review name this family
A18: FAM-025 | B18: FERREIRO | C18: 1 | D18: 2026-058 | E18: =SUMIFS(Children!$R$4:$R$500,Children!$B$4:$B$500,$A18,Children!$F$4:$F$500,"Enrolled",Children!$G$4:$G$500,"JAN-2026") -> 434.5 | F18: =SUMIFS(Receipts!$B$4:$B$600,Receipts!$G$4:$G$600,$A18,Receipts!$E$4:$E$600,"JAN-2026") -> 217.25 | G18: =$E18-$F18 -> 217.25 | H18: =IF($E18=0,"no charge",IF($F18<=0,"unpaid",IF(ABS($G18)<=0.5,"settled",IF($G18>0,"part paid","overpaid")))) -> part paid | I18: =COUNTIFS(Receipts!$G$4:$G$600,$A18,Receipts!$E$4:$E$600,"JAN-2026") -> 1 | J18: 46144 | K18: =IF($G18>0.5,$B$2-Terms!$G$5,"") -> 260 | L18: Ferreiro 2nd | M18: £217.25 tagged AUT-2025 looks like a JAN-2026 payment
A19: FAM-021 | B19: DUPLANTIER | C19: 1 | D19: 2026-016 | E19: =SUMIFS(Children!$R$4:$R$500,Children!$B$4:$B$500,$A19,Children!$F$4:$F$500,"Enrolled",Children!$G$4:$G$500,"JAN-2026") -> 409.5 | F19: =SUMIFS(Receipts!$B$4:$B$600,Receipts!$G$4:$G$600,$A19,Receipts!$E$4:$E$600,"JAN-2026") -> 204.75 | G19: =$E19-$F19 -> 204.75 | H19: =IF($E19=0,"no charge",IF($F19<=0,"unpaid",IF(ABS($G19)<=0.5,"settled",IF($G19>0,"part paid","overpaid")))) -> part paid | I19: =COUNTIFS(Receipts!$G$4:$G$600,$A19,Receipts!$E$4:$E$600,"JAN-2026") -> 1 | J19: 46064 | K19: =IF($G19>0.5,$B$2-Terms!$G$5,"") -> 260 | L19: 2nd payment | M19: £204.75 tagged AUT-2025 looks like a JAN-2026 payment
A20: FAM-061 | B20: ZIMMERLI | C20: 1 | D20: 2026-051 | E20: =SUMIFS(Children!$R$4:$R$500,Children!$B$4:$B$500,$A20,Children!$F$4:$F$500,"Enrolled",Children!$G$4:$G$500,"JAN-2026") -> 409.5 | F20: =SUMIFS(Receipts!$B$4:$B$600,Receipts!$G$4:$G$600,$A20,Receipts!$E$4:$E$600,"JAN-2026") -> 204.75 | G20: =$E20-$F20 -> 204.75 | H20: =IF($E20=0,"no charge",IF($F20<=0,"unpaid",IF(ABS($G20)<=0.5,"settled",IF($G20>0,"part paid","overpaid")))) -> part paid | I20: =COUNTIFS(Receipts!$G$4:$G$600,$A20,Receipts!$E$4:$E$600,"JAN-2026") -> 1 | J20: 46101 | K20: =IF($G20>0.5,$B$2-Terms!$G$5,"") -> 260 | L20: 2nd payment | M20: £204.75 tagged AUT-2025 looks like a JAN-2026 payment
A21: FAM-001 | B21: ABARCA | C21: 1 | D21: 2026-004 | E21: =SUMIFS(Children!$R$4:$R$500,Children!$B$4:$B$500,$A21,Children!$F$4:$F$500,"Enrolled",Children!$G$4:$G$500,"JAN-2026") -> 409.5 | F21: =SUMIFS(Receipts!$B$4:$B$600,Receipts!$G$4:$G$600,$A21,Receipts!$E$4:$E$600,"JAN-2026") -> 409.5 | G21: =$E21-$F21 -> 0 | H21: =IF($E21=0,"no charge",IF($F21<=0,"unpaid",IF(ABS($G21)<=0.5,"settled",IF($G21>0,"part paid","overpaid")))) -> settled | I21: =COUNTIFS(Receipts!$G$4:$G$600,$A21,Receipts!$E$4:$E$600,"JAN-2026") -> 1 | J21: 46103 | K21: =IF($G21>0.5,$B$2-Terms!$G$5,"") | L21: 2026-004
A22: FAM-003 | B22: ACHTERBERG-MARCHETTI | C22: 1 | D22: 2026-001 | E22: =SUMIFS(Children!$R$4:$R$500,Children!$B$4:$B$500,$A22,Children!$F$4:$F$500,"Enrolled",Children!$G$4:$G$500,"JAN-2026") -> 434.5 | F22: =SUMIFS(Receipts!$B$4:$B$600,Receipts!$G$4:$G$600,$A22,Receipts!$E$4:$E$600,"JAN-2026") -> 434.5 | G22: =$E22-$F22 -> 0 | H22: =IF($E22=0,"no charge",IF($F22<=0,"unpaid",IF(ABS($G22)<=0.5,"settled",IF($G22>0,"part paid","overpaid")))) -> settled | I22: =COUNTIFS(Receipts!$G$4:$G$600,$A22,Receipts!$E$4:$E$600,"JAN-2026") -> 1 | J22: 46129 | K22: =IF($G22>0.5,$B$2-Terms!$G$5,"") | L22: 2026-001 | M22: 1 receipt(s) in Review name this family
A23: FAM-004 | B23: ASHWORTH | C23: 1 | D23: 2026-005 | E23: =SUMIFS(Children!$R$4:$R$500,Children!$B$4:$B$500,$A23,Children!$F$4:$F$500,"Enrolled",Children!$G$4:$G$500,"JAN-2026") -> 434.5 | F23: =SUMIFS(Receipts!$B$4:$B$600,Receipts!$G$4:$G$600,$A23,Receipts!$E$4:$E$600,"JAN-2026") -> 434.5 | G23: =$E23-$F23 -> 0 | H23: =IF($E23=0,"no charge",IF($F23<=0,"unpaid",IF(ABS($G23)<=0.5,"settled",IF($G23>0,"part paid","overpaid")))) -> settled | I23: =COUNTIFS(Receipts!$G$4:$G$600,$A23,Receipts!$E$4:$E$600,"JAN-2026") -> 1 | J23: 46044 | K23: =IF($G23>0.5,$B$2-Terms!$G$5,"") | L23: ASHWORTH FRENCH SCHOO
A24: FAM-005 | B24: AUCLAIR | C24: 2 | D24: 2026-054 | E24: =SUMIFS(Children!$R$4:$R$500,Children!$B$4:$B$500,$A24,Children!$F$4:$F$500,"Enrolled",Children!$G$4:$G$500,"JAN-2026") -> 749.5 | F24: =SUMIFS(Receipts!$B$4:$B$600,Receipts!$G$4:$G$600,$A24,Receipts!$E$4:$E$600,"JAN-2026") -> 749.5 | G24: =$E24-$F24 -> 0 | H24: =IF($E24=0,"no charge",IF($F24<=0,"unpaid",IF(ABS($G24)<=0.5,"settled",IF($G24>0,"part paid","overpaid")))) -> settled | I24: =COUNTIFS(Receipts!$G$4:$G$600,$A24,Receipts!$E$4:$E$600,"JAN-2026") -> 1 | J24: 46116 | K24: =IF($G24>0.5,$B$2-Terms!$G$5,"") | L24: 2026-054
A25: FAM-006 | B25: BAPTISTE | C25: 2 | D25: 2026-006 | E25: =SUMIFS(Children!$R$4:$R$500,Children!$B$4:$B$500,$A25,Children!$F$4:$F$500,"Enrolled",Children!$G$4:$G$500,"JAN-2026") -> 774.5 | F25: =SUMIFS(Receipts!$B$4:$B$600,Receipts!$G$4:$G$600,$A25,Receipts!$E$4:$E$600,"JAN-2026") -> 774.5 | G25: =$E25-$F25 -> 0 | H25: =IF($E25=0,"no charge",IF($F25<=0,"unpaid",IF(ABS($G25)<=0.5,"settled",IF($G25>0,"part paid","overpaid")))) -> settled | I25: =COUNTIFS(Receipts!$G$4:$G$600,$A25,Receipts!$E$4:$E$600,"JAN-2026") -> 2 | J25: 46182 | K25: =IF($G25>0.5,$B$2-Terms!$G$5,"") | L25: 2026-006 | Baptiste
A26: FAM-010 | B26: BERGQVIST | C26: 2 | D26: 2026-009 | E26: =SUMIFS(Children!$R$4:$R$500,Children!$B$4:$B$500,$A26,Children!$F$4:$F$500,"Enrolled",Children!$G$4:$G$500,"JAN-2026") -> 719.5 | F26: =SUMIFS(Receipts!$B$4:$B$600,Receipts!$G$4:$G$600,$A26,Receipts!$E$4:$E$600,"JAN-2026") -> 719.5 | G26: =$E26-$F26 -> 0 | H26: =IF($E26=0,"no charge",IF($F26<=0,"unpaid",IF(ABS($G26)<=0.5,"settled",IF($G26>0,"part paid","overpaid")))) -> settled | I26: =COUNTIFS(Receipts!$G$4:$G$600,$A26,Receipts!$E$4:$E$600,"JAN-2026") -> 1 | J26: 46065 | K26: =IF($G26>0.5,$B$2-Terms!$G$5,"") | L26: BERGQV2026-009
A27: FAM-011 | B27: BLOMFIELD | C27: 1 | D27: 2026-010 | E27: =SUMIFS(Children!$R$4:$R$500,Children!$B$4:$B$500,$A27,Children!$F$4:$F$500,"Enrolled",Children!$G$4:$G$500,"JAN-2026") -> 434.5 | F27: =SUMIFS(Receipts!$B$4:$B$600,Receipts!$G$4:$G$600,$A27,Receipts!$E$4:$E$600,"JAN-2026") -> 434.5 | G27: =$E27-$F27 -> 0 | H27: =IF($E27=0,"no charge",IF($F27<=0,"unpaid",IF(ABS($G27)<=0.5,"settled",IF($G27>0,"part paid","overpaid")))) -> settled | I27: =COUNTIFS(Receipts!$G$4:$G$600,$A27,Receipts!$E$4:$E$600,"JAN-2026") -> 1 | J27: 46138 | K27: =IF($G27>0.5,$B$2-Terms!$G$5,"") | L27: BLOMFIELD FRENCH SCHO
A28: FAM-012 | B28: BOSANQUET | C28: 2 | D28: 2026-053 | E28: =SUMIFS(Children!$R$4:$R$500,Children!$B$4:$B$500,$A28,Children!$F$4:$F$500,"Enrolled",Children!$G$4:$G$500,"JAN-2026") -> 749.5 | F28: =SUMIFS(Receipts!$B$4:$B$600,Receipts!$G$4:$G$600,$A28,Receipts!$E$4:$E$600,"JAN-2026") -> 749.5 | G28: =$E28-$F28 -> 0 | H28: =IF($E28=0,"no charge",IF($F28<=0,"unpaid",IF(ABS($G28)<=0.5,"settled",IF($G28>0,"part paid","overpaid")))) -> settled | I28: =COUNTIFS(Receipts!$G$4:$G$600,$A28,Receipts!$E$4:$E$600,"JAN-2026") -> 2 | J28: 46132 | K28: =IF($G28>0.5,$B$2-Terms!$G$5,"") | L28: 053 | 2026-053
A29: FAM-013 | B29: BRANNIGAN | C29: 4 | D29: 2026-055 | E29: =SUMIFS(Children!$R$4:$R$500,Children!$B$4:$B$500,$A29,Children!$F$4:$F$500,"Enrolled",Children!$G$4:$G$500,"JAN-2026") -> 1249.12 | F29: =SUMIFS(Receipts!$B$4:$B$600,Receipts!$G$4:$G$600,$A29,Receipts!$E$4:$E$600,"JAN-2026") -> 1249.12 | G29: =$E29-$F29 -> 0 | H29: =IF($E29=0,"no charge",IF($F29<=0,"unpaid",IF(ABS($G29)<=0.5,"settled",IF($G29>0,"part paid","overpaid")))) -> settled | I29: =COUNTIFS(Receipts!$G$4:$G$600,$A29,Receipts!$E$4:$E$600,"JAN-2026") -> 1 | J29: 46133 | K29: =IF($G29>0.5,$B$2-Terms!$G$5,"") | L29: Brannigan
A30: FAM-014 | B30: CARDOSO | C30: 3 | D30: 2026-011 | E30: =SUMIFS(Children!$R$4:$R$500,Children!$B$4:$B$500,$A30,Children!$F$4:$F$500,"Enrolled",Children!$G$4:$G$500,"JAN-2026") -> 1041 | F30: =SUMIFS(Receipts!$B$4:$B$600,Receipts!$G$4:$G$600,$A30,Receipts!$E$4:$E$600,"JAN-2026") -> 1041 | G30: =$E30-$F30 -> 0 | H30: =IF($E30=0,"no charge",IF($F30<=0,"unpaid",IF(ABS($G30)<=0.5,"settled",IF($G30>0,"part paid","overpaid")))) -> settled | I30: =COUNTIFS(Receipts!$G$4:$G$600,$A30,Receipts!$E$4:$E$600,"JAN-2026") -> 1 | J30: 46137 | K30: =IF($G30>0.5,$B$2-Terms!$G$5,"") | L30: CARDOSO FRENCH SCHOOL
A31: FAM-015 | B31: CASTELLANE | C31: 2 | D31: 2026-056 | E31: =SUMIFS(Children!$R$4:$R$500,Children!$B$4:$B$500,$A31,Children!$F$4:$F$500,"Enrolled",Children!$G$4:$G$500,"JAN-2026") -> 774.5 | F31: =SUMIFS(Receipts!$B$4:$B$600,Receipts!$G$4:$G$600,$A31,Receipts!$E$4:$E$600,"JAN-2026") -> 774.5 | G31: =$E31-$F31 -> 0 | H31: =IF($E31=0,"no charge",IF($F31<=0,"unpaid",IF(ABS($G31)<=0.5,"settled",IF($G31>0,"part paid","overpaid")))) -> settled | I31: =COUNTIFS(Receipts!$G$4:$G$600,$A31,Receipts!$E$4:$E$600,"JAN-2026") -> 1 | J31: 46090 | K31: =IF($G31>0.5,$B$2-Terms!$G$5,"") | L31: 2026-056
A32: FAM-018 | B32: COMEAU | C32: 1 | D32: 2026-013 | E32: =SUMIFS(Children!$R$4:$R$500,Children!$B$4:$B$500,$A32,Children!$F$4:$F$500,"Enrolled",Children!$G$4:$G$500,"JAN-2026") -> 409.5 | F32: =SUMIFS(Receipts!$B$4:$B$600,Receipts!$G$4:$G$600,$A32,Receipts!$E$4:$E$600,"JAN-2026") -> 409.5 | G32: =$E32-$F32 -> 0 | H32: =IF($E32=0,"no charge",IF($F32<=0,"unpaid",IF(ABS($G32)<=0.5,"settled",IF($G32>0,"part paid","overpaid")))) -> settled | I32: =COUNTIFS(Receipts!$G$4:$G$600,$A32,Receipts!$E$4:$E$600,"JAN-2026") -> 1 | J32: 46139 | K32: =IF($G32>0.5,$B$2-Terms!$G$5,"") | L32: COMEAU2026-013
A33: FAM-019 | B33: DARRIEUSSECQ | C33: 1 | D33: 2026-014 | E33: =SUMIFS(Children!$R$4:$R$500,Children!$B$4:$B$500,$A33,Children!$F$4:$F$500,"Enrolled",Children!$G$4:$G$500,"JAN-2026") -> 434.5 | F33: =SUMIFS(Receipts!$B$4:$B$600,Receipts!$G$4:$G$600,$A33,Receipts!$E$4:$E$600,"JAN-2026") -> 434.5 | G33: =$E33-$F33 -> 0 | H33: =IF($E33=0,"no charge",IF($F33<=0,"unpaid",IF(ABS($G33)<=0.5,"settled",IF($G33>0,"part paid","overpaid")))) -> settled | I33: =COUNTIFS(Receipts!$G$4:$G$600,$A33,Receipts!$E$4:$E$600,"JAN-2026") -> 2 | J33: 46141 | K33: =IF($G33>0.5,$B$2-Terms!$G$5,"") | L33: 2026-014 | Darrieussecq
A34: FAM-020 | B34: DELACROIX | C34: 3 | D34: 2026-015 | E34: =SUMIFS(Children!$R$4:$R$500,Children!$B$4:$B$500,$A34,Children!$F$4:$F$500,"Enrolled",Children!$G$4:$G$500,"JAN-2026") -> 1041 | F34: =SUMIFS(Receipts!$B$4:$B$600,Receipts!$G$4:$G$600,$A34,Receipts!$E$4:$E$600,"JAN-2026") -> 1041 | G34: =$E34-$F34 -> 0 | H34: =IF($E34=0,"no charge",IF($F34<=0,"unpaid",IF(ABS($G34)<=0.5,"settled",IF($G34>0,"part paid","overpaid")))) -> settled | I34: =COUNTIFS(Receipts!$G$4:$G$600,$A34,Receipts!$E$4:$E$600,"JAN-2026") -> 1 | J34: 46053 | K34: =IF($G34>0.5,$B$2-Terms!$G$5,"") | L34: 2026-015
... A43: FAM-031 | B43: HASANOVIC | C43: 1 | D43: 2026-060 | E43: =SUMIFS(Children!$R$4:$R$500,Children!$B$4:$B$500,$A43,Children!$F$4:$F$500,"Enrolled",Children!$G$4:$G$500,"JAN-2026") -> 434.5 | F43: =SUMIFS(Receipts!$B$4:$B$600,Receipts!$G$4:$G$600,$A43,Receipts!$E$4:$E$600,"JAN-2026") -> 434.5 | G43: =$E43-$F43 -> 0 | H43: =IF($E43=0,"no charge",IF($F43<=0,"unpaid",IF(ABS($G43)<=0.5,"settled",IF($G43>0,"part paid","overpaid")))) -> settled | I43: =COUNTIFS(Receipts!$G$4:$G$600,$A43,Receipts!$E$4:$E$600,"JAN-2026") -> 1 | J43: 46053 | K43: =IF($G43>0.5,$B$2-Terms!$G$5,"") | L43: 060
A44: FAM-033 | B44: IBARRA | C44: 1 | D44: 2026-024 | E44: =SUMIFS(Children!$R$4:$R$500,Children!$B$4:$B$500,$A44,Children!$F$4:$F$500,"Enrolled",Children!$G$4:$G$500,"JAN-2026") -> 434.5 | F44: =SUMIFS(Receipts!$B$4:$B$600,Receipts!$G$4:$G$600,$A44,Receipts!$E$4:$E$600,"JAN-2026") -> 434.5 | G44: =$E44-$F44 -> 0 | H44: =IF($E44=0,"no charge",IF($F44<=0,"unpaid",IF(ABS($G44)<=0.5,"settled",IF($G44>0,"part paid","overpaid")))) -> settled | I44: =COUNTIFS(Receipts!$G$4:$G$600,$A44,Receipts!$E$4:$E$600,"JAN-2026") -> 1 | J44: 46112 | K44: =IF($G44>0.5,$B$2-Terms!$G$5,"") | L44: 2026-024 | M44: 1 receipt(s) in Review name this family
A45: FAM-034 | B45: JANKOWSKI | C45: 1 | D45: 2026-025 | E45: =SUMIFS(Children!$R$4:$R$500,Children!$B$4:$B$500,$A45,Children!$F$4:$F$500,"Enrolled",Children!$G$4:$G$500,"JAN-2026") -> 434.5 | F45: =SUMIFS(Receipts!$B$4:$B$600,Receipts!$G$4:$G$600,$A45,Receipts!$E$4:$E$600,"JAN-2026") -> 434.5 | G45: =$E45-$F45 -> 0 | H45: =IF($E45=0,"no charge",IF($F45<=0,"unpaid",IF(ABS($G45)<=0.5,"settled",IF($G45>0,"part paid","overpaid")))) -> settled | I45: =COUNTIFS(Receipts!$G$4:$G$600,$A45,Receipts!$E$4:$E$600,"JAN-2026") -> 2 | J45: 46121 | K45: =IF($G45>0.5,$B$2-Terms!$G$5,"") | L45: 2026025 | 2nd payment
A46: FAM-035 | B46: KACZMAREK | C46: 3 | D46: 2026-026 | E46: =SUMIFS(Children!$R$4:$R$500,Children!$B$4:$B$500,$A46,Children!$F$4:$F$500,"Enrolled",Children!$G$4:$G$500,"JAN-2026") -> 1041 | F46: =SUMIFS(Receipts!$B$4:$B$600,Receipts!$G$4:$G$600,$A46,Receipts!$E$4:$E$600,"JAN-2026") -> 1041 | G46: =$E46-$F46 -> 0 | H46: =IF($E46=0,"no charge",IF($F46<=0,"unpaid",IF(ABS($G46)<=0.5,"settled",IF($G46>0,"part paid","overpaid")))) -> settled | I46: =COUNTIFS(Receipts!$G$4:$G$600,$A46,Receipts!$E$4:$E$600,"JAN-2026") -> 1 | J46: 46138 | K46: =IF($G46>0.5,$B$2-Terms!$G$5,"") | L46: 2026026
A47: FAM-037 | B47: LACHAPELLE | C47: 2 | D47: 2026-028 | E47: =SUMIFS(Children!$R$4:$R$500,Children!$B$4:$B$500,$A47,Children!$F$4:$F$500,"Enrolled",Children!$G$4:$G$500,"JAN-2026") -> 774.5 | F47: =SUMIFS(Receipts!$B$4:$B$600,Receipts!$G$4:$G$600,$A47,Receipts!$E$4:$E$600,"JAN-2026") -> 774.5 | G47: =$E47-$F47 -> 0 | H47: =IF($E47=0,"no charge",IF($F47<=0,"unpaid",IF(ABS($G47)<=0.5,"settled",IF($G47>0,"part paid","overpaid")))) -> settled | I47: =COUNTIFS(Receipts!$G$4:$G$600,$A47,Receipts!$E$4:$E$600,"JAN-2026") -> 2 | J47: 46135 | K47: =IF($G47>0.5,$B$2-Terms!$G$5,"") | L47: 2026-028 | LACHAP2026-028
A48: FAM-038 | B48: LINDQVIST | C48: 2 | D48: 2026-029 | E48: =SUMIFS(Children!$R$4:$R$500,Children!$B$4:$B$500,$A48,Children!$F$4:$F$500,"Enrolled",Children!$G$4:$G$500,"JAN-2026") -> 799.5 | F48: =SUMIFS(Receipts!$B$4:$B$600,Receipts!$G$4:$G$600,$A48,Receipts!$E$4:$E$600,"JAN-2026") -> 799.5 | G48: =$E48-$F48 -> 0 | H48: =IF($E48=0,"no charge",IF($F48<=0,"unpaid",IF(ABS($G48)<=0.5,"settled",IF($G48>0,"part paid","overpaid")))) -> settled | I48: =COUNTIFS(Receipts!$G$4:$G$600,$A48,Receipts!$E$4:$E$600,"JAN-2026") -> 1 | J48: 46087 | K48: =IF($G48>0.5,$B$2-Terms!$G$5,"") | L48: LINDQVIST FRENCH SCHO
A49: FAM-039 | B49: MAALOUF | C49: 2 | D49: 2026-030 | E49: =SUMIFS(Children!$R$4:$R$500,Children!$B$4:$B$500,$A49,Children!$F$4:$F$500,"Enrolled",Children!$G$4:$G$500,"JAN-2026") -> 774.5 | F49: =SUMIFS(Receipts!$B$4:$B$600,Receipts!$G$4:$G$600,$A49,Receipts!$E$4:$E$600,"JAN-2026") -> 774.5 | G49: =$E49-$F49 -> 0 | H49: =IF($E49=0,"no charge",IF($F49<=0,"unpaid",IF(ABS($G49)<=0.5,"settled",IF($G49>0,"part paid","overpaid")))) -> settled | I49: =COUNTIFS(Receipts!$G$4:$G$600,$A49,Receipts!$E$4:$E$600,"JAN-2026") -> 2 | J49: 46063 | K49: =IF($G49>0.5,$B$2-Terms!$G$5,"") | L49: 2nd payment | MAALOU2026-030
A50: FAM-040 | B50: MARCHETTI | C50: 1 | D50: 2026-031 | E50: =SUMIFS(Children!$R$4:$R$500,Children!$B$4:$B$500,$A50,Children!$F$4:$F$500,"Enrolled",Children!$G$4:$G$500,"JAN-2026") -> 434.5 | F50: =SUMIFS(Receipts!$B$4:$B$600,Receipts!$G$4:$G$600,$A50,Receipts!$E$4:$E$600,"JAN-2026") -> 434.5 | G50: =$E50-$F50 -> 0 | H50: =IF($E50=0,"no charge",IF($F50<=0,"unpaid",IF(ABS($G50)<=0.5,"settled",IF($G50>0,"part paid","overpaid")))) -> settled | I50: =COUNTIFS(Receipts!$G$4:$G$600,$A50,Receipts!$E$4:$E$600,"JAN-2026") -> 1 | J50: 46086 | K50: =IF($G50>0.5,$B$2-Terms!$G$5,"") | L50: 2026-031
A51: FAM-041 | B51: NAKASHIMA | C51: 1 | D51: 2026-032 | E51: =SUMIFS(Children!$R$4:$R$500,Children!$B$4:$B$500,$A51,Children!$F$4:$F$500,"Enrolled",Children!$G$4:$G$500,"JAN-2026") -> 434.5 | F51: =SUMIFS(Receipts!$B$4:$B$600,Receipts!$G$4:$G$600,$A51,Receipts!$E$4:$E$600,"JAN-2026") -> 434.5 | G51: =$E51-$F51 -> 0 | H51: =IF($E51=0,"no charge",IF($F51<=0,"unpaid",IF(ABS($G51)<=0.5,"settled",IF($G51>0,"part paid","overpaid")))) -> settled | I51: =COUNTIFS(Receipts!$G$4:$G$600,$A51,Receipts!$E$4:$E$600,"JAN-2026") -> 1 | J51: 46063 | K51: =IF($G51>0.5,$B$2-Terms!$G$5,"") | L51: 2026-032
A52: FAM-043 | B52: NWACHUKWU | C52: 1 | D52: 2026-033 | E52: =SUMIFS(Children!$R$4:$R$500,Children!$B$4:$B$500,$A52,Children!$F$4:$F$500,"Enrolled",Children!$G$4:$G$500,"JAN-2026") -> 409.5 | F52: =SUMIFS(Receipts!$B$4:$B$600,Receipts!$G$4:$G$600,$A52,Receipts!$E$4:$E$600,"JAN-2026") -> 409.5 | G52: =$E52-$F52 -> 0 | H52: =IF($E52=0,"no charge",IF($F52<=0,"unpaid",IF(ABS($G52)<=0.5,"settled",IF($G52>0,"part paid","overpaid")))) -> settled | I52: =COUNTIFS(Receipts!$G$4:$G$600,$A52,Receipts!$E$4:$E$600,"JAN-2026") -> 1 | J52: 46069 | K52: =IF($G52>0.5,$B$2-Terms!$G$5,"") | L52: Giulia
A53: FAM-047 | B53: QUILLIAM | C53: 2 | D53: 2026-037 | E53: =SUMIFS(Children!$R$4:$R$500,Children!$B$4:$B$500,$A53,Children!$F$4:$F$500,"Enrolled",Children!$G$4:$G$500,"JAN-2026") -> 774.5 | F53: =SUMIFS(Receipts!$B$4:$B$600,Receipts!$G$4:$G$600,$A53,Receipts!$E$4:$E$600,"JAN-2026") -> 774.5 | G53: =$E53-$F53 -> 0 | H53: =IF($E53=0,"no charge",IF($F53<=0,"unpaid",IF(ABS($G53)<=0.5,"settled",IF($G53>0,"part paid","overpaid")))) -> settled | I53: =COUNTIFS(Receipts!$G$4:$G$600,$A53,Receipts!$E$4:$E$600,"JAN-2026") -> 1 | J53: 46070 | K53: =IF($G53>0.5,$B$2-Terms!$G$5,"") | L53: school fees
A54: FAM-049 | B54: ROCHETEAU | C54: 1 | D54: 2026-039 | E54: =SUMIFS(Children!$R$4:$R$500,Children!$B$4:$B$500,$A54,Children!$F$4:$F$500,"Enrolled",Children!$G$4:$G$500,"JAN-2026") -> 434.5 | F54: =SUMIFS(Receipts!$B$4:$B$600,Receipts!$G$4:$G$600,$A54,Receipts!$E$4:$E$600,"JAN-2026") -> 434.5 | G54: =$E54-$F54 -> 0 | H54: =IF($E54=0,"no charge",IF($F54<=0,"unpaid",IF(ABS($G54)<=0.5,"settled",IF($G54>0,"part paid","overpaid")))) -> settled | I54: =COUNTIFS(Receipts!$G$4:$G$600,$A54,Receipts!$E$4:$E$600,"JAN-2026") -> 1 | J54: 46121 | K54: =IF($G54>0.5,$B$2-Terms!$G$5,"") | L54: 039 | M54: 1 receipt(s) in Review name this family
A55: FAM-050 | B55: SANDOVAL | C55: 2 | D55: 2026-040 | E55: =SUMIFS(Children!$R$4:$R$500,Children!$B$4:$B$500,$A55,Children!$F$4:$F$500,"Enrolled",Children!$G$4:$G$500,"JAN-2026") -> 774.5 | F55: =SUMIFS(Receipts!$B$4:$B$600,Receipts!$G$4:$G$600,$A55,Receipts!$E$4:$E$600,"JAN-2026") -> 774.5 | G55: =$E55-$F55 -> 0 | H55: =IF($E55=0,"no charge",IF($F55<=0,"unpaid",IF(ABS($G55)<=0.5,"settled",IF($G55>0,"part paid","overpaid")))) -> settled | I55: =COUNTIFS(Receipts!$G$4:$G$600,$A55,Receipts!$E$4:$E$600,"JAN-2026") -> 1 | J55: 46118 | K55: =IF($G55>0.5,$B$2-Terms!$G$5,"") | L55: 2026-040
A56: FAM-051 | B56: SIGURDSSON | C56: 2 | D56: 2026-041 | E56: =SUMIFS(Children!$R$4:$R$500,Children!$B$4:$B$500,$A56,Children!$F$4:$F$500,"Enrolled",Children!$G$4:$G$500,"JAN-2026") -> 749.5 | F56: =SUMIFS(Receipts!$B$4:$B$600,Receipts!$G$4:$G$600,$A56,Receipts!$E$4:$E$600,"JAN-2026") -> 749.5 | G56: =$E56-$F56 -> 0 | H56: =IF($E56=0,"no charge",IF($F56<=0,"unpaid",IF(ABS($G56)<=0.5,"settled",IF($G56>0,"part paid","overpaid")))) -> settled | I56: =COUNTIFS(Receipts!$G$4:$G$600,$A56,Receipts!$E$4:$E$600,"JAN-2026") -> 2 | J56: 46083 | K56: =IF($G56>0.5,$B$2-Terms!$G$5,"") | L56: 2026041 | 2nd payment
A57: FAM-052 | B57: THIBODEAUX | C57: 1 | D57: 2026-042 | E57: =SUMIFS(Children!$R$4:$R$500,Children!$B$4:$B$500,$A57,Children!$F$4:$F$500,"Enrolled",Children!$G$4:$G$500,"JAN-2026") -> 409.5 | F57: =SUMIFS(Receipts!$B$4:$B$600,Receipts!$G$4:$G$600,$A57,Receipts!$E$4:$E$600,"JAN-2026") -> 409.5 | G57: =$E57-$F57 -> 0 | H57: =IF($E57=0,"no charge",IF($F57<=0,"unpaid",IF(ABS($G57)<=0.5,"settled",IF($G57>0,"part paid","overpaid")))) -> settled | I57: =COUNTIFS(Receipts!$G$4:$G$600,$A57,Receipts!$E$4:$E$600,"JAN-2026") -> 2 | J57: 46094 | K57: =IF($G57>0.5,$B$2-Terms!$G$5,"") | L57: Thibodeaux 2nd | Thibodeaux fees
A58: FAM-054 | B58: UCHENDU | C58: 1 | D58: 2026-044 | E58: =SUMIFS(Children!$R$4:$R$500,Children!$B$4:$B$500,$A58,Children!$F$4:$F$500,"Enrolled",Children!$G$4:$G$500,"JAN-2026") -> 434.5 | F58: =SUMIFS(Receipts!$B$4:$B$600,Receipts!$G$4:$G$600,$A58,Receipts!$E$4:$E$600,"JAN-2026") -> 434.5 | G58: =$E58-$F58 -> 0 | H58: =IF($E58=0,"no charge",IF($F58<=0,"unpaid",IF(ABS($G58)<=0.5,"settled",IF($G58>0,"part paid","overpaid")))) -> settled | I58: =COUNTIFS(Receipts!$G$4:$G$600,$A58,Receipts!$E$4:$E$600,"JAN-2026") -> 1 | J58: 46140 | K58: =IF($G58>0.5,$B$2-Terms!$G$5,"") | L58: 2026-044
A59: FAM-055 | B59: VANTERPOOL | C59: 1 | D59: 2026-045 | E59: =SUMIFS(Children!$R$4:$R$500,Children!$B$4:$B$500,$A59,Children!$F$4:$F$500,"Enrolled",Children!$G$4:$G$500,"JAN-2026") -> 434.5 | F59: =SUMIFS(Receipts!$B$4:$B$600,Receipts!$G$4:$G$600,$A59,Receipts!$E$4:$E$600,"JAN-2026") -> 434.5 | G59: =$E59-$F59 -> 0 | H59: =IF($E59=0,"no charge",IF($F59<=0,"unpaid",IF(ABS($G59)<=0.5,"settled",IF($G59>0,"part paid","overpaid")))) -> settled | I59: =COUNTIFS(Receipts!$G$4:$G$600,$A59,Receipts!$E$4:$E$600,"JAN-2026") -> 1 | J59: 46029 | K59: =IF($G59>0.5,$B$2-Terms!$G$5,"") | L59: Halima
A60: FAM-057 | B60: WENDELIN | C60: 1 | D60: 2026-047 | E60: =SUMIFS(Children!$R$4:$R$500,Children!$B$4:$B$500,$A60,Children!$F$4:$F$500,"Enrolled",Children!$G$4:$G$500,"JAN-2026") -> 434.5 | F60: =SUMIFS(Receipts!$B$4:$B$600,Receipts!$G$4:$G$600,$A60,Receipts!$E$4:$E$600,"JAN-2026") -> 434.5 | G60: =$E60-$F60 -> 0 | H60: =IF($E60=0,"no charge",IF($F60<=0,"unpaid",IF(ABS($G60)<=0.5,"settled",IF($G60>0,"part paid","overpaid")))) -> settled | I60: =COUNTIFS(Receipts!$G$4:$G$600,$A60,Receipts!$E$4:$E$600,"JAN-2026") -> 1 | J60: 46114 | K60: =IF($G60>0.5,$B$2-Terms!$G$5,"") | L60: 2026-047
A61: FAM-058 | B61: WOJCIECHOWSKI | C61: 1 | D61: 2026-048 | E61: =SUMIFS(Children!$R$4:$R$500,Children!$B$4:$B$500,$A61,Children!$F$4:$F$500,"Enrolled",Children!$G$4:$G$500,"JAN-2026") -> 434.5 | F61: =SUMIFS(Receipts!$B$4:$B$600,Receipts!$G$4:$G$600,$A61,Receipts!$E$4:$E$600,"JAN-2026") -> 434.5 | G61: =$E61-$F61 -> 0 | H61: =IF($E61=0,"no charge",IF($F61<=0,"unpaid",IF(ABS($G61)<=0.5,"settled",IF($G61>0,"part paid","overpaid")))) -> settled | I61: =COUNTIFS(Receipts!$G$4:$G$600,$A61,Receipts!$E$4:$E$600,"JAN-2026") -> 1 | J61: 46077 | K61: =IF($G61>0.5,$B$2-Terms!$G$5,"") | L61: 048
A62: FAM-059 | B62: YANKOVIC | C62: 1 | D62: 2026-049 | E62: =SUMIFS(Children!$R$4:$R$500,Children!$B$4:$B$500,$A62,Children!$F$4:$F$500,"Enrolled",Children!$G$4:$G$500,"JAN-2026") -> 409.5 | F62: =SUMIFS(Receipts!$B$4:$B$600,Receipts!$G$4:$G$600,$A62,Receipts!$E$4:$E$600,"JAN-2026") -> 409.5 | G62: =$E62-$F62 -> 0 | H62: =IF($E62=0,"no charge",IF($F62<=0,"unpaid",IF(ABS($G62)<=0.5,"settled",IF($G62>0,"part paid","overpaid")))) -> settled | I62: =COUNTIFS(Receipts!$G$4:$G$600,$A62,Receipts!$E$4:$E$600,"JAN-2026") -> 1 | J62: 46064 | K62: =IF($G62>0.5,$B$2-Terms!$G$5,"") | L62: Yankovic
A63: FAM-060 | B63: ZABALA | C63: 2 | D63: 2026-050 | E63: =SUMIFS(Children!$R$4:$R$500,Children!$B$4:$B$500,$A63,Children!$F$4:$F$500,"Enrolled",Children!$G$4:$G$500,"JAN-2026") -> 749.5 | F63: =SUMIFS(Receipts!$B$4:$B$600,Receipts!$G$4:$G$600,$A63,Receipts!$E$4:$E$600,"JAN-2026") -> 749.5 | G63: =$E63-$F63 -> 0 | H63: =IF($E63=0,"no charge",IF($F63<=0,"unpaid",IF(ABS($G63)<=0.5,"settled",IF($G63>0,"part paid","overpaid")))) -> settled | I63: =COUNTIFS(Receipts!$G$4:$G$600,$A63,Receipts!$E$4:$E$600,"JAN-2026") -> 2 | J63: 46182 | K63: =IF($G63>0.5,$B$2-Terms!$G$5,"") | L63: 2026-050 | Zabala 2nd
A64: FAM-008 | B64: BELHADJ | C64: 2 | D64: 2026-008 | E64: =SUMIFS(Children!$R$4:$R$500,Children!$B$4:$B$500,$A64,Children!$F$4:$F$500,"Enrolled",Children!$G$4:$G$500,"JAN-2026") -> 774.5 | F64: =SUMIFS(Receipts!$B$4:$B$600,Receipts!$G$4:$G$600,$A64,Receipts!$E$4:$E$600,"JAN-2026") -> 1184 | G64: =$E64-$F64 -> -409.5 | H64: =IF($E64=0,"no charge",IF($F64<=0,"unpaid",IF(ABS($G64)<=0.5,"settled",IF($G64>0,"part paid","overpaid")))) -> overpaid | I64: =COUNTIFS(Receipts!$G$4:$G$600,$A64,Receipts!$E$4:$E$600,"JAN-2026") -> 1 | J64: 46042 | K64: =IF($G64>0.5,$B$2-Terms!$G$5,"") | L64: 2026-008 | M64: 2 receipt(s) in Review name this family
